Workbook
Name ฉ141: RRP_1_V4_Sep25!$A$1
Name ธ160: 'Bond Buy-Sell_V4_Sep25 + Oct25'!$C$8

Sheet All Table
A2: Counterparty_Master | C2: Yellow means updated per our disscussion as of 3 Oct
A4: This table serves as the single, authoritative repository for all external and internal entities with which the bank conducts treasury business.
A6: Column Name | B6: Data Type | C6: Description | D6: Example
A7: counterparty_id | B7: INT | C7: Unique system-generated identifier for the counterparty. | D7: 101
A8: LegalName | B8: VARCHAR(255) | C8: The full legal name of the entity. | D8: Bangkok Bank PCL
A9: ShortCode | B9: VARCHAR(50) | C9: A short, unique code used for quick identification in user interfaces. | D9: BBL
A10: CounterpartyType | B10: VARCHAR(50) | C10: Type of counterparty (e.g., 'Commercial Bank', 'SOE', 'Corporate', 'Central Bank'). | D10: Commercial Bank
A11: BANK_CODE | B11: VARCHAR(11) | C11: Official identifier assigned by the Bank of Thailand. | D11: 2
A12: SWIFT_BIC | B12: VARCHAR(11) | C12: The counterparty's Business Identifier Code for SWIFT messaging. | D12: BKKBTHBK
A13: PrimaryCreditRating | B13: VARCHAR(10) | C13: The primary credit rating from the designated agency. | D13: AA+
A14: PrimaryRatingAgency | B14: VARCHAR(50) | C14: The name of the primary credit rating agency (e.g., 'Fitch', 'TRIS Rating'). | D14: TRIS Rating
A15: PrimaryRatingDate | B15: DATE | C15: The date the primary rating was assigned or last updated. | D15: 45853
A16: GMRA_AgreementID | B16: INT | C16: Links to a master table of legal agreements, crucial for REPO trades. | D16: 56
A17: CreatedDate | B17: DATE | C17: Timestamp of record creation for audit purposes. | D17: 45301
A18: LastUpdatedDate | B18: DATE | C18: Timestamp of the last update for audit purposes. | D18: 45853
A20: Security_Master
A22: This table is a comprehensive catalog of every financial instrument the bank can trade or hold, aligned with standards from the Thai Bond Market Association (ThaiBMA).
A24: Column Name | B24: Data Type | C24: Description | D24: Example | E24: Remark
A25: SecurityID | B25: INT | C25: Unique system-generated identifier for the security. | D25: 5010
A26: ISIN | B26: VARCHAR(12) | C26: International Securities Identification Number. | D26: TH0623038C09
A27: ThaiBMA_Symbol | B27: VARCHAR(10) | C27: The official trading symbol used by ThaiBMA. | D27: LB28DA
A28: IssuerID | B28: INT | C28: Identify the issuer. | D28: 1 (Govt of Thailand)
A29: UniqueID | B29: VARCHAR(20) | C29: ID for BOT report | D29: 176015 (Ministry of Finance),176017(State own enterprise),001(Bank of Thailand) | E29: https://www.bot.or.th/th/our-services/data-acquisition-publication/da-and-standard/standard-code.html
A30: InstrumentType | B30: VARCHAR(20) | C30: The type of instrument (e.g., 'T-Bill', 'Gov Bond', 'Corp Bond', 'SOE Bond', 'BOT Bond'). | D30: Gov Bond
A31: IssueDate | B31: DATE | C31: The date the security was issued. | D31: 43451
A32: MaturityDate | B32: DATE | C32: The date the security matures. | D32: 47104
A33: CouponRate | B33: DECIMAL(10,6) | C33: The nominal coupon rate. Null for zero-coupon bonds. | D33: 2.75 | E33: ถ้าเป็น floating ให้ใส่ coupon rate ล่าสุด
A34: CouponFrequency | B34: VARCHAR(20) | C34: Frequency of coupon payments (e.g., 'Semi-Annual', 'Quarterly'). | D34: Semi-Annual
A35: DayCountConvention | B35: VARCHAR(20) | C35: The convention for calculating accrued interest (e.g., 'Actual/365'). 1 | D35: Actual/365
A36: Currency | B36: VARCHAR(3) | C36: ISO 4217 currency code. | D36: THB
A37: Country | B37: VARCHAR(3) | C37: Country Code | D37: TH
A38: BondStructure | B38: VARCHAR(20) | C38: Structure of principal repayment (e.g., "ZERO", 'Bullet', 'Amortizing'). | D38: Bullet
A39: IsEligibleBOT_RepoCollateral | B39: BOOLEAN | C39: Flag indicating if the security is eligible for use in BOT's repo operations. | D39: TRUE
A40: IsEligibleCRM_Collateral | B40: BOOLEAN | C40: Flag indicating if the security meets BOT's criteria for Credit Risk Mitigation. 2 | D40: TRUE
A42: Portfolio_Master
A44: This table allows for the logical segregation of the bank's treasury positions according to their strategic intent.
A46: Column Name | B46: Data Type | C46: Description | D46: Example
A47: PortfolioID | B47: INT | C47: Unique system-generated identifier for the portfolio. | D47: 201
A48: PortfolioName | B48: VARCHAR(100) | C48: Clear accounting classification upfront (e.g., 'Amortized Cost', 'Fair Value through OCI', 'Fair Value through P&L (Trading Book)') along with Asset type (Gov, SOE, BOT, T-Bill) | D48: AMC - Govt Bonds
A49: PortfolioManager | B49: VARCHAR(100) | C49: The name or ID of the responsible manager or desk. | D49: John Doe
A50: AccountingTreatment | B50: VARCHAR(50) | C50: The accounting designation which dictates valuation and P&L recognition rules. | D50: FVOCI
A51: CreatedTimestamp | B51: DATETIME | C51: Timestamp of record creation. | D51: 45323.458
A53: Interbank_Deals
A55: This table records all interbank lending (placements) and borrowing (takings) transactions.
A57: Column Name | B57: Data Type | C57: Description | D57: Example
A58: DealID | B58: INT | C58: Unique identifier for the deal. | D58: 45001
A59: TradeDate | B59: DATETIME | C59: Date and time the deal was executed. | D59: 45905.438
A60: ValueDate | B60: DATE | C60: The start date of the loan/deposit. | D60: 45905
A61: MaturityDate | B61: DATE | C61: The end date of the loan/deposit. | D61: 45908
A62: DealType | B62: VARCHAR(10) | C62: Lend' or 'Borrow'. | D62: Lend
A63: counterparty_id | B63: INT | C63: Links to Counterparty_Master. | D63: 101
A64: PrincipalAmount | B64: DECIMAL(20,2) | C64: The nominal amount of the deal. | D64: 250000000
A65: Currency | B65: VARCHAR(3) | C65: Currency of the deal. | D65: THB
A66: InterestRateType | B66: VARCHAR(10) | C66: Fixed' or 'Floating'. | D66: Fixed
A67: InterestRate | B67: DECIMAL(10,6) | C67: The fixed interest rate. | D67: 2.25
A68: ReferenceRate | B68: VARCHAR(20) | C68: For floating rates (e.g., 'THOR'). | D68: NULL
A69: Margin | B69: DECIMAL(10,6) | C69: The spread over the reference rate. | D69: NULL
A70: DayCountConvention | B70: VARCHAR(20) | C70: The convention for calculating accrued interest (e.g., 'Actual/365'). 1 | D70: Actual/365
A71: AccruedInterest | B71: DECIMAL(20,2) | C71: The calculated interest accrued to date. | D71: 46232.88
A72: Status | B72: VARCHAR(20) | C72: Active', 'Matured', 'Defaulted'. | D72: Active
A73: Confirmation_Ref | B73: VARCHAR(50) | C73: Reference to the outgoing/incoming ISO 20022 confirmation. | D73: CONF-ISO-45001-20250905
A75: Repo_Trades
A77: This table captures the master details of each REPO or Reverse REPO transaction.
A79: Column Name | B79: Data Type | C79: Description | D79: Example
A80: RepoTradeID | B80: INT | C80: Unique identifier for the REPO trade. | D80: 7702
A81: TradeDate | B81: DATETIME | C81: Date and time the trade was executed. | D81: 45905.583
A82: TradeType | B82: VARCHAR(20) | C82: REPO' (lending securities) or 'Reverse REPO' (borrowing securities). | D82: REPO
A83: counterparty_id | B83: INT | C83: Links to Counterparty_Master. | D83: 215
A84: PurchaseDate | B84: DATE | C84: Start date of the REPO (first leg). | D84: 45908
A85: RepurchaseDate | B85: DATE | C85: End date of the REPO (second leg). | D85: 45915
A86: PurchasePrice | B86: DECIMAL(20,2) | C86: The cash amount exchanged on the purchase date. | D86: 100000000
A87: RepurchasePrice | B87: DECIMAL(20,2) | C87: The cash amount to be exchanged on the repurchase date. | D87: 1.0003836e+08
A88: InterestRateType | B88: VARCHAR(10) | C88: Fixed' or 'Floating'. | D88: Fixed
A89: InterestRate | B89: DECIMAL(10,6) | C89: The fixed interest rate. | D89: 2.25
A90: ReferenceRate | B90: VARCHAR(20) | C90: For floating rates (e.g., 'THOR'). | D90: NULL
A91: Margin | B91: DECIMAL(10,6) | C91: The spread over the reference rate. | D91: NULL
A92: DayCountConvention | B92: VARCHAR(20) | C92: The convention for calculating accrued interest (e.g., 'Actual/365'). 1 | D92: Actual/365
A93: RepoRate | B93: DECIMAL(10,6) | C93: The implied interest rate of the transaction. | D93: 2
A94: Term | B94: INT | C94: The term of the REPO in days. | D94: 7
A95: Status | B95: VARCHAR(20) | C95: Active', 'Matured', 'In-Default'. | D95: Active
A97: Collateral_Positions
A99: This is a child table to Repo_Trades, providing a granular log of all securities allocated as collateral for a specific trade.
A101: Column Name | B101: Data Type | C101: Description | D101: Example
A102: CollateralID | B102: INT | C102: Unique identifier for this specific collateral allocation. | D102: 9151
A103: RepoTradeID | B103: INT | C103: Links to the parent Repo_Trades record. | D103: 7702
A104: SecurityID | B104: INT | C104: Links to the specific security in Security_Master. | D104: 5015
A105: NominalAmount | B105: DECIMAL(20,2) | C105: The face value of the securities pledged. | D105: 102500000
A106: AllocationDate | B106: DATE | C106: The date this collateral was allocated to the trade. | D106: 45908
A107: ValuationPrice | B107: DECIMAL(18,6) | C107: The clean price used for valuation at the last MTM cycle. | D107: 100.1
A108: MarketValue | B108: DECIMAL(20,2) | C108: The calculated market value (Nominal * Price + Accrued). | D108: 102602500
A109: HaircutPercentage | B109: DECIMAL(5,2) | C109: The haircut applied, as per the master agreement or CRM rules. 2 | D109: 2
A110: CollateralValue_AfterHaircut | B110: DECIMAL(20,2) | C110: The final value of the collateral for margining purposes. | D110: 100550450
A111: MarginCallID | B111: INT | C111: Links to a margin call event table if this allocation was part of a margin call. | D111: NULL
A113: Bond_Trades
A115: This table records all outright purchases and sales of bonds for the bank's investment portfolios.
A117: Column Name | B117: Data Type | C117: Description | D117: Example | E117: Column 1 | F117: Column 2
A118: BondTradeID | B118: INT | C118: Unique identifier for the bond trade. | D118: 12301
A119: PortfolioID | B119: INT | C119: Links to Portfolio_Master to indicate which portfolio the trade belongs to. | D119: 201
A121: TradeDate | B121: DATETIME | C121: Date and time the trade was executed. | D121: 45905.625
A122: SettlementDate | B122: DATE | C122: The date for settlement (typically T+2 in Thailand). 1 | D122: 45909
...

Sheet Edit_control
A2: No. | B2: Log date | C2: Action / Next Step | D2: Table / Stage | E2: Priority | F2: Status | G2: Remarks / Rationale | H2: Link/Input
A3: 1 | B3: =DATE(2025,10,14) -> 45944 | C3: Create end-to-end mock-up for Bond Buy-Side flow (FVOCI & AMC, across Gov, T-Bill, BOT, SOE) to validate structure and data flow. | D3: Bond_Positions + Bond_Trades | E3: High | F3: Completed | G3: Ensures integration between trade booking → position build-up → valuation. Essential for walkthrough with stakeholders (accounting, treasury).
A4: 2 | B4: =DATE(2025,10,14) -> 45944 | C4: Create Bond_Positions table with required fields (per discussion on 3 Oct): • UnrealizedGainLoss • InterestRateType • ReferenceRate • Margin | D4: Bond_Positions | E4: High | F4: Completed | G4: - This is a core table for inventory, valuation, and reporting. Foundation for downstream EVE / accrual / accounting treatment. - This can be linked to BOT data set of investment portfolio required by YIP.
A5: 3 | B5: =DATE(2025,10,14) -> 45944 | C5: Add field "DayCountConvention" to Interbank_Deals (per discussion on 3 Oct) | D5: Interbank_Deals | E5: High | F5: Completed | G5: Needed for interest accrual and harmonization with bond instruments. Critical for consistent yield calculations and EVE linkage.
A6: =A5+1 -> 4 | B6: =DATE(2025,10,14) -> 45944 | C6: Add key rate fields to Repo_Trades (per discussion on 3 Oct): • InterestRateType • InterestRate • ReferenceRate • Margin | D6: Repo_Trades + Limit_Utilization | E6: High | F6: Completed | G6: Aligns with interbank & bond pricing logic. Enables consistent calculation engine.
A7: =A6+1 -> 5 | B7: =DATE(2025,10,14) -> 45944 | C7: Create mock-up scenario for Repo Transaction to test Limit Utilization logic: • Cover both placement and repo limit types • Include edge cases for limit direction & utilization calculation • Validate LimitType and UtilizationDirection fields in Limit_Utilization table | D7: Repo_Trades | E7: High | F7: Completed | G7: This is critical to verify how repo transactions interact with treasury placement/repo limits. Scenario should include breach cases and intra-day netting assumptions. Coordinate with Risk & Treasury for realistic cases.
A8: =A7+1 -> 6 | B8: =DATE(2025,10,14) -> 45944 | C8: Refine Field "PortfolioName" descriptions in Portfolio_Master to align with accounting classification (AMC, FVOCI) | D8: Portfolio_Master | E8: High | F8: Completed | G8: Improves clarity and reporting alignment. Useful for both system users and accounting interface.
A9: =A8+1 -> 7 | B9: =DATE(2025,10,14) -> 45944 | C9: Add limit fields to Limit_Utilization: • LimitType (Placement vs Repo) • UtilizationDirection | D9: Limit_Utilization | E9: High | F9: Completed | G9: Supports future dashboard and regulatory reporting. Not blocking core bond flow but useful for risk/limit monitoring.
A10: =A9+1 -> 8 | B10: =DATE(2025,10,14) -> 45944 | C10: Define approach for bond position valuation - TBC with Accounting team whether to apply FIFO vs Weighted Average method for cost layering.(using Weighted avg cost) - Initially, keep transaction-level (no netting) structure. | D10: Bond_Positions | E10: High | F10: Completed | G10: Impacts how realized/unrealized gains are tracked. Affects EVE and accounting treatment. Requires alignment with policy.
A11: =A10+1 -> 9 | B11: =DATE(2025,10,14) -> 45944 | C11: Link DiscountCurveID in bond position / valuation to Market Data table or curve repository (for EVE). | D11: Bond_Positions + Market Data | E11: High | F11: Not started | G11: Needed for IRRBB and scenario valuation. Can be implemented after base table structures are stable.
A12: =A11+1 -> 10 | B12: =DATE(2025,10,14) -> 45944 | C12: Create a unique results summary table as of 30 Sep 2025 to consolidate positions and trades. | D12: ALL | E12: High | F12: Completed | G12: Needed to validate cut-off balances and reconcile mock-up vs real data.
A13: =A12+1 -> 11 | B13: =DATE(2025,10,14) -> 45944 | C13: Refine Limit_Utilization table to show limit-level view per counterparty by limit type. | D13: Limit_Utilization | E13: High | F13: Completed | G13: Improves clarity of limit reporting and ensures alignment with regulatory dashboards.
A14: =A13+1 -> 12 | B14: =DATE(2025,10,14) -> 45944 | C14: Verify that all transactions after 30 Sep 2025 are correctly captured, so that the unique result table (No. 10) reflects accurate current activity. | D14: ALL | E14: High | F14: Completed | G14: Ensures completeness and accuracy of transaction capture beyond reporting cut-off for YIP's disscusion
A15: =A14+1 -> 13 | B15: =DATE(2025,10,14) -> 45944 | C15: To create the "Bond sell" mock up scenario | D15: ALL | E15: High | F15: Not started
A16: =A15+1 -> 14 | B16: =DATE(2025,10,14) -> 45944 | C16: To create the "Margin_call" master table | D16: ALL | E16: High | F16: Not started | G16: Ideally we can add field flag Collateral type = Bond, Cash (no haircut) to chek Moody's table - HQLA whether if margin call is cash , Find the BOT notificaiton and pending CSA_Margin Repo table whether it can able contain morethan 2 collatertal
A17: =A16+1 -> 15 | B17: =DATE(2025,10,18) -> 45948 | C17: P'Yut to provide Hair cut repo the market practice BOT | D17: ALL | E17: High | F17: Completed | G17: for repo case of collateral | H17: ประกาศธนาคารแห่งประเทศไทย - ที่ สกง. 1 /2556
A18: =A17+1 -> 16 | B18: =DATE(2025,10,28) -> 45958 | C18: Create Bond_Positions_Realization_Cost table to serve realized/unrealized gain/loss | D18: ALL | E18: High | F18: Not started
A19: =A18+1 -> 17 | B19: =DATE(2025,10,29) -> 45959 | C19: Added FI_CODE from BOT website in Sheet 'BANK_CODE' for references | D19: ALL | E19: High | F19: Completed
A20: =A19+1 -> 18 | B20: =DATE(2025,10,29) -> 45959 | C20: Added Netting agreement table for Moodys database | D20: ALL | E20: High | F20: Completed

Sheet Stage_master
A1: No. | B1: Stage_master | C1: Description | D1: TableType | E1: DataNature | F1: DataNature note | I1: Event | J1: Impact to..
A2: 1 | B2: ='All Table_V4_Clean'!A3 -> entity_master | C2: ='All Table_V4_Clean'!A4 -> This table represents the authoritative, enterprise-wide obligor registry. It stores the top-level identity of each customer group, legal entity, or economic group used for credit risk, Basel, TFRS 9, Moody’s mapping, and BOT DER_CPEN.Entity Id. | D2: Master | E2: Static | F2: Maintained by Credit Risk / KYC teams; changes infrequently except for rating updates, group restructuring, or regulatory classification changes. | I2: update MTM from ThaiBMA
A3: =A2+1 -> 2 | B3: ='All Table_V4_Clean'!A21 -> counterparty_master | C3: ='All Table_V4_Clean'!A22 -> This table serves as the single, authoritative repository for all external and internal entities with which the bank conducts treasury business. | D3: Master | E3: Static | F3: Updated manually by KYC / customer on-boarding and credit teams. | I3: update accru int daily
A4: =A3+1 -> 3 | B4: ='All Table_V4_Clean'!A42 -> security_master | C4: This table is a comprehensive catalog of every financial instrument the bank can trade or hold, aligned with standards from the Thai Bond Market Association (ThaiBMA). | D4: Master | E4: Static | F4: Updated manually from ThaiBMA / market data feeds when new issues are added or terms change. | I4: update margin call
A5: =A4+1 -> 4 | B5: ='All Table_V4_Clean'!A70 -> portfolio_master | C5: This table allows for the logical segregation of the bank's treasury positions according to their strategic intent. | D5: Master | E5: Static | F5: Rarely changes; configuration-driven (set up by Treasury/Accounting policy). | I5: update maturity
A6: =A5+1 -> 5 | B6: ='All Table_V4_Clean'!A80 -> netting_agreement | C6: This table contains the master information for all legally enforceable netting and collateral agreements (e.g., ISDA, GMRA) established between the institution and its counterparties. Each record defines the scope, effective period, and key legal attributes governing how financial transactions (e.g., swaps, repos, FX, securities lending) are netted, margined, and settled. | D6: Master | E6: Static | F6: Legal data, created or amended infrequently when agreements are executed, amended, or terminated. | I6: coupon payment
A7: =A6+1 -> 6 | B7: ='All Table_V4_Clean'!A100 -> interbank_deals | C7: This table records all interbank lending (placements) and borrowing (takings) transactions. | D7: Transaction | E7: Event-driven | F7: Daily deal capture from treasury dealing systems (front office). | I7: floating rate reprice
A8: =A7+1 -> 7 | B8: ='All Table_V4_Clean'!A129 -> interbank_interest_schedule | C8: This child table maintains the interest period schedule (floating) and reset details for each interbank lending or borrowing deal recorded in the Interbank_Deals table. Each record represents a single interest accrual period, storing the applicable benchmark rate, margin, effective interest rate, and accrued interest for that specific period. | D8: Transaction (Child) | E8: Derived | F8: System-generated and updated from Interbank_Deals; adjusted on rate reset, accrual runs, and at period close. | I8: Input deal buy sell lend borrow | J8: cost & Realized P/L
A9: =A8+1 -> 8 | B9: ='All Table_V4_Clean'!A142 -> repo_trades | C9: This table captures the master details of each REPO or Reverse REPO transaction. | D9: Transaction | E9: Event-driven | F9: Daily capture of new repo / reverse repo deals, linked to collateral and margining.
A10: =A9+1 -> 9 | B10: ='All Table_V4_Clean'!A173 -> collateral_positions | C10: This is a child table to Repo_Trades, providing a granular log of all securities allocated as collateral for a specific trade. | D10: Transaction (Child) | E10: Event-driven | F10: Updated when repo trades are booked, collateral is allocated/substituted, or positions roll/mature.
A11: =A10+1 -> 10 | B11: ='All Table_V4_Clean'!A189 -> bond_trades | C11: This table records all outright purchases and sales of bonds for the bank's investment portfolios. | D11: Transaction | E11: Event-driven | F11: Populated by trade capture from dealing systems; each record is a buy/sell event.
A12: =A11+1 -> 11 | B12: ='All Table_V4_Clean'!A205 -> bond_transactions | C12: This table captures all bond trading activities at the transaction level executed by the bank across its investment and trading portfolios. Each record represents a single trade event, providing full details of the commercial terms, settlement information, pricing attributes, coupon characteristics, and valuation data associated with that transaction. | D12: Transaction | E12: Event-driven | F12: Detailed trade-level event store; may be sourced from multiple front-office systems and normalized here.
A13: =A12+1 -> 12 | B13: ='All Table_V4_Clean'!A240 -> bond_positions | C13: This table maintains the current holding details for each bond investment. Each row represents a unique position in a bond under a specific portfolio. | D13: Position | E13: Derived | F13: Derived from Bond_Transactions / Bond_Trades via end-of-day position building and lifecycle events (buys, sells, transfers, maturities).
A14: =A13+1 -> 13 | B14: ='All Table_V4_Clean'!A268 -> position_costing | C14: This table maintains the current cost basis and realized P&L state for each active bond position. Each record represents the aggregated weighted-average cost (WAC) of all buy transactions linked to a position, as well as the cumulative realized gain/loss from any partial disposals. The table is updated whenever a buy or sell transaction occurs. It supports valuation, accounting, and audit purposes by preserving a clear linkage between trade events, cost accumulation, and realized results. | D14: Analytical | E14: Derived | F14: Updated by the costing engine whenever trades (buys/sells/transfers) affect the position’s cost basis or realized P&L.
A15: =A14+1 -> 14 | B15: ='All Table_V4_Clean'!A282 -> position_realization_events | C15: This table serves as an immutable journal of realized P&L events for bond positions. Each record represents a single realization event (e.g., a sale or transfer-out) capturing the clean-price differential between the sale and the weighted-average cost at that time. | D15: Journal | E15: Event-driven | F15: Appended when a realization event occurs; never updated or deleted (immutable audit log).
A16: =A15+1 -> 15 | B16: ='All Table_V4_Clean'!A298 -> margin_calls | C16: This table records all daily margin call events arising from collateralized trading relationships such as repo, reverse repo, and OTC derivative agreements (e.g., GMRA, ISDA). Each record represents a calculated margin requirement based on mark-to-market exposure as of a specific valuation date, adjusted for thresholds, minimum transfer amounts (MTA), and rounding rules. The table provides a clear workflow and audit trail from exposure calculation through to margin agreement, settlement, and reconciliation. | D16: Control | E16: Derived | F16: Calculated by the margin engine from exposure and collateral data at each valuation date; workflow-driven (Pending → Agreed → Settled).
A17: =A16+1 -> 16 | B17: ='All Table_V4_Clean'!A313 -> cash_margin_movements | C17: This table records all cash-based collateral (margin) movements exchanged between the institution and its counterparties under collateralized agreements such as GMRA (Repo / Reverse Repo). It represents the cash-side lifecycle of margining, acting as the operational mirror of exposure and margin call calculations. Each row captures a single cash event—posting, receiving, returning, or adjusting margin—and provides a full audit trail from margin call through settlement and reconciliation. The table also maintains a running outstanding margin balance per margin_call_id and supports the accrual of interest receivable on cash margin that we have posted (typical Repo case), in accordance with GMRA terms. | D17: Journal / Transaction | E17: Event-driven | F17: Populated when margin cash is instructed/settled (BAHTNET/SWIFT); used for cash & collateral reconciliation.
A18: =A17+1 -> 17 | B18: ='All Table_V4_Clean'!A336 -> limit_utilization | C18: This table provides an immutable, auditable log of every transaction that impacts a credit limit, enabling true pre-trade and post-trade limit checking. | D18: Control | E18: Event-driven | F18: Updated whenever exposures change (new trades, maturities, margining, adjustments); supports limit monitoring and MIS.
A19: =A18+1 -> 18 | B19: ='All Table_V4_Clean'!A352 -> entity_counterparty | C19: ='All Table_V4_Clean'!A353 -> This table defines which counterparties are linked to which entity (obligor group) and which parent limit they are allowed to use. ใช้เก็บ mapping ว่า Entity ID ประกอบด้วย Counterparty ID อะไรบ้าง และทุกตัวใช้วงเงิน Parent ใดร่วมกัน | D19: Master | E19: Static | F19: Updated when group structures change, when counterparties are added/removed, or when shared limit assignments are revised. Used for mapping Entity → Counterparty → Parent Limit for group-level limit enforcement.
B24: Event type to update data in table | C24: Related Table | D24: Department in Charge
B25: Create new Counterparty input | C25: counterparty_master, entity_master, entity_counterparty | D25: Back Office
B26: Create new Security input(Reverse REPO,Bond Buy) | C26: security_master | D26: Back Office
B27: Credit limit update & newly add | C27: limit_utilization | D27: Back Office
B28: REPO setup GMRA
B29: update MTM from ThaiBMA | D29: Back Office
B30: update accru int daily
B31: update margin call
B32: update maturity
B33: coupon payment
B34: floating rate reprice
B35: Input deal buy sell lend borrow

Sheet Accouting QA
A1: # | B1: Q | C1: Ans as of 24 Nov
A2: 1 | B2: สามารถใช้ตัว Accrued Interest ที่ ThaiBMA report (mark-to-market) มาโดยตรงได้ไหมสำหรับการรายงานบัญชี หรือจะต้องปรับอะไรเพิ่ม? | C2: Pending Acc team to check
A3: 2 | B3: Flow การ reconcile ระหว่าง Treasury → ThaiBMA → Accounting GL ต้องใช้ข้อมูลอะไรบ้าง และ format ไหน | C3: Pending Acc team to check
A4: 3 | B4: Journal entries ที่ทีมบัญชีใช้สำหรับการรับรู้ / ปิดบัญชี / reversal ของดอกเบี้ยค้างรับเป็นอย่างไร
A9: Step | B9: Owner | C9: Output
A10: Accrued calculation (ThaiBMA / Treasury System) feed daily to Datamart | B10: Treasury | C10: Position-level accrued interest
A11: Mapping classification (FVOCI, AC, FVTPL) | B11: Accounting | C11: Classification logic
A12: GL Posting (Journal Entry) | B12: Accounting | C12: P&L + BS impact
A13: Reconciliation | B13: Treasury + Accounting | C13: Break-down and adjustments
A14: Reporting (FS, BOT, Management) | B14: Accounting | C14: Final consolidation

Sheet Sheet39
A4: No. | B4: Event | C4: Product | D4: Source of data | E4: Impact to..
E5: Table | F5: Field
A6: 1 | B6: update MTM from ThaiBMA | C6: Bond | D6: Thai BMA website | E6: bond_trades | F6: clean_price_trade
C7: Bond | D7: Thai BMA website | E7: bond_transactions | F7: clean_price_trade | G7: clean_price | H7: accrued_interest | I7: dirty_price
C8: Bond | D8: Thai BMA website | E8: position_realization_events | F8: sell_clean_price_pct
C9: Bond | D9: Thai BMA website | E9: bond_positions | F9: avg_book_clean_price_pct | G9: clean_price | H9: accrued_interest | I9: dirty_price
C10: Bond | D10: Thai BMA website | E10: Collateral_Positions | F10: market_value
A12: 2 | B12: update accrued interest income daily | C12: Bond | D12: Thai BMA website | E12: bond_transactions | F12: accrued_interest
C13: Bond | D13: Thai BMA website | E13: bond_positions | F13: accrued_interest
C14: Interbank lending/borrowing | D14: Treasury System Database | E14: interbank_deals | F14: accrued_interest
A16: 3 | B16: update margin call daily | C16: Bond | D16: Thai BMA website | E16: Collateral_Positions | F16: market_value
C17: Reverse repo/Repo | D17: Treasury System Database | E17: margin_calls | F17: call_type | G17: call_amount
C18: Reverse repo/Repo | D18: Treasury System Database | E18: Repo_Trades | F18: purchase_price
C19: Reverse repo/Repo | D19: Treasury System Database | E19: Cash_Margin_Movements | F19: amount
A21: 4 | B21: update maturity
A24: 5 | B24: coupon payment | C24: Bond | D24: Thai BMA website | E24: bond_transactions | F24: trade_type = Coupon | G24: accrued_interest
E25: bond_positions | F25: accrued_interest
E26: position_realization_events | F26: accrued_int_realized
B28: floating rate reprice | C28: Bond
C29: Interbank lending/borrowing
B33: Input deal buy sell lend borrow | E33: cost & Realized P/L

Sheet All Table_V4_Clean
A1: Timestamp update as of | B1: 46037.479
A3: entity_master
A4: This table represents the authoritative, enterprise-wide obligor registry. It stores the top-level identity of each customer group, legal entity, or economic group used for credit risk, Basel, TFRS 9, Moody’s mapping, and BOT DER_CPEN.Entity Id.
A6: Column Name | B6: Data Type | C6: Description | D6: Example | E6: Primary key/Foreign key | F6: Allow Null | G6: Remark
A7: entity_id | B7: VARCHAR(40) | C7: Top-level unique identifier for the obligor or customer group. Used as the BOT DER_CPEN.Entity Id and compatible with Moody’s ENTITY_CODE. This identifier is systematically constructed by concatenating "entity_short_name + juristic_registration_number" to ensure uniqueness and consistency across counterparty_master, entity_master, and regulatory reporting. This is the primary key that counterparty_master.entity_id references. | D7: =CONCAT(D9,D13) -> BBL0107536000374 | E7: PK | F7: No
A8: entity_name | B8: VARCHAR(255) | C8: Full legal name of the entity/obligor. Often the same as Counterparty_Master.legal_name, but stored here at obligor/group level. | D8: Bangkok Bank PCL | E8: - | F8: No
A9: entity_short_name | B9: VARCHAR(10) | C9: Short name / abbreviation used in risk reporting. | D9: BBL | E9: - | F9: Yes
A10: entity_type | B10: VARCHAR(50) | C10: Fine-grained Basel/Moody’s obligor classification (BANK, BANK_SOV, PSE, CORP_HVCRE, SME_PF, INDIV, SOV, SUPRA, etc.). Used for regulatory RW, EAD grouping, and Moody’s mapped class. | D10: BANK | E10: - | F10: No
A11: industry_sector | B11: VARCHAR(50) | C11: User-defined industry sector (Moody’s INDUSTRY_SECTOR). Used for concentration analysis. | D11: FINANCIALS | E11: - | F11: Yes
A12: country_code | B12: CHAR(3) | C12: Country of domicile for country risk and Basel mapping. | D12: TH | E12: - | F12: No
A13: juristic_registration_number | B13: VARCHAR(20) | C13: เลขจดทะเบียนนิติบุคคล / เลขนิติบุคคล (13 digits for Thai juristic entities). Used for KYC, BOT reporting, and obligor-level regulatory mapping. | D13: 0107536000374 | E13: - | F13: No
A14: registered_capital_amount | B14: DECIMAL(20,2) | C14: ทุนจดทะเบียนของนิติบุคคล (Registered Capital of the entity). | D14: 40000000000 | E14: - | F14: Yes
A15: financials_currency | B15: CHAR(3) | C15: Currency for financials. | D15: THB | F15: Yes
A16: g_sib_type | B16: CHAR(1) | C16: G-SIB / D-SIB classification (G/D/NULL). | D16: D | E16: - | F16: Yes
A17: created_date | B17: DATE | C17: Record creation timestamp. | D17: 45301 | E17: - | F17: No
A18: last_updated_date | B18: DATE | C18: Record last update timestamp. | D18: 45853 | E18: - | F18: Yes
A21: counterparty_master
A22: This table serves as the single, authoritative repository for all external and internal entities with which the bank conducts treasury business.
A24: Column Name | B24: Data Type | C24: Description | D24: Example | E24: Primary key/Foreign key | F24: Allow Null | G24: Remark
A25: entity_id | B25: VARCHAR(40) | C25: Unique reference number identifying a person, juristic person, group of persons, group of juristic persons, or customer group. May represent either (a) an internal identifier used within the financial institution, or (b) an external reference number used for BOT data submission. | D25: BBL0107536000374 | E25: FK → entity_master.entity_id | F25: No
A26: counterparty_id | B26: VARCHAR(40) | C26: Unique system-generated identifier for the counterparty. | D26: 101 | E26: PK | F26: Yes
A27: legal_name | B27: VARCHAR(255) | C27: The full legal name of the entity. | D27: Bangkok Bank PCL | E27: - | F27: No
A28: short_code | B28: VARCHAR(50) | C28: A short, unique code used for quick identification in user interfaces. | D28: BBL | E28: - | F28: Yes
A29: counterparty_type | B29: VARCHAR(50) | C29: Type of counterparty (e.g., 'Commercial Bank', 'SOE', 'Corporate', 'Central Bank'). | D29: Commercial Bank | E29: - | F29: No
A30: bank_code | B30: VARCHAR(13) | C30: Official identifier assigned by the Bank of Thailand in Sheet 'BANK_CODE'. The format should be Text "XXX". | D30: 001 | E30: - | F30: Yes | G30: Applicable only for financial institutions. Leave blank for corporates.
A31: swift_bic | B31: VARCHAR(11) | C31: The counterparty's Business Identifier Code for SWIFT messaging. | D31: BKKBTHBK | E31: - | F31: Yes | G31: Used for payment, settlement, and messaging systems.
A32: primary_credit_rating | B32: VARCHAR(10) | C32: The primary credit rating from the designated agency. | D32: AA+ | E32: - | F32: Yes
A33: primary_rating_agency | B33: VARCHAR(50) | C33: The name of the primary credit rating agency (e.g., 'Fitch', 'TRIS Rating'). | D33: TRIS Rating | E33: - | F33: Yes
A34: primary_rating_date | B34: DATE | C34: The date the primary rating was assigned or last updated. | D34: 45853 | E34: - | F34: Yes
A35: created_date | B35: DATE | C35: Timestamp of record creation for audit purposes. | D35: 45301 | E35: - | F35: No
A36: last_updated_date | B36: DATE | C36: Timestamp of the last update for audit purposes. | D36: 45853 | E36: - | F36: Yes
A37: involved_party_type | B37: INT | C37: Classification code representing the type of institution or counterparty based on the Bank of Thailand’s (BOT) standardized in sheet “Involved_Party_Type” list. | D37: 176039 | E37: - | F37: No
A38: customer_code | B38: VARCHAR(10) | C38: Bank-defined customer classification code used to identify the type of customer for regulatory, reporting, and business rules (e.g., interest calculation, FCC, interbank classification). Each CIF must be mapped to exactly one customer type. The code is maintained by the bank and aligned with BOT/MFSMCG concepts such as Personal, Juristic Person, Government, Financial Institution (Resident / Non-Resident), etc. Please refer to sheet 'Customer_type_master' for the defition. | D38: 2008 | E38: - | F38: No | G38: Remark: This field is introduced in advance to prepare for future customer classification and regulatory use cases. At this stage, the detailed customer code mapping may not yet be fully defined. From a data model perspective, the preferred approach is to use customer_type_code as the single source of truth, and let downstream processes and reports map this code to required attributes (e.g., residency, interbank, FCC class, sector, etc.) via reference tables. This avoids creating many hard-coded flags (e.g., is_interbank_flag, is_financial_institution_flag, is_government_flag, etc.). In the future, once the customer code mapping is stabilized, this field can become the primary driver and allow removal of overlapping or redundant flags. Otherwise, continuing to add multiple boolean flags will eventually result in a table filled with overlapping indicators that represent the same business meaning in different forms. See sheet 'Customer_type_master'
A39: reside_in_thailand_flag | B39: BOOLEAN | C39: Indicates whether the counterparty is a financial institution that resides in Thailand, in accordance with the Monetary and Financial Statistics Manual and Compilation Guide (MFSMCG) residency classification. - TRUE = Counterparty is resident in Thailand (มีถิ่นฐานอยู่ในประเทศ) - FALSE = Counterparty is non-resident (มีถิ่นฐานอยู่นอกประเทศ) Please refer to sheet 'Resident definition' for the defition. | D39: TRUE | E39: - | F39: No | G39: See sheet 'Resident definition'
A42: security_master
A43: This table is a comprehensive catalog of every financial instrument the bank can trade or hold, aligned with standards from the Thai Bond Market Association (ThaiBMA).
A45: Column Name | B45: Data Type | C45: Description | D45: Example | E45: Primary key/Foreign key | F45: Allow Null | G45: Remark
A46: security_id | B46: VARCHAR(10) | C46: Unique system-generated identifier for the security e.g. The official trading symbol used by ThaiBMA. | D46: LB28DA | E46: PK | F46: No
A47: isin | B47: VARCHAR(12) | C47: International Securities Identification Number. | D47: TH0623038C09 | E47: PK | F47: No
A48: issuer_id | B48: VARCHAR(40) | C48: Identify the issuer. 1 = Govt of Thailand, 2 = BOT, 3 = State Own Enterprise, 4 = Corporate https://www.thaibma.or.th/EN/Issuer/IssuerSearch.aspx | D48: 1 | E48: PK | F48: No
A49: unique_id | B49: VARCHAR(20) | C49: ID for BOT report , Please refer to Sheet 'Unique Id Type'. ( (1) BOT bond use BANK_CODE (2) Govt bond, T-bill, SOE bond, SOE MOF use Govt Agency code (3) Corp bond, use Juristic Id from dataforThai website) | D49: 001 | E49: PK | F49: No | G49: Used in BOT data submissions
A50: instrument_type | B50: VARCHAR(20) | C50: The type of instrument (e.g., 'T-Bill', 'Gov Bond', 'Corp Bond', 'SOE Bond', 'BOT Bond', 'SOE MOF'). | D50: Gov Bond | E50: - | F50: No
A51: issue_date | B51: DATE | C51: The date the security was issued. | D51: 43451 | E51: - | F51: No
A52: maturity_date | B52: DATE | C52: The date the security matures. | D52: 47104 | E52: - | F52: No
A53: coupon_rate | B53: DECIMAL(10,6) | C53: Nominal coupon rate. “0” for zero-coupon bonds. Fixed: contract rate; Floating: last reset per ThaiBMA MTM. | D53: 2.75 | E53: - | F53: Yes
A54: coupon_margin | B54: DECIMAL(10,6) | C54: Spread over the reference rate in percentage terms. For fixed-rate deals, set to 0 | D54: 0.1 | E54: - | F54: Yes
A55: coupon_reference_rate | B55: VARCHAR(20) | C55: Floating rate benchmark (e.g., THBFIX6M). If fixed, set to NULL. | D55: NULL | E55: - | F55: Yes
A56: coupon_frequency | B56: VARCHAR(20) | C56: Frequency of coupon payments (e.g., 'Semi-Annual', 'Quarterly'). | D56: Semi-Annual | E56: - | F56: No
A57: coupon_day_count_conv | B57: VARCHAR(20) | C57: The convention for calculating accrued interest (e.g., 'Actual/365'). 1 | D57: Actual/365 | E57: - | F57: No
A58: currency | B58: VARCHAR(3) | C58: ISO 4217 currency code. | D58: THB | E58: - | F58: No
A59: country | B59: VARCHAR(3) | C59: Country Code | D59: TH | E59: - | F59: No
A60: bond_structure | B60: VARCHAR(20) | C60: Structure of principal repayment (e.g., "ZERO", 'Bullet'). | D60: Bullet | E60: - | F60: No
A61: rating_tris | B61: VARCHAR(8) | C61: The long-term credit rating assigned to the security or issuer by TRIS Rating (Thailand). This field stores the latest available rating used for credit risk assessment and reporting. Leave blank for Government or MOF-guaranteed securities where ratings are not applicable. | D61: A- | E61: - | F61: Yes
A62: rating_fitch | B62: VARCHAR(8) | C62: The long-term credit rating assigned to the security or issuer by Fitch Ratings. This field stores the latest available rating used for credit risk assessment, valuation models, and investment eligibility checks. Leave blank for Government or MOF-guaranteed securities where ratings are not applicable. | D62: A-(tha) | E62: - | F62: Yes
A63: is_eligible_bot_repo_collateral | B63: BOOLEAN | C63: Flag indicating if the security is eligible for use in BOT's repo operations. | D63: TRUE | E63: - | F63: No
A64: is_eligible_crm_collateral | B64: BOOLEAN | C64: Flag indicating if the security meets BOT's criteria for Credit Risk Mitigation. | D64: TRUE | E64: - | F64: No
A65: status | B65: VARCHAR(20) | C65: Active', 'Matured', 'Defaulted'. | D65: Active | E65: - | F65: No
A66: status_timestamp | B66: DATETIME | C66: Timestamp of record creation. Time zone in Thailand (GMT+7). Format: YYYY-MM-DD HH:MM:SS | D66: 45323.458 | E66: - | F66: Yes
A67: coupon_rate_type | B67: VARCHAR(10) | C67: ‘Fixed’ or ‘Floating’. | D67: Fixed | E67: - | F67: No
A68: cross_default | B68: BOOLEAN | C68: Flag indicating if the security has entered default due to a cross-default event triggered by another security under the same issuer. If TRUE, the system immediately treats this plan as defaulted. | D68: FALSE | E68: - | F68: No
A70: portfolio_master
A71: This table allows for the logical segregation of the bank's treasury positions according to their strategic intent.
A73: Column Name | B73: Data Type | C73: Description | D73: Example | E73: Primary key/Foreign key | F73: Allow Null | G73: Remark
A74: portfolio_id | B74: VARCHAR(40) | C74: Unique system-generated identifier for the portfolio. | D74: 201 | E74: PK | F74: No
A75: portfolio_name | B75: VARCHAR(100) | C75: Clear accounting classification upfront (e.g., 'Amortized Cost', 'Fair Value through OCI', 'Fair Value through P&L (Trading Book)') along with Asset type (Gov, SOE, BOT, T-Bill) | D75: AMC - Govt Bonds | E75: - | F75: No
A76: portfolio_manager | B76: portfolio_manager | C76: The name or ID of the responsible manager or desk. | D76: John Doe | E76: - | F76: No
A77: accounting_treatment | B77: VARCHAR(50) | C77: The accounting designation which dictates valuation and P&L recognition rules. | D77: FVOCI | E77: - | F77: No
A78: created_timestamp | B78: DATETIME | C78: Timestamp of record creation. Time zone in Thailand (GMT+7). Format: YYYY-MM-DD HH:MM:SS | D78: 45323.458 | E78: - | F78: No
A80: netting_agreement
A81: This table contains the master information for all legally enforceable netting and collateral agreements (e.g., ISDA, CSA, GMRA, GMSLA) established between the institution and its counterparties. Each record represents one agreement that defines the scope, effective period, and key legal attributes governing how financial transactions (e.g., swaps, repos, FX, securities lending) are netted, margined, and settled.
A83: Column Name | B83: Data Type | C83: Description | D83: Example | E83: Primary key/Foreign key | F83: Allow Null | G83: Remark
A84: netting_agreement_id | B84: VARCHAR2(40) | C84: Unique generated identifier for each netting agreement record. | D84: GMRA_2023_KB | E84: PK | F84: No
A85: counterparty_id | B85: VARCHAR(40) | C85: Identifier linking to the counterparty legal entity in Counterparty_Master. | D85: 101 | E85: FK → counterparty_master.counterparty_id | F85: No
A86: netting_set_id | B86: VARCHAR(40) | C86: Logical identifier for the enforceable netting set under which trades are aggregated. Remains the same for new/replacement agreements if the legal relationship continues. | D86: 20001 | E86: - | F86: No
A87: agreement_type | B87: VARCHAR(10) | C87: Type of master/annex agreement defining the netting scope i.e. GMRA, ISDA. | D87: GMRA | E87: - | F87: No
A88: netting_type | B88: VARCHAR2(20) | C88: Classification of the netting structure used in the agreement. Examples: • CLOSE_OUT – for close-out netting under ISDA/CSA • COLLATERAL – for collateral netting • SET_OFF – for balance sheet set-off netting | D88: COLLATERAL | E88: - | F88: No
A89: collateral_contract_type | B89: VARCHAR2(12) | C89: Classification of the netting collateral type, used by the engine to determine exposure and regulatory product mapping: • REP – contract type for collateral legs under repo agreements. • BAL – contract type for balance sheet/liability netting. • OTC – contract type for OTC derivatives. | D89: REP | E89: - | F89: No
A90: trade_date | B90: DATE | C90: Date of signature or execution of the agreement by both parties. | D90: 45092 | E90: - | F90: No
A91: value_date | B91: DATE | C91: Effective or enforcement date when the agreement becomes active for new trades. | D91: 45108 | E91: - | F91: No
A92: maturity_date | B92: DATE | C92: Expiry or termination date of the agreement. No new trades should map after this date. | D92: 45838 | E92: - | F92: Yes | G92: No new trades mapped beyond this date.
A93: is_replacement | B93: TINYINT (0/1) | C93: Flag indicating if this agreement replaces an earlier one (1 = Yes, 0 = No). | D93: 0 | E93: - | F93: No
A94: replaced_agreement_id | B94: VARCHAR(40) | C94: References the previous NettingAgreementID that this record replaces. Null if not a replacement | D94: NULL | E94: FK → netting_agreement.netting_agreement_id | F94: Yes
A95: settlement_currency | B95: VARCHAR(3) | C95: Primary settlement or close-out currency used under the agreement. | D95: THB | E95: - | F95: Yes
A96: created_at | B96: DATETIME | C96: Timestamp of record creation. Time zone in Thailand (GMT+7). Format: YYYY-MM-DD HH:MM:SS | D96: 45717.438 | E96: - | F96: No
A97: updated_at | B97: DATETIME | C97: Timestamp of the latest record update. Time zone in Thailand (GMT+7). Format: YYYY-MM-DD HH:MM:SS | D97: 45741.781 | E97: - | F97: Yes
A98: agreement_status | B98: VARCHAR(20) | C98: ‘Active’, ‘Matured’, ‘In-Default’. | D98: Active | E98: - | F98: No
A100: interbank_deals
A101: This table records all interbank lending (placements) and borrowing (takings) transactions.
A103: Column Name | B103: Data Type | C103: Description | D103: Example | E103: Primary key/Foreign key | F103: Allow Null | G103: Remark
A104: deal_id | B104: VARCHAR(40) | C104: Unique identifier for the deal. | D104: 40001 | E104: PK | F104: No
A105: trade_date | B105: DATETIME | C105: Date and time the deal was executed. Time zone in Thailand (GMT+7). Format: YYYY-MM-DD HH:MM:SS | D105: 45905.438 | E105: - | F105: No
A106: value_date | B106: DATE | C106: The start date of the loan/deposit. | D106: 45905 | E106: - | F106: No
A107: maturity_date | B107: DATE | C107: The end date of the loan/deposit. | D107: 45908 | E107: - | F107: No
A108: deal_type | B108: VARCHAR(10) | C108: Lend' or 'Borrow'. | D108: Lend | E108: - | F108: No
A109: counterparty_id | B109: VARCHAR(40) | C109: Links to Counterparty_Master. | D109: 101 | E109: FK → counterparty_master.counterparty_id | F109: No | G109: Must match an active counterparty record.
A110: principal_amount | B110: DECIMAL(20,2) | C110: The nominal amount of the deal. | D110: 250000000 | E110: - | F110: No | G110: Positive value; currency defined in Currency. Additional logic from DP before send to YIP If interbank_deals.status = 'Matured', DP adjust interbank_deals.principal_amount value to '0.00' before send to YIP
A111: currency | B111: VARCHAR(3) | C111: ISO 4217 currency code. | D111: THB | E111: - | F111: No | G111: e.g. THB, USD, EUR.
A112: reference_rate_id | B112: VARCHAR(20) | C112: Contractual reference rate identifier, typically ReferenceRate + ReferenceRate_Tenor + DealID (e.g. ‘THOR1M45001’). | D112: THOR1M | E112: - | F112: Yes | G112: Derived contract key. NULL for fixed-rate deals or where no benchmark is defined.
A113: interest_rate_type | B113: VARCHAR(10) | C113: Fixed' or 'Floating'. | D113: Fixed | E113: - | F113: No
A114: interest_rate | B114: DECIMAL(10,6) | C114: The current applicable interest rate (% p.a.). • Fixed: the agreed contractual rate (reported from TradeDate). • Floating: the latest ResetRate (= ReferenceRate + Margin) effective from LastResetDate. | D114: 2.25 | E114: - | F114: No
...

Sheet accrued_interest
A1: bond_positions.accrued_interest
A2: Case | B2: Behavior
A3: หลังลงทุน / ไม่มี coupon ยังไม่ถึงงวด | B3: AI เพิ่มขึ้นรายวันตั้งแต่ settlement date
A4: หลัง partial sale | B4: AI คิดใหม่บน nominal ที่เหลือ (ไม่ใช้ของ trade เดิม)
A5: หลัง coupon event | B5: AI reset → เริ่มนับใหม่จาก 0
A6: ขายออกเต็มจำนวน (position closed) | B6: Position.accrued_interest = 0
A7: หลัง maturity | B7: accrued_interest → 0 และไม่มีการ accrue ต่อ
A8: Floating bonds | B8: ใช้อัตรา coupon ล่าสุดจาก bond_transactions (Reset rate)

Sheet Product_table structure
A1: Interbank table structure
A2: The primary purpose of this table is to clearly outline the related tables and key linking fields necessary to record, manage, and track data for each product within the interbank system.
A3: It serves as a quick reference guide summarizing all related tables and key linking fields required for Interbank Lending/Borrowing, Reverse Repo/Repo, and Bond Buying/Selling, illustrating the overall data structure needed to support each product’s operation.
A5: Product | B5: No. | C5: Related table | D5: Key fields
A6: Interbank lending/borrowing | B6: 1 | C6: Counterparty_Master | D6: entity_id | E6: counterparty_id | F6: bank_code
B7: 2 | C7: Limit_Utilization | D7: LimitID | E7: counterparty_id | F7: entity_id
B8: 3 | C8: Interbank_Deals | D8: DealID | E8: counterparty_id | F8: LimitID | G8: entity_id
B9: 4 | C9: Interbank_Interest_Schedule (Child Table) | D9: ScheduleID | E9: DealID
A11: Reverse repo/ Repo | B11: 1 | C11: Netting_Agreement | D11: NettingAgreementID | E11: counterparty_id
B12: 2 | C12: Counterparty_Master | D12: entity_id | E12: counterparty_id | F12: bank_code
B13: 3 | C13: Security_Master | D13: SecurityID
B14: 4 | C14: Limit_Utilization | D14: LimitID | E14: counterparty_id | F14: entity_id
B15: 5 | C15: Repo_Trades | D15: RepoTradeID | E15: counterparty_id | F15: LimitID | G15: entity_id
B16: 6 | C16: Collateral_Positions | D16: CollateralID | E16: RepoTradeID | F16: SecurityID
B17: 7 | C17: Bond_Transactions | D17: TradeID | E17: SecurityID | F17: PortfolioID | G17: counterparty_id | H17: TradeType
B18: 8 | C18: Bond_Positions | D18: PositionID | E18: SecurityID | F18: PortfolioID
B19: 9 | C19: Margin_Calls | D19: MarginCallID | E19: counterparty_id | F19: RepoTradeID
B20: 10 | C20: Cash_Margin_Movements | D20: CashMarginMovementID | E20: MarginCallID | F20: counterparty_id | G20: RepoTradeID
A23: Bond buying/ selling | B23: 1 | C23: Counterparty_Master | D23: entity_id | E23: counterparty_id | F23: bank_code
B24: 2 | C24: Security_Master | D24: SecurityID
B25: 3 | C25: Portfolio_Master | D25: PortfolioID
B26: 4 | C26: Bond_Trades | D26: BondTradeID | E26: PortfolioID | F26: SecurityID
B27: 5 | C27: Bond_Transactions | D27: TradeID | E27: SecurityID | F27: PortfolioID | G27: counterparty_id | H27: TradeType
B28: 6 | C28: Bond_Positions | D28: PositionID | E28: SecurityID | F28: PortfolioID
B29: 7 | C29: Position_Costing | D29: CostingID | E29: PositionID
B30: 8 | C30: Position_RealizationEvents | D30: RealizationID | E30: PositionID | F30: TradeID

Sheet cashmargin
F1: PAY
A2: cash_margin_movements | F2: RECEIVE | H2: sum by margin_call_id | L2: cal AI only negative outstanding_balance
A3: cash_margin_movement_id | B3: margin_call_id | C3: counterparty_id | D3: repo_trade_id | E3: call_currency | F3: movement_type | G3: amount | H3: outstanding_balance | I3: value_date | J3: created_timestamp | K3: bank_account_code | L3: accrued_int_payable | M3: daily_accrued_int_payable
A4: 1 | B4: 1 | C4: 101 | D4: 70001 | E4: THB | F4: RECEIVE | G4: 2100000 | H4: 0 | I4: 45909 | J4: 45909.625 | K4: MRGN_THSCCB01
A5: 2 | B5: 2 | C5: 102 | D5: 7703 | E5: THB | F5: RECEIVE | G5: 5500000 | H5: 5500000 | I5: 45930 | J5: 45930.625 | K5: MRGN_THSCCB02
A6: 3 | B6: 3 | C6: 102 | D6: 70004 | E6: THB | F6: PAY | G6: -600000 | H6: -600000 | I6: 45929 | J6: 45929.844 | K6: MRGN_THSCCB03
A7: 4 | B7: 1 | C7: 101 | D7: 70001 | E7: THB | F7: PAY | G7: -2100000 | H7: 0 | I7: 45915 | J7: 45909.625 | K7: MRGN_THSCCB01 | L7: 0
A11: Outstanding Balance | B11: Daily Accrued Interest | C11: Cumulative Accrued Interest
A12: ≥ 0 | B12: 0 | C12: 0 (reset)
A13: < 0 | B13: Calculated | C13: Accumulates

Sheet Data Month N >>

Sheet V4_Result_30 Sep 2025
A1: Export as of | B1: =DATE(2025,9,30) -> 45930 | D1: Timestamp update as of | E1: 46037.666
A3: counterparty_master
A4: {=TRANSPOSE('All Table_V4_Clean'!A25:A39)} -> entity_id | B4: counterparty_id | C4: legal_name | D4: short_code | E4: counterparty_type | F4: bank_code | G4: swift_bic | H4: primary_credit_rating | I4: primary_rating_agency | J4: primary_rating_date | K4: created_date | L4: last_updated_date | M4: involved_party_type | N4: customer_code | O4: reside_in_thailand_flag
A5: =RRP_1_V4_Sep25!B13 -> BBL0107536000374 | B5: =RRP_1_V4_Sep25!C13 -> 101 | C5: =RRP_1_V4_Sep25!D13 -> BANGKOK BANK PCL | D5: =RRP_1_V4_Sep25!E13 -> BBL | E5: =RRP_1_V4_Sep25!F13 -> Commercial Bank | F5: =RRP_1_V4_Sep25!G13 -> 002 | G5: =RRP_1_V4_Sep25!H13 -> BKKBTHBK | H5: =RRP_1_V4_Sep25!I13 -> AA- | ... M5: =RRP_1_V4_Sep25!N13 -> 176039 | N5: 2008 | O5: TRUE
A6: =RRP_2_V4_Sep25!B13 -> KBANK0107536000315 | B6: =RRP_2_V4_Sep25!C13 -> 102 | C6: =RRP_2_V4_Sep25!D13 -> KASIKORNBANK PCL | D6: =RRP_2_V4_Sep25!E13 -> KBANK | E6: =RRP_2_V4_Sep25!F13 -> Commercial Bank | F6: =RRP_2_V4_Sep25!G13 -> 004 | G6: =RRP_2_V4_Sep25!H13 -> KASITHBK | H6: =RRP_2_V4_Sep25!I13 -> AA | ... M6: =RRP_2_V4_Sep25!N13 -> 176039 | N6: 2008 | O6: TRUE
A7: =Repo_1_V4_Sep25!B13 -> KTB107537000882 | B7: =Repo_1_V4_Sep25!C13 -> 103 | C7: =Repo_1_V4_Sep25!D13 -> KRUNGTHAI BANK PCL | D7: =Repo_1_V4_Sep25!E13 -> KTB | E7: =Repo_1_V4_Sep25!F13 -> Commercial Bank | F7: =Repo_1_V4_Sep25!G13 -> 006 | G7: =Repo_1_V4_Sep25!H13 -> KRTHTHBK | H7: =Repo_1_V4_Sep25!I13 -> AA+ | ... M7: =Repo_1_V4_Sep25!N13 -> 176039 | N7: 2008 | O7: TRUE
A8: ='IB Lend_V4_Sep25'!A12 -> CIMB0107537002338 | B8: ='IB Lend_V4_Sep25'!B12 -> 104 | C8: ='IB Lend_V4_Sep25'!C12 -> CIMB THAI BANK PCL | D8: ='IB Lend_V4_Sep25'!D12 -> CIMB | E8: ='IB Lend_V4_Sep25'!E12 -> Commercial Bank | F8: ='IB Lend_V4_Sep25'!F12 -> 022 | G8: ='IB Lend_V4_Sep25'!G12 -> UBOBTHBK | H8: ='IB Lend_V4_Sep25'!H12 -> AA(THA) | ... M8: ='IB Lend_V4_Sep25'!M12 -> 176039 | N8: 2008 | O8: TRUE
A10: security_master
A11: {=TRANSPOSE('All Table_V4_Clean'!A46:A68)} -> security_id | B11: isin | C11: issuer_id | D11: unique_id | E11: instrument_type | F11: issue_date | G11: maturity_date | H11: coupon_rate | I11: coupon_margin | J11: coupon_reference_rate | K11: coupon_frequency | L11: coupon_day_count_conv | M11: currency | N11: country | O11: bond_structure | P11: rating_tris | Q11: rating_fitch | R11: is_eligible_bot_repo_collateral | S11: is_eligible_crm_collateral | T11: status | U11: status_timestamp | V11: coupon_rate_type | W11: cross_default
A12: ='Bond buy_1_V4_Sep25'!B21 -> GSB26OA | B12: ='Bond buy_1_V4_Sep25'!C21 -> TH1029036A07 | C12: ='Bond buy_1_V4_Sep25'!D21 -> 3 | D12: ='Bond buy_1_V4_Sep25'!E21 -> 176017 | E12: ='Bond buy_1_V4_Sep25'!F21 -> SOE Bond | F12: ='Bond buy_1_V4_Sep25'!G21 -> 43754 | G12: ='Bond buy_1_V4_Sep25'!H21 -> 46311 | H12: ='Bond buy_1_V4_Sep25'!I21 -> 1.69 | ... V12: ='Bond buy_1_V4_Sep25'!W21 -> Fixed | W12: FALSE
A13: ='Bond buy_1_V4_Sep25'!B22 -> LB616A | B13: ='Bond buy_1_V4_Sep25'!C22 -> TH0623B3B607 | C13: ='Bond buy_1_V4_Sep25'!D22 -> 1 | D13: ='Bond buy_1_V4_Sep25'!E22 -> 176015 | E13: ='Bond buy_1_V4_Sep25'!F22 -> Gov Bond | F13: ='Bond buy_1_V4_Sep25'!G22 -> 40606 | G13: ='Bond buy_1_V4_Sep25'!H22 -> 58974 | H13: ='Bond buy_1_V4_Sep25'!I22 -> 4.85 | ... V13: ='Bond buy_1_V4_Sep25'!W22 -> Fixed | W13: FALSE
A14: ='Bond buy_1_V4_Sep25'!B23 -> TB26128A | B14: ='Bond buy_1_V4_Sep25'!C23 -> TH0623A76183 | C14: ='Bond buy_1_V4_Sep25'!D23 -> 1 | D14: ='Bond buy_1_V4_Sep25'!E23 -> 176015 | E14: ='Bond buy_1_V4_Sep25'!F23 -> T-Bill | F14: ='Bond buy_1_V4_Sep25'!G23 -> 45868 | G14: ='Bond buy_1_V4_Sep25'!H23 -> 46050 | H14: ='Bond buy_1_V4_Sep25'!I23 -> 0 | ... V14: ='Bond buy_1_V4_Sep25'!W23 -> Fixed | W14: FALSE
A15: ='Bond buy_1_V4_Sep25'!B24 -> BOT25NA | B15: ='Bond buy_1_V4_Sep25'!C24 -> TH0655035B00 | C15: ='Bond buy_1_V4_Sep25'!D24 -> 2 | D15: ='Bond buy_1_V4_Sep25'!E24 -> 001 | E15: ='Bond buy_1_V4_Sep25'!F24 -> BOT Bond | F15: ='Bond buy_1_V4_Sep25'!G24 -> 45236 | G15: ='Bond buy_1_V4_Sep25'!H24 -> 45967 | H15: ='Bond buy_1_V4_Sep25'!I24 -> 2.58 | ... V15: ='Bond buy_1_V4_Sep25'!W24 -> Fixed | W15: FALSE
A16: ='Bond buy_1_V4_Sep25'!B25 -> TB26211A | B16: ='Bond buy_1_V4_Sep25'!C25 -> TH0623076286 | C16: ='Bond buy_1_V4_Sep25'!D25 -> 1 | D16: ='Bond buy_1_V4_Sep25'!E25 -> 176015 | E16: ='Bond buy_1_V4_Sep25'!F25 -> T-Bill | F16: ='Bond buy_1_V4_Sep25'!G25 -> 45882 | G16: ='Bond buy_1_V4_Sep25'!H25 -> 46064 | H16: ='Bond buy_1_V4_Sep25'!I25 -> 0 | ... V16: ='Bond buy_1_V4_Sep25'!W25 -> Fixed | W16: FALSE
A17: ='Bond buy_1_V4_Sep25'!B26 -> BOTF267A | B17: ='Bond buy_1_V4_Sep25'!C26 -> TH0655036711 | C17: ='Bond buy_1_V4_Sep25'!D26 -> 2 | D17: ='Bond buy_1_V4_Sep25'!E26 -> 001 | E17: ='Bond buy_1_V4_Sep25'!F26 -> BOT Bond | F17: ='Bond buy_1_V4_Sep25'!G26 -> 45474 | G17: ='Bond buy_1_V4_Sep25'!H26 -> 46204 | H17: ='Bond buy_1_V4_Sep25'!I26 -> 1.68404 | ... V17: ='Bond buy_1_V4_Sep25'!W26 -> Floating | W17: FALSE
A18: =RRP_1_V4_Sep25!B19 -> LB29DA | B18: =RRP_1_V4_Sep25!C19 -> TH0623039C07 | C18: =RRP_1_V4_Sep25!D19 -> 1 | D18: =RRP_1_V4_Sep25!E19 -> 176015 | E18: =RRP_1_V4_Sep25!F19 -> Gov Bond | F18: =RRP_1_V4_Sep25!G19 -> 43784 | G18: =RRP_1_V4_Sep25!H19 -> 47469 | H18: =RRP_1_V4_Sep25!I19 -> 1.6 | ... V18: =RRP_1_V4_Sep25!W19 -> Fixed | W18: FALSE
A19: =RRP_2_V4_Sep25!B19 -> LB28DA | B19: =RRP_2_V4_Sep25!C19 -> TH0623038C09 | C19: =RRP_2_V4_Sep25!D19 -> 1 | D19: =RRP_2_V4_Sep25!E19 -> 176015 | E19: =RRP_2_V4_Sep25!F19 -> Gov Bond | F19: =RRP_2_V4_Sep25!G19 -> 43294 | G19: =RRP_2_V4_Sep25!H19 -> 47104 | H19: =RRP_2_V4_Sep25!I19 -> 2.875 | ... V19: =RRP_2_V4_Sep25!W19 -> Fixed | W19: FALSE
A20: ='Bond Buy-Sell_V4_Sep25 + Oct25'!A24 -> EXIM266A | B20: ='Bond Buy-Sell_V4_Sep25 + Oct25'!B24 -> TH0624036602 | C20: ='Bond Buy-Sell_V4_Sep25 + Oct25'!C24 -> 3 | D20: ='Bond Buy-Sell_V4_Sep25 + Oct25'!D24 -> 035 | E20: ='Bond Buy-Sell_V4_Sep25 + Oct25'!E24 -> SOE Bond | F20: ='Bond Buy-Sell_V4_Sep25 + Oct25'!F24 -> 45083 | G20: ='Bond Buy-Sell_V4_Sep25 + Oct25'!G24 -> 46179 | H20: ='Bond Buy-Sell_V4_Sep25 + Oct25'!H24 -> 2.71 | ... V20: ='Bond Buy-Sell_V4_Sep25 + Oct25'!V24 -> Fixed | W20: FALSE
A22: portfolio_master
A23: {=TRANSPOSE('All Table_V4_Clean'!A74:A78)} -> portfolio_id | B23: portfolio_name | C23: portfolio_manager | D23: accounting_treatment | E23: created_timestamp
A24: ='Bond buy_1_V4_Sep25'!B34 -> 301 | B24: ='Bond buy_1_V4_Sep25'!C34 -> AMC - Govt | C24: ='Bond buy_1_V4_Sep25'!D34 -> Treasury Desk | D24: ='Bond buy_1_V4_Sep25'!E34 -> AMC | E24: ='Bond buy_1_V4_Sep25'!F34 -> 45839
A25: ='Bond buy_1_V4_Sep25'!B35 -> 302 | B25: ='Bond buy_1_V4_Sep25'!C35 -> AMC - T-Bill | C25: ='Bond buy_1_V4_Sep25'!D35 -> Treasury Desk | D25: ='Bond buy_1_V4_Sep25'!E35 -> AMC | E25: ='Bond buy_1_V4_Sep25'!F35 -> 45839
A26: ='Bond buy_1_V4_Sep25'!B36 -> 303 | B26: ='Bond buy_1_V4_Sep25'!C36 -> AMC - BOT bond | C26: ='Bond buy_1_V4_Sep25'!D36 -> Treasury Desk | D26: ='Bond buy_1_V4_Sep25'!E36 -> AMC | E26: ='Bond buy_1_V4_Sep25'!F36 -> 45839
A27: ='Bond buy_1_V4_Sep25'!B37 -> 401 | B27: ='Bond buy_1_V4_Sep25'!C37 -> FVOCI - T-Bill | C27: ='Bond buy_1_V4_Sep25'!D37 -> Treasury Desk | D27: ='Bond buy_1_V4_Sep25'!E37 -> FVOCI | E27: ='Bond buy_1_V4_Sep25'!F37 -> 45839
A28: ='Bond buy_1_V4_Sep25'!B38 -> 402 | B28: ='Bond buy_1_V4_Sep25'!C38 -> FVOCI - BOT bond | C28: ='Bond buy_1_V4_Sep25'!D38 -> Treasury Desk | D28: ='Bond buy_1_V4_Sep25'!E38 -> FVOCI | E28: ='Bond buy_1_V4_Sep25'!F38 -> 45839
A29: ='Bond buy_1_V4_Sep25'!B39 -> 403 | B29: ='Bond buy_1_V4_Sep25'!C39 -> FVOCI - SOE | C29: ='Bond buy_1_V4_Sep25'!D39 -> Treasury Desk | D29: ='Bond buy_1_V4_Sep25'!E39 -> FVOCI | E29: ='Bond buy_1_V4_Sep25'!F39 -> 45839
A32: netting_agreement
A33: {=TRANSPOSE('All Table_V4_Clean'!A84:A98)} -> netting_agreement_id | B33: counterparty_id | C33: netting_set_id | D33: agreement_type | E33: netting_type | F33: collateral_contract_type | G33: trade_date | H33: value_date | I33: maturity_date | J33: is_replacement | K33: replaced_agreement_id | L33: settlement_currency | M33: created_at | N33: updated_at | O33: agreement_status
A34: =RRP_1_V4_Sep25!B31 -> GMRA_2023_BB | B34: =RRP_1_V4_Sep25!C31 -> 101 | C34: =RRP_1_V4_Sep25!D31 -> 20001 | D34: =RRP_1_V4_Sep25!E31 -> GMRA | E34: =RRP_1_V4_Sep25!F31 -> COLLATERAL | F34: =RRP_1_V4_Sep25!G31 -> REP | G34: =RRP_1_V4_Sep25!H31 -> 45823 | H34: =RRP_1_V4_Sep25!I31 -> 45839 | ... O34: =RRP_1_V4_Sep25!P31 -> Active
A35: =RRP_2_V4_Sep25!B31 -> GMRA_2023_KB | B35: =RRP_2_V4_Sep25!C31 -> 102 | C35: =RRP_2_V4_Sep25!D31 -> 20002 | D35: =RRP_2_V4_Sep25!E31 -> GMRA | E35: =RRP_2_V4_Sep25!F31 -> COLLATERAL | F35: =RRP_2_V4_Sep25!G31 -> REP | G35: =RRP_2_V4_Sep25!H31 -> 45823 | H35: =RRP_2_V4_Sep25!I31 -> 45839 | ... O35: =RRP_2_V4_Sep25!P31 -> Active
A36: =Repo_1_V4_Sep25!B25 -> GMRA_2023_KT | B36: =Repo_1_V4_Sep25!C25 -> 103 | C36: =Repo_1_V4_Sep25!D25 -> 20003 | D36: =Repo_1_V4_Sep25!E25 -> GMRA | E36: =Repo_1_V4_Sep25!F25 -> COLLATERAL | F36: =Repo_1_V4_Sep25!G25 -> REP | G36: =Repo_1_V4_Sep25!H25 -> 45823 | H36: =Repo_1_V4_Sep25!I25 -> 45839 | ... O36: =Repo_1_V4_Sep25!P25 -> Active
A37: =Repo_2_V4_Sep25!B25 -> GMRA_2024_KB | B37: =Repo_2_V4_Sep25!C25 -> 102 | C37: =Repo_2_V4_Sep25!D25 -> 20004 | D37: =Repo_2_V4_Sep25!E25 -> GMRA | E37: =Repo_2_V4_Sep25!F25 -> COLLATERAL | F37: =Repo_2_V4_Sep25!G25 -> REP | G37: =Repo_2_V4_Sep25!H25 -> 45823 | H37: =Repo_2_V4_Sep25!I25 -> 45839 | ... O37: =Repo_2_V4_Sep25!P25 -> Active
A40: limit_utilization
A41: {=TRANSPOSE('All Table_V4_Clean'!A340:A350)} -> limit_id | B41: counterparty_id | C41: limit_type | D41: currency | E41: available_line | F41: total_credit_line | G41: utilization_amount | H41: credit_line_approve_date | I41: timestamp | J41: created_date | K41: entity_id
A42: =RRP_1_V4_Sep25!B25 -> 1001 | B42: =RRP_1_V4_Sep25!C25 -> 101 | C42: =RRP_1_V4_Sep25!D25 -> REPO_LIMIT | D42: =RRP_1_V4_Sep25!E25 -> THB | E42: =RRP_1_V4_Sep25!F25 -> 800000000 | F42: =RRP_1_V4_Sep25!G25 -> 1000000000 | G42: =RRP_1_V4_Sep25!H25 -> 200000000 | H42: =RRP_1_V4_Sep25!I25 -> 45782 | ... K42: =RRP_1_V4_Sep25!L25 -> BBL0107536000374
A43: =RRP_2_V4_Sep25!B25 -> 1002 | B43: =RRP_2_V4_Sep25!C25 -> 102 | C43: =RRP_2_V4_Sep25!D25 -> REPO_LIMIT | D43: =RRP_2_V4_Sep25!E25 -> THB | E43: =RRP_2_V4_Sep25!F25 -> 900000000 | F43: =RRP_2_V4_Sep25!G25 -> 1000000000 | G43: =RRP_2_V4_Sep25!H25 -> 300000000 | H43: =RRP_2_V4_Sep25!I25 -> 45782 | ... K43: =RRP_2_V4_Sep25!L25 -> KBANK0107536000315
A44: ='IB Lend_V4_Sep25'!A135 -> 2001 | B44: ='IB Lend_V4_Sep25'!B135 -> 101 | C44: ='IB Lend_V4_Sep25'!C135 -> PLACEMENT_LIMIT | D44: ='IB Lend_V4_Sep25'!D135 -> THB | E44: ='IB Lend_V4_Sep25'!E135 -> 500000000 | F44: ='IB Lend_V4_Sep25'!F135 -> 1000000000 | G44: ='IB Lend_V4_Sep25'!G135 -> 500000000 | H44: ='IB Lend_V4_Sep25'!H135 -> 45901 | ... K44: ='IB Lend_V4_Sep25'!K135 -> BBL0107536000374
A45: ='IB Lend_V4_Sep25'!A136 -> 2002 | B45: ='IB Lend_V4_Sep25'!B136 -> 104 | C45: ='IB Lend_V4_Sep25'!C136 -> PLACEMENT_LIMIT | D45: ='IB Lend_V4_Sep25'!D136 -> THB | E45: ='IB Lend_V4_Sep25'!E136 -> 400000000 | F45: ='IB Lend_V4_Sep25'!F136 -> 500000000 | G45: ='IB Lend_V4_Sep25'!G136 -> 100000000 | H45: ='IB Lend_V4_Sep25'!H136 -> 45828 | ... K45: ='IB Lend_V4_Sep25'!K136 -> CIMB0107537002338
A48: repo_trades
A49: {=TRANSPOSE('All Table_V4_Clean'!A146:A171)} -> repo_trade_id | B49: trade_date | C49: trade_type | D49: counterparty_id | E49: netting_agreement_id | F49: netting_set_id | G49: nominal_amount | H49: purchase_date | I49: repurchase_date | J49: purchase_price | K49: repurchase_price | L49: currency | M49: reference_rate_id | N49: interest_rate_type | O49: interest_rate | P49: reference_rate | Q49: margin | R49: day_count_convention | S49: repo_rate | T49: term | U49: repo_out_flag | V49: repo_in_flag | W49: status | X49: limit_id | Y49: accrued_interest | Z49: entity_id
A50: =RRP_1_V4_Sep25!B123 -> 70001 | B50: =RRP_1_V4_Sep25!C123 -> 45905.583 | C50: =RRP_1_V4_Sep25!D123 -> Reverse REPO | D50: =RRP_1_V4_Sep25!E123 -> 101 | E50: =RRP_1_V4_Sep25!F123 -> GMRA_2023_BB | F50: =RRP_1_V4_Sep25!G123 -> 20001 | G50: =RRP_1_V4_Sep25!H123 -> 200000000 | H50: =RRP_1_V4_Sep25!I123 -> 45908 | ... Z50: =RRP_1_V4_Sep25!AA123 -> BBL0107536000374
A51: =RRP_2_V4_Sep25!B125 -> 70002 | B51: =RRP_2_V4_Sep25!C125 -> 45905.583 | C51: =RRP_2_V4_Sep25!D125 -> Reverse REPO | D51: =RRP_2_V4_Sep25!E125 -> 102 | E51: =RRP_2_V4_Sep25!F125 -> GMRA_2023_KB | F51: =RRP_2_V4_Sep25!G125 -> 20002 | G51: =RRP_2_V4_Sep25!H125 -> 300000000 | H51: =RRP_2_V4_Sep25!I125 -> 45929 | ... Z51: =RRP_2_V4_Sep25!AA125 -> KBANK0107536000315
A52: =Repo_1_V4_Sep25!B107 -> 70003 | B52: =Repo_1_V4_Sep25!C107 -> 45922.417 | C52: =Repo_1_V4_Sep25!D107 -> REPO | D52: =Repo_1_V4_Sep25!E107 -> 103 | E52: =Repo_1_V4_Sep25!F107 -> GMRA_2023_KT | F52: =Repo_1_V4_Sep25!G107 -> 20003 | G52: =Repo_1_V4_Sep25!H107 -> 50000000 | H52: =Repo_1_V4_Sep25!I107 -> 45924 | ... Z52: =Repo_1_V4_Sep25!AA107 -> KTB107537000882
A53: =Repo_2_V4_Sep25!B113 -> 70004 | B53: =Repo_2_V4_Sep25!C113 -> 45924.417 | C53: =Repo_2_V4_Sep25!D113 -> REPO | D53: =Repo_2_V4_Sep25!E113 -> 102 | E53: =Repo_2_V4_Sep25!F113 -> GMRA_2024_KB | F53: =Repo_2_V4_Sep25!G113 -> 20004 | G53: =Repo_2_V4_Sep25!H113 -> 30000000 | H53: =Repo_2_V4_Sep25!I113 -> 45926 | ... Z53: =Repo_2_V4_Sep25!AA113 -> KBANK0107536000315
A56: collateral_positions
A57: {=TRANSPOSE('All Table_V4_Clean'!A177:A187)} -> collateral_id | B57: repo_trade_id | C57: security_id | D57: nominal_amount | E57: allocation_date | F57: valuation_price | G57: market_value | H57: haircut_percentage | I57: collateral_value_after_haircut | J57: margin_call_id | K57: currency
A58: =RRP_1_V4_Sep25!B66 -> 70001_LB29DA_1 | B58: =RRP_1_V4_Sep25!C66 -> 70001 | C58: =RRP_1_V4_Sep25!D66 -> LB29DA | D58: =RRP_1_V4_Sep25!E66 -> 205000000 | E58: =RRP_1_V4_Sep25!F66 -> 45908 | F58: =RRP_1_V4_Sep25!G66 -> 99.85 | G58: =RRP_1_V4_Sep25!H66 -> 204692500 | H58: =RRP_1_V4_Sep25!I66 -> 2 | ... K58: =RRP_1_V4_Sep25!L66 -> THB
A59: =RRP_2_V4_Sep25!B66 -> 70002_LB28DA_1 | B59: =RRP_2_V4_Sep25!C66 -> 70002 | C59: =RRP_2_V4_Sep25!D66 -> LB28DA | D59: =RRP_2_V4_Sep25!E66 -> 305000000 | E59: =RRP_2_V4_Sep25!F66 -> 45929 | F59: =RRP_2_V4_Sep25!G66 -> 100.1 | G59: =RRP_2_V4_Sep25!H66 -> 305305000 | H59: =RRP_2_V4_Sep25!I66 -> 2 | ... K59: =RRP_2_V4_Sep25!L66 -> THB
A60: =Repo_1_V4_Sep25!B60 -> 70003_LB616A_1 | B60: =Repo_1_V4_Sep25!C60 -> 70003 | C60: =Repo_1_V4_Sep25!D60 -> LB616A | D60: =Repo_1_V4_Sep25!E60 -> 50000000 | E60: =Repo_1_V4_Sep25!F60 -> 45924 | F60: =Repo_1_V4_Sep25!G60 -> 170.81 | G60: =Repo_1_V4_Sep25!H60 -> 85405000 | H60: =Repo_1_V4_Sep25!I60 -> 2 | ... K60: =Repo_1_V4_Sep25!L60 -> THB
A61: =Repo_2_V4_Sep25!B60 -> 70004_BOT25NA_1 | B61: =Repo_2_V4_Sep25!C60 -> 70004 | C61: =Repo_2_V4_Sep25!D60 -> BOT25NA | D61: =Repo_2_V4_Sep25!E60 -> 30000000 | E61: =Repo_2_V4_Sep25!F60 -> 45926 | F61: =Repo_2_V4_Sep25!G60 -> 100.25761 | G61: =Repo_2_V4_Sep25!H60 -> 30078000 | H61: =Repo_2_V4_Sep25!I60 -> 2 | ... K61: =Repo_2_V4_Sep25!L60 -> THB
A64: bond_trades
A65: {=TRANSPOSE('All Table_V4_Clean'!A193:A203)} -> bond_trade_id | B65: portfolio_id | C65: trade_date | D65: settlement_date | E65: security_id | F65: counterparty_id | G65: trade_type | H65: nominal_amount | I65: clean_price_trade | J65: yield_to_maturity | K65: settlement_status
A66: ='Bond Buy-Sell_V4_Sep25 + Oct25'!A148 -> 90001 | B66: ='Bond Buy-Sell_V4_Sep25 + Oct25'!B148 -> 403 | C66: ='Bond Buy-Sell_V4_Sep25 + Oct25'!C148 -> 45659 | D66: ='Bond Buy-Sell_V4_Sep25 + Oct25'!D148 -> 45663 | E66: ='Bond Buy-Sell_V4_Sep25 + Oct25'!E148 -> EXIM266A | F66: ='Bond Buy-Sell_V4_Sep25 + Oct25'!F148 -> 101 | G66: ='Bond Buy-Sell_V4_Sep25 + Oct25'!G148 -> Buy | H66: ='Bond Buy-Sell_V4_Sep25 + Oct25'!H148 -> 100000000 | ... K66: ='Bond Buy-Sell_V4_Sep25 + Oct25'!K148 -> Settled
A67: ='Bond Buy-Sell_V4_Sep25 + Oct25'!A149 -> 90002 | B67: ='Bond Buy-Sell_V4_Sep25 + Oct25'!B149 -> 403 | C67: ='Bond Buy-Sell_V4_Sep25 + Oct25'!C149 -> 45726 | D67: ='Bond Buy-Sell_V4_Sep25 + Oct25'!D149 -> 45728 | E67: ='Bond Buy-Sell_V4_Sep25 + Oct25'!E149 -> EXIM266A | F67: ='Bond Buy-Sell_V4_Sep25 + Oct25'!F149 -> 101 | G67: ='Bond Buy-Sell_V4_Sep25 + Oct25'!G149 -> Buy | H67: ='Bond Buy-Sell_V4_Sep25 + Oct25'!H149 -> 50000000 | ... K67: ='Bond Buy-Sell_V4_Sep25 + Oct25'!K149 -> Settled
A68: ='Bond Buy-Sell_V4_Sep25 + Oct25'!A150 -> 90003 | B68: ='Bond Buy-Sell_V4_Sep25 + Oct25'!B150 -> 403 | C68: ='Bond Buy-Sell_V4_Sep25 + Oct25'!C150 -> 45915 | D68: ='Bond Buy-Sell_V4_Sep25 + Oct25'!D150 -> 45917 | E68: ='Bond Buy-Sell_V4_Sep25 + Oct25'!E150 -> EXIM266A | F68: ='Bond Buy-Sell_V4_Sep25 + Oct25'!F150 -> 101 | G68: ='Bond Buy-Sell_V4_Sep25 + Oct25'!G150 -> Sell | H68: ='Bond Buy-Sell_V4_Sep25 + Oct25'!H150 -> 100000000 | ... K68: ='Bond Buy-Sell_V4_Sep25 + Oct25'!K150 -> Settled
A69: ='Bond buy_1_V4_Sep25'!B65 -> 90004 | B69: ='Bond buy_1_V4_Sep25'!C65 -> 403 | C69: ='Bond buy_1_V4_Sep25'!D65 -> 45854.458 | D69: ='Bond buy_1_V4_Sep25'!E65 -> 45856.458 | E69: ='Bond buy_1_V4_Sep25'!F65 -> GSB26OA | F69: ='Bond buy_1_V4_Sep25'!G65 -> 102 | G69: ='Bond buy_1_V4_Sep25'!H65 -> Buy | H69: ='Bond buy_1_V4_Sep25'!I65 -> 100000000 | ... K69: ='Bond buy_1_V4_Sep25'!L65 -> Settled
A70: ='Bond buy_1_V4_Sep25'!B66 -> 90005 | B70: ='Bond buy_1_V4_Sep25'!C66 -> 301 | C70: ='Bond buy_1_V4_Sep25'!D66 -> 45917.458 | D70: ='Bond buy_1_V4_Sep25'!E66 -> 45919.458 | E70: ='Bond buy_1_V4_Sep25'!F66 -> LB616A | F70: ='Bond buy_1_V4_Sep25'!G66 -> 101 | G70: ='Bond buy_1_V4_Sep25'!H66 -> Buy | H70: ='Bond buy_1_V4_Sep25'!I66 -> 100000000 | ... K70: ='Bond buy_1_V4_Sep25'!L66 -> Settled
A71: ='Bond buy_1_V4_Sep25'!B67 -> 90006 | B71: ='Bond buy_1_V4_Sep25'!C67 -> 302 | C71: ='Bond buy_1_V4_Sep25'!D67 -> 45917.458 | D71: ='Bond buy_1_V4_Sep25'!E67 -> 45919.458 | E71: ='Bond buy_1_V4_Sep25'!F67 -> TB26128A | F71: ='Bond buy_1_V4_Sep25'!G67 -> 101 | G71: ='Bond buy_1_V4_Sep25'!H67 -> Buy | H71: ='Bond buy_1_V4_Sep25'!I67 -> 100000000 | ... K71: ='Bond buy_1_V4_Sep25'!L67 -> Settled
A72: ='Bond buy_1_V4_Sep25'!B68 -> 90007 | B72: ='Bond buy_1_V4_Sep25'!C68 -> 303 | C72: ='Bond buy_1_V4_Sep25'!D68 -> 45917.458 | D72: ='Bond buy_1_V4_Sep25'!E68 -> 45919.458 | E72: ='Bond buy_1_V4_Sep25'!F68 -> BOT25NA | F72: ='Bond buy_1_V4_Sep25'!G68 -> 101 | G72: ='Bond buy_1_V4_Sep25'!H68 -> Buy | H72: ='Bond buy_1_V4_Sep25'!I68 -> 100000000 | ... K72: ='Bond buy_1_V4_Sep25'!L68 -> Settled
A73: ='Bond buy_1_V4_Sep25'!B69 -> 90008 | B73: ='Bond buy_1_V4_Sep25'!C69 -> 401 | C73: ='Bond buy_1_V4_Sep25'!D69 -> 45917.458 | D73: ='Bond buy_1_V4_Sep25'!E69 -> 45919.458 | E73: ='Bond buy_1_V4_Sep25'!F69 -> TB26211A | F73: ='Bond buy_1_V4_Sep25'!G69 -> 102 | G73: ='Bond buy_1_V4_Sep25'!H69 -> Buy | H73: ='Bond buy_1_V4_Sep25'!I69 -> 100000000 | ... K73: ='Bond buy_1_V4_Sep25'!L69 -> Settled
A74: ='Bond buy_1_V4_Sep25'!B70 -> 90009 | B74: ='Bond buy_1_V4_Sep25'!C70 -> 402 | C74: ='Bond buy_1_V4_Sep25'!D70 -> 45917.458 | D74: ='Bond buy_1_V4_Sep25'!E70 -> 45919.458 | E74: ='Bond buy_1_V4_Sep25'!F70 -> BOTF267A | F74: ='Bond buy_1_V4_Sep25'!G70 -> 102 | G74: ='Bond buy_1_V4_Sep25'!H70 -> Buy | H74: ='Bond buy_1_V4_Sep25'!I70 -> 100000000 | ... K74: ='Bond buy_1_V4_Sep25'!L70 -> Settled
A77: bond_transactions
A78: {=TRANSPOSE('All Table_V4_Clean'!A209:A238)} -> trade_id | B78: security_id | C78: portfolio_id | D78: counterparty_id | E78: trade_type | F78: trade_date | G78: settlement_date | H78: maturity_date | I78: currency | J78: nominal_amount | K78: clean_price | L78: clean_price_trade | M78: accrued_interest | N78: dirty_price | O78: classification | P78: book_value | Q78: market_clean_value | R78: market_value | S78: last_coupon_date | T78: coupon_rate_type | U78: coupon_reference_rate | V78: coupon_margin | W78: coupon_frequency | X78: coupon_rate | Y78: coupon_day_count_conv | Z78: rating_tris | AA78: rating_fitch | AB78: status | AC78: last_updated_timestamp | AD78: valuation_date
A79: ='Bond Buy-Sell_V4_Sep25 + Oct25'!A189 -> 90001 | B79: ='Bond Buy-Sell_V4_Sep25 + Oct25'!B189 -> EXIM266A | C79: ='Bond Buy-Sell_V4_Sep25 + Oct25'!C189 -> 403 | D79: ='Bond Buy-Sell_V4_Sep25 + Oct25'!D189 -> 101 | E79: ='Bond Buy-Sell_V4_Sep25 + Oct25'!E189 -> Buy | F79: ='Bond Buy-Sell_V4_Sep25 + Oct25'!F189 -> 45659 | G79: ='Bond Buy-Sell_V4_Sep25 + Oct25'!G189 -> 45663 | H79: ='Bond Buy-Sell_V4_Sep25 + Oct25'!H189 -> 46179 | ... AD79: ='Bond Buy-Sell_V4_Sep25 + Oct25'!AD189 -> 45930
A80: ='Bond Buy-Sell_V4_Sep25 + Oct25'!A190 -> 90002 | B80: ='Bond Buy-Sell_V4_Sep25 + Oct25'!B190 -> EXIM266A | C80: ='Bond Buy-Sell_V4_Sep25 + Oct25'!C190 -> 403 | D80: ='Bond Buy-Sell_V4_Sep25 + Oct25'!D190 -> 101 | E80: ='Bond Buy-Sell_V4_Sep25 + Oct25'!E190 -> Buy | F80: ='Bond Buy-Sell_V4_Sep25 + Oct25'!F190 -> 45726 | G80: ='Bond Buy-Sell_V4_Sep25 + Oct25'!G190 -> 45728 | H80: ='Bond Buy-Sell_V4_Sep25 + Oct25'!H190 -> 46179 | ... AD80: ='Bond Buy-Sell_V4_Sep25 + Oct25'!AD190 -> 45930
A81: ='Bond Buy-Sell_V4_Sep25 + Oct25'!A191 -> 90003 | B81: ='Bond Buy-Sell_V4_Sep25 + Oct25'!B191 -> EXIM266A | C81: ='Bond Buy-Sell_V4_Sep25 + Oct25'!C191 -> 403 | D81: ='Bond Buy-Sell_V4_Sep25 + Oct25'!D191 -> 101 | E81: ='Bond Buy-Sell_V4_Sep25 + Oct25'!E191 -> Sell | F81: ='Bond Buy-Sell_V4_Sep25 + Oct25'!F191 -> 45915 | G81: ='Bond Buy-Sell_V4_Sep25 + Oct25'!G191 -> 45917 | H81: ='Bond Buy-Sell_V4_Sep25 + Oct25'!H191 -> 46179 | ... AD81: ='Bond Buy-Sell_V4_Sep25 + Oct25'!AD191 -> 45930
A82: ='Bond buy_1_V4_Sep25'!B107 -> 90004 | B82: ='Bond buy_1_V4_Sep25'!C107 -> GSB26OA | C82: ='Bond buy_1_V4_Sep25'!D107 -> 403 | D82: ='Bond buy_1_V4_Sep25'!E107 -> 102 | E82: ='Bond buy_1_V4_Sep25'!F107 -> Buy | F82: ='Bond buy_1_V4_Sep25'!G107 -> 45854 | G82: ='Bond buy_1_V4_Sep25'!H107 -> 45856 | H82: ='Bond buy_1_V4_Sep25'!I107 -> 46311 | ... AD82: ='Bond buy_1_V4_Sep25'!AE107 -> 45930
A83: ='Bond buy_1_V4_Sep25'!B108 -> 90005 | B83: ='Bond buy_1_V4_Sep25'!C108 -> LB616A | C83: ='Bond buy_1_V4_Sep25'!D108 -> 301 | D83: ='Bond buy_1_V4_Sep25'!E108 -> 101 | E83: ='Bond buy_1_V4_Sep25'!F108 -> Buy | F83: ='Bond buy_1_V4_Sep25'!G108 -> 45917 | G83: ='Bond buy_1_V4_Sep25'!H108 -> 45919 | H83: ='Bond buy_1_V4_Sep25'!I108 -> 58974 | ... AD83: ='Bond buy_1_V4_Sep25'!AE108 -> 45930
A84: ='Bond buy_1_V4_Sep25'!B109 -> 90006 | B84: ='Bond buy_1_V4_Sep25'!C109 -> TB26128A | C84: ='Bond buy_1_V4_Sep25'!D109 -> 302 | D84: ='Bond buy_1_V4_Sep25'!E109 -> 101 | E84: ='Bond buy_1_V4_Sep25'!F109 -> Buy | F84: ='Bond buy_1_V4_Sep25'!G109 -> 45917 | G84: ='Bond buy_1_V4_Sep25'!H109 -> 45919 | H84: ='Bond buy_1_V4_Sep25'!I109 -> 46050 | ... AD84: ='Bond buy_1_V4_Sep25'!AE109 -> 45930
A85: ='Bond buy_1_V4_Sep25'!B110 -> 90007 | B85: ='Bond buy_1_V4_Sep25'!C110 -> BOT25NA | C85: ='Bond buy_1_V4_Sep25'!D110 -> 303 | D85: ='Bond buy_1_V4_Sep25'!E110 -> 101 | E85: ='Bond buy_1_V4_Sep25'!F110 -> Buy | F85: ='Bond buy_1_V4_Sep25'!G110 -> 45917 | G85: ='Bond buy_1_V4_Sep25'!H110 -> 45919 | H85: ='Bond buy_1_V4_Sep25'!I110 -> 45967 | ... AD85: ='Bond buy_1_V4_Sep25'!AE110 -> 45930
A86: ='Bond buy_1_V4_Sep25'!B111 -> 90008 | B86: ='Bond buy_1_V4_Sep25'!C111 -> TB26211A | C86: ='Bond buy_1_V4_Sep25'!D111 -> 401 | D86: ='Bond buy_1_V4_Sep25'!E111 -> 102 | E86: ='Bond buy_1_V4_Sep25'!F111 -> Buy | F86: ='Bond buy_1_V4_Sep25'!G111 -> 45917 | G86: ='Bond buy_1_V4_Sep25'!H111 -> 45919 | H86: ='Bond buy_1_V4_Sep25'!I111 -> 46064 | ... AD86: ='Bond buy_1_V4_Sep25'!AE111 -> 45930
A87: ='Bond buy_1_V4_Sep25'!B112 -> 90009 | B87: ='Bond buy_1_V4_Sep25'!C112 -> BOTF267A | C87: ='Bond buy_1_V4_Sep25'!D112 -> 402 | D87: ='Bond buy_1_V4_Sep25'!E112 -> 102 | E87: ='Bond buy_1_V4_Sep25'!F112 -> Buy | F87: ='Bond buy_1_V4_Sep25'!G112 -> 45917 | G87: ='Bond buy_1_V4_Sep25'!H112 -> 45919 | H87: ='Bond buy_1_V4_Sep25'!I112 -> 46204 | ... AD87: ='Bond buy_1_V4_Sep25'!AE112 -> 45930
A88: =RRP_1_V4_Sep25!B129 -> 70001 | B88: =RRP_1_V4_Sep25!C129 -> LB29DA | C88: =RRP_1_V4_Sep25!D129 -> 301 | D88: =RRP_1_V4_Sep25!E129 -> 101 | E88: =RRP_1_V4_Sep25!F129 -> ReverseRepo | F88: =RRP_1_V4_Sep25!G129 -> 45905 | G88: =RRP_1_V4_Sep25!H129 -> 45908 | H88: =RRP_1_V4_Sep25!I129 -> 45915 | ... AD88: =RRP_1_V4_Sep25!AE129 -> 45930
A89: =RRP_2_V4_Sep25!B131 -> 70002 | B89: =RRP_2_V4_Sep25!C131 -> LB28DA | C89: =RRP_2_V4_Sep25!D131 -> 302 | D89: =RRP_2_V4_Sep25!E131 -> 102 | E89: =RRP_2_V4_Sep25!F131 -> ReverseRepo | F89: =RRP_2_V4_Sep25!G131 -> 45926 | G89: =RRP_2_V4_Sep25!H131 -> 45929 | H89: =RRP_2_V4_Sep25!I131 -> 47104 | ... AD89: =RRP_2_V4_Sep25!AE131 -> 45930
A90: =Repo_1_V4_Sep25!B113 -> 70003 | B90: =Repo_1_V4_Sep25!C113 -> LB616A | C90: =Repo_1_V4_Sep25!D113 -> 301 | D90: =Repo_1_V4_Sep25!E113 -> 103 | E90: =Repo_1_V4_Sep25!F113 -> Repo | F90: =Repo_1_V4_Sep25!G113 -> 45922 | G90: =Repo_1_V4_Sep25!H113 -> 45924 | H90: =Repo_1_V4_Sep25!I113 -> 58983 | ... AD90: =Repo_1_V4_Sep25!AE113 -> 45930
A91: =Repo_2_V4_Sep25!B119 -> 70004 | B91: =Repo_2_V4_Sep25!C119 -> BOT25NA | C91: =Repo_2_V4_Sep25!D119 -> 402 | D91: =Repo_2_V4_Sep25!E119 -> 102 | E91: =Repo_2_V4_Sep25!F119 -> Repo | F91: =Repo_2_V4_Sep25!G119 -> 45924 | G91: =Repo_2_V4_Sep25!H119 -> 45926 | H91: =Repo_2_V4_Sep25!I119 -> 45933 | ... AD91: =Repo_2_V4_Sep25!AE119 -> 45930
A94: margin_calls
A95: {=TRANSPOSE('All Table_V4_Clean'!A302:A311)} -> margin_call_id | B95: counterparty_id | C95: repo_trade_id | D95: valuation_date | E95: call_currency | F95: call_type | G95: call_amount | H95: due_time | I95: status | J95: created_timestamp
A96: =RRP_1_V4_Sep25!B92 -> 1 | B96: =RRP_1_V4_Sep25!C92 -> 101 | C96: =RRP_1_V4_Sep25!D92 -> 70001 | D96: =RRP_1_V4_Sep25!E92 -> 45909 | E96: =RRP_1_V4_Sep25!F92 -> THB | F96: =RRP_1_V4_Sep25!G92 -> CALL | G96: =RRP_1_V4_Sep25!H92 -> 2100000 | H96: =RRP_1_V4_Sep25!I92 -> 45909.625 | ... J96: =RRP_1_V4_Sep25!K92 -> 45909.625
A97: =RRP_2_V4_Sep25!B92 -> 2 | B97: =RRP_2_V4_Sep25!C92 -> 102 | C97: =RRP_2_V4_Sep25!D92 -> 70002 | D97: =RRP_2_V4_Sep25!E92 -> 45930 | E97: =RRP_2_V4_Sep25!F92 -> THB | F97: =RRP_2_V4_Sep25!G92 -> CALL | G97: =RRP_2_V4_Sep25!H92 -> 5500000 | H97: =RRP_2_V4_Sep25!I92 -> 45930.625 | ... J97: =RRP_2_V4_Sep25!K92 -> 45930.625
A98: =Repo_2_V4_Sep25!B86 -> 3 | B98: =Repo_2_V4_Sep25!C86 -> 102 | C98: =Repo_2_V4_Sep25!D86 -> 70004 | D98: =Repo_2_V4_Sep25!E86 -> 45929 | E98: =Repo_2_V4_Sep25!F86 -> THB | F98: =Repo_2_V4_Sep25!G86 -> RETURN | G98: =Repo_2_V4_Sep25!H86 -> 600000 | H98: =Repo_2_V4_Sep25!I86 -> 45929.625 | ... J98: =Repo_2_V4_Sep25!K86 -> 45929.625
A101: cash_margin_movements
A102: {=TRANSPOSE('All Table_V4_Clean'!A317:A334)} -> cash_margin_movement_id | B102: margin_call_id | C102: counterparty_id | D102: repo_trade_id | E102: call_currency | F102: movement_type | G102: amount | H102: outstanding_balance | I102: value_date | J102: created_timestamp | K102: bank_account_code | L102: daily_accrued_int_receivable | M102: accrued_int_receivable | N102: interest_on_margin_code | O102: interest_on_margin_rate | P102: day_count_basis | Q102: accrual_days | R102: interest_direction
A103: =RRP_1_V4_Sep25!B137 -> 1 | B103: =RRP_1_V4_Sep25!C137 -> 1 | C103: =RRP_1_V4_Sep25!D137 -> 101 | D103: =RRP_1_V4_Sep25!E137 -> 70001 | E103: =RRP_1_V4_Sep25!F137 -> THB | F103: =RRP_1_V4_Sep25!G137 -> RECEIVE | G103: =RRP_1_V4_Sep25!H137 -> 2100000 | H103: =RRP_1_V4_Sep25!I137 -> 2100000 | ... R103: =RRP_1_V4_Sep25!S137 -> NONE
A104: =RRP_1_V4_Sep25!B138 -> 2 | B104: =RRP_1_V4_Sep25!C138 -> 1 | C104: =RRP_1_V4_Sep25!D138 -> 101 | D104: =RRP_1_V4_Sep25!E138 -> 70001 | E104: =RRP_1_V4_Sep25!F138 -> THB | F104: =RRP_1_V4_Sep25!G138 -> PAY | G104: =RRP_1_V4_Sep25!H138 -> -2100000 | H104: =RRP_1_V4_Sep25!I138 -> 0 | ... R104: =RRP_1_V4_Sep25!S138 -> NONE
A105: =RRP_2_V4_Sep25!B143 -> 3 | B105: =RRP_2_V4_Sep25!C143 -> 2 | C105: =RRP_2_V4_Sep25!D143 -> 102 | D105: =RRP_2_V4_Sep25!E143 -> 70002 | E105: =RRP_2_V4_Sep25!F143 -> THB | F105: =RRP_2_V4_Sep25!G143 -> RECEIVE | G105: =RRP_2_V4_Sep25!H143 -> 5500000 | H105: =RRP_2_V4_Sep25!I143 -> 5500000 | ... R105: =RRP_2_V4_Sep25!S143 -> NONE
A106: =Repo_2_V4_Sep25!B126 -> 4 | B106: =Repo_2_V4_Sep25!C126 -> 3 | C106: =Repo_2_V4_Sep25!D126 -> 102 | D106: =Repo_2_V4_Sep25!E126 -> 70004 | E106: =Repo_2_V4_Sep25!F126 -> THB | F106: =Repo_2_V4_Sep25!G126 -> PAY | G106: =Repo_2_V4_Sep25!H126 -> -600000 | H106: =Repo_2_V4_Sep25!I126 -> -600000 | ... R106: =Repo_2_V4_Sep25!S126 -> NONE
A109: position_costing
A110: {=TRANSPOSE('All Table_V4_Clean'!A272:A280)} -> costing_id | B110: position_id | C110: cost_method | D110: avg_book_price_pct | E110: sum_product_clean | F110: total_nominal_in | G110: cumulative_sold_nominal | H110: realized_gain_loss_to_date | I110: last_realization_date
A111: ='Bond Buy-Sell_V4_Sep25 + Oct25'!A119 -> 1 | B111: ='Bond Buy-Sell_V4_Sep25 + Oct25'!B119 -> 1 | C111: ='Bond Buy-Sell_V4_Sep25 + Oct25'!C119 -> WAC | D111: ='Bond Buy-Sell_V4_Sep25 + Oct25'!D119 -> 101.28851 | E111: ='Bond Buy-Sell_V4_Sep25 + Oct25'!E119 -> 151932761 | F111: ='Bond Buy-Sell_V4_Sep25 + Oct25'!F119 -> 150000000 | G111: ='Bond Buy-Sell_V4_Sep25 + Oct25'!G119 -> 100000000 | H111: ='Bond Buy-Sell_V4_Sep25 + Oct25'!H119 -> -512562.33 | I111: ='Bond Buy-Sell_V4_Sep25 + Oct25'!I119 -> 45917
A113: position_realization_events
A114: {=TRANSPOSE('All Table_V4_Clean'!A286:A296)} -> realization_id | B114: position_id | C114: trade_id | D114: event_date | E114: sold_nominal | F114: sell_clean_price_pct | G114: avg_book_price_pct | H114: realized_gainloss | I114: accrued_int_realized | J114: method_used | K114: created_at
A115: ='Bond Buy-Sell_V4_Sep25 + Oct25'!A137 -> 1 | B115: ='Bond Buy-Sell_V4_Sep25 + Oct25'!B137 -> 1 | C115: ='Bond Buy-Sell_V4_Sep25 + Oct25'!C137 -> 90003 | D115: ='Bond Buy-Sell_V4_Sep25 + Oct25'!D137 -> 45915 | E115: ='Bond Buy-Sell_V4_Sep25 + Oct25'!E137 -> 100000000 | F115: ='Bond Buy-Sell_V4_Sep25 + Oct25'!F137 -> 100.77594 | G115: ='Bond Buy-Sell_V4_Sep25 + Oct25'!G137 -> 101.28851 | H115: ='Bond Buy-Sell_V4_Sep25 + Oct25'!H137 -> -512562.33 | ... K115: ='Bond Buy-Sell_V4_Sep25 + Oct25'!K137 -> 45915.708
A117: bond_positions
A118: {=TRANSPOSE('All Table_V4_Clean'!A244:A266)} -> position_id | B118: security_id | C118: portfolio_id | D118: open_date | E118: maturity_date | F118: currency | G118: nominal_amount | H118: unencumbrance | I118: encumbrance | J118: unenc_from_reverse_repo | K118: rehypothecation | L118: avg_book_clean_price_pct | M118: book_value | N118: valuation_date | O118: clean_price | P118: accrued_interest | Q118: dirty_price | R118: market_value | S118: realized_gain_loss | T118: unrealized_gain_loss | U118: status | V118: last_updated_timestamp | W118: market_rate
A119: ='Bond Buy-Sell_V4_Sep25 + Oct25'!A198 -> 1 | B119: ='Bond Buy-Sell_V4_Sep25 + Oct25'!B198 -> EXIM266A | C119: ='Bond Buy-Sell_V4_Sep25 + Oct25'!C198 -> 403 | D119: ='Bond Buy-Sell_V4_Sep25 + Oct25'!D198 -> 45663 | E119: ='Bond Buy-Sell_V4_Sep25 + Oct25'!E198 -> 46179 | F119: ='Bond Buy-Sell_V4_Sep25 + Oct25'!F198 -> THB | G119: ='Bond Buy-Sell_V4_Sep25 + Oct25'!G198 -> 50000000 | H119: ='Bond Buy-Sell_V4_Sep25 + Oct25'!H198 -> 50000000 | ... W119: ='Bond Buy-Sell_V4_Sep25 + Oct25'!W198 -> 1.563666
A120: ='Bond buy_1_V4_Sep25'!B118 -> 2 | B120: ='Bond buy_1_V4_Sep25'!C118 -> GSB26OA | C120: ='Bond buy_1_V4_Sep25'!D118 -> 403 | D120: ='Bond buy_1_V4_Sep25'!E118 -> 43754 | E120: ='Bond buy_1_V4_Sep25'!F118 -> 46311 | F120: ='Bond buy_1_V4_Sep25'!G118 -> THB | G120: ='Bond buy_1_V4_Sep25'!H118 -> 100000000 | H120: ='Bond buy_1_V4_Sep25'!I118 -> 100000000 | ... W120: ='Bond buy_1_V4_Sep25'!X118 -> 1.441214
A121: ='Bond buy_1_V4_Sep25'!B119 -> 3 | B121: ='Bond buy_1_V4_Sep25'!C119 -> LB616A | C121: ='Bond buy_1_V4_Sep25'!D119 -> 301 | D121: ='Bond buy_1_V4_Sep25'!E119 -> 40606 | E121: ='Bond buy_1_V4_Sep25'!F119 -> 58974 | F121: ='Bond buy_1_V4_Sep25'!G119 -> THB | G121: ='Bond buy_1_V4_Sep25'!H119 -> 100000000 | H121: ='Bond buy_1_V4_Sep25'!I119 -> 100000000 | ... W121: ='Bond buy_1_V4_Sep25'!X119 -> 2.19452
A122: ='Bond buy_1_V4_Sep25'!B120 -> 4 | B122: ='Bond buy_1_V4_Sep25'!C120 -> TB26128A | C122: ='Bond buy_1_V4_Sep25'!D120 -> 302 | D122: ='Bond buy_1_V4_Sep25'!E120 -> 45868 | E122: ='Bond buy_1_V4_Sep25'!F120 -> 46050 | F122: ='Bond buy_1_V4_Sep25'!G120 -> THB | G122: ='Bond buy_1_V4_Sep25'!H120 -> 100000000 | H122: ='Bond buy_1_V4_Sep25'!I120 -> 100000000 | ... W122: ='Bond buy_1_V4_Sep25'!X120 -> 1.172568
A123: ='Bond buy_1_V4_Sep25'!B121 -> 5 | B123: ='Bond buy_1_V4_Sep25'!C121 -> BOT25NA | C123: ='Bond buy_1_V4_Sep25'!D121 -> 303 | D123: ='Bond buy_1_V4_Sep25'!E121 -> 45236 | E123: ='Bond buy_1_V4_Sep25'!F121 -> 45967 | F123: ='Bond buy_1_V4_Sep25'!G121 -> THB | G123: ='Bond buy_1_V4_Sep25'!H121 -> 100000000 | H123: ='Bond buy_1_V4_Sep25'!I121 -> 70000000 | ... W123: ='Bond buy_1_V4_Sep25'!X121 -> 1.25
...

Sheet V4_Result_31 Oct 2025
A1: Export as of | B1: =DATE(2025,10,31) -> 45961 | D1: Timestamp update as of | E1: 46037.666
A3: ='V4_Result_30 Sep 2025'!A3 -> counterparty_master
A4: {=TRANSPOSE('All Table_V4_Clean'!A25:A39)} -> entity_id | B4: counterparty_id | C4: legal_name | D4: short_code | E4: counterparty_type | F4: bank_code | G4: swift_bic | H4: primary_credit_rating | I4: primary_rating_agency | J4: primary_rating_date | K4: created_date | L4: last_updated_date | M4: involved_party_type | N4: customer_code | O4: reside_in_thailand_flag
A5: =RRP_1_V4_Sep25!B13 -> BBL0107536000374 | B5: =RRP_1_V4_Sep25!C13 -> 101 | C5: =RRP_1_V4_Sep25!D13 -> BANGKOK BANK PCL | D5: =RRP_1_V4_Sep25!E13 -> BBL | E5: =RRP_1_V4_Sep25!F13 -> Commercial Bank | F5: =RRP_1_V4_Sep25!G13 -> 002 | G5: =RRP_1_V4_Sep25!H13 -> BKKBTHBK | H5: =RRP_1_V4_Sep25!I13 -> AA- | ... M5: =RRP_1_V4_Sep25!N13 -> 176039 | N5: 2008 | O5: TRUE
A6: =RRP_2_V4_Sep25!B13 -> KBANK0107536000315 | B6: =RRP_2_V4_Sep25!C13 -> 102 | C6: =RRP_2_V4_Sep25!D13 -> KASIKORNBANK PCL | D6: =RRP_2_V4_Sep25!E13 -> KBANK | E6: =RRP_2_V4_Sep25!F13 -> Commercial Bank | F6: =RRP_2_V4_Sep25!G13 -> 004 | G6: =RRP_2_V4_Sep25!H13 -> KASITHBK | H6: =RRP_2_V4_Sep25!I13 -> AA | ... M6: =RRP_2_V4_Sep25!N13 -> 176039 | N6: 2008 | O6: TRUE
A7: =Repo_1_V4_Sep25!B13 -> KTB107537000882 | B7: =Repo_1_V4_Sep25!C13 -> 103 | C7: =Repo_1_V4_Sep25!D13 -> KRUNGTHAI BANK PCL | D7: =Repo_1_V4_Sep25!E13 -> KTB | E7: =Repo_1_V4_Sep25!F13 -> Commercial Bank | F7: =Repo_1_V4_Sep25!G13 -> 006 | G7: =Repo_1_V4_Sep25!H13 -> KRTHTHBK | H7: =Repo_1_V4_Sep25!I13 -> AA+ | ... M7: =Repo_1_V4_Sep25!N13 -> 176039 | N7: 2008 | O7: TRUE
A8: ='IB Lend_V4_Oct25'!A12 -> CIMB0107537002338 | B8: ='IB Lend_V4_Oct25'!B12 -> 104 | C8: ='IB Lend_V4_Oct25'!C12 -> CIMB THAI BANK PCL | D8: ='IB Lend_V4_Oct25'!D12 -> CIMB | E8: ='IB Lend_V4_Oct25'!E12 -> Commercial Bank | F8: ='IB Lend_V4_Oct25'!F12 -> 022 | G8: ='IB Lend_V4_Oct25'!G12 -> UBOBTHBK | H8: ='IB Lend_V4_Oct25'!H12 -> AA(THA) | ... M8: ='IB Lend_V4_Oct25'!M12 -> 176039 | N8: 2008 | O8: TRUE
A9: ='IB Lend_V4_Oct25'!A11 -> SCB0107536000102 | B9: ='IB Lend_V4_Oct25'!B11 -> 113 | C9: ='IB Lend_V4_Oct25'!C11 -> SIAM COMMERCIAL BANK PCL | D9: ='IB Lend_V4_Oct25'!D11 -> SCB | E9: ='IB Lend_V4_Oct25'!E11 -> Commercial Bank | F9: ='IB Lend_V4_Oct25'!F11 -> 084 | G9: ='IB Lend_V4_Oct25'!G11 -> SICOTHBK | H9: ='IB Lend_V4_Oct25'!H11 -> AA+(THA) | ... M9: ='IB Lend_V4_Oct25'!M11 -> 176039 | N9: 2008 | O9: TRUE
A11: ='V4_Result_30 Sep 2025'!A10 -> security_master
A12: {=TRANSPOSE('All Table_V4_Clean'!A46:A68)} -> security_id | B12: isin | C12: issuer_id | D12: unique_id | E12: instrument_type | F12: issue_date | G12: maturity_date | H12: coupon_rate | I12: coupon_margin | J12: coupon_reference_rate | K12: coupon_frequency | L12: coupon_day_count_conv | M12: currency | N12: country | O12: bond_structure | P12: rating_tris | Q12: rating_fitch | R12: is_eligible_bot_repo_collateral | S12: is_eligible_crm_collateral | T12: status | U12: status_timestamp | V12: coupon_rate_type | W12: cross_default
A13: ='Bond buy_1_V4_Sep25'!B21 -> GSB26OA | B13: ='Bond buy_1_V4_Sep25'!C21 -> TH1029036A07 | C13: ='Bond buy_1_V4_Sep25'!D21 -> 3 | D13: ='Bond buy_1_V4_Sep25'!E21 -> 176017 | E13: ='Bond buy_1_V4_Sep25'!F21 -> SOE Bond | F13: ='Bond buy_1_V4_Sep25'!G21 -> 43754 | G13: ='Bond buy_1_V4_Sep25'!H21 -> 46311 | H13: ='Bond buy_1_V4_Sep25'!I21 -> 1.69 | ... V13: ='Bond buy_1_V4_Sep25'!W21 -> Fixed | W13: FALSE
A14: ='Bond buy_1_V4_Sep25'!B22 -> LB616A | B14: ='Bond buy_1_V4_Sep25'!C22 -> TH0623B3B607 | C14: ='Bond buy_1_V4_Sep25'!D22 -> 1 | D14: ='Bond buy_1_V4_Sep25'!E22 -> 176015 | E14: ='Bond buy_1_V4_Sep25'!F22 -> Gov Bond | F14: ='Bond buy_1_V4_Sep25'!G22 -> 40606 | G14: ='Bond buy_1_V4_Sep25'!H22 -> 58974 | H14: ='Bond buy_1_V4_Sep25'!I22 -> 4.85 | ... V14: ='Bond buy_1_V4_Sep25'!W22 -> Fixed | W14: FALSE
A15: ='Bond buy_1_V4_Sep25'!B23 -> TB26128A | B15: ='Bond buy_1_V4_Sep25'!C23 -> TH0623A76183 | C15: ='Bond buy_1_V4_Sep25'!D23 -> 1 | D15: ='Bond buy_1_V4_Sep25'!E23 -> 176015 | E15: ='Bond buy_1_V4_Sep25'!F23 -> T-Bill | F15: ='Bond buy_1_V4_Sep25'!G23 -> 45868 | G15: ='Bond buy_1_V4_Sep25'!H23 -> 46050 | H15: ='Bond buy_1_V4_Sep25'!I23 -> 0 | ... V15: ='Bond buy_1_V4_Sep25'!W23 -> Fixed | W15: FALSE
A16: ='Bond buy_1_V4_Sep25'!B24 -> BOT25NA | B16: ='Bond buy_1_V4_Sep25'!C24 -> TH0655035B00 | C16: ='Bond buy_1_V4_Sep25'!D24 -> 2 | D16: ='Bond buy_1_V4_Sep25'!E24 -> 001 | E16: ='Bond buy_1_V4_Sep25'!F24 -> BOT Bond | F16: ='Bond buy_1_V4_Sep25'!G24 -> 45236 | G16: ='Bond buy_1_V4_Sep25'!H24 -> 45967 | H16: ='Bond buy_1_V4_Sep25'!I24 -> 2.58 | ... V16: ='Bond buy_1_V4_Sep25'!W24 -> Fixed | W16: FALSE
A17: ='Bond buy_1_V4_Sep25'!B25 -> TB26211A | B17: ='Bond buy_1_V4_Sep25'!C25 -> TH0623076286 | C17: ='Bond buy_1_V4_Sep25'!D25 -> 1 | D17: ='Bond buy_1_V4_Sep25'!E25 -> 176015 | E17: ='Bond buy_1_V4_Sep25'!F25 -> T-Bill | F17: ='Bond buy_1_V4_Sep25'!G25 -> 45882 | G17: ='Bond buy_1_V4_Sep25'!H25 -> 46064 | H17: ='Bond buy_1_V4_Sep25'!I25 -> 0 | ... V17: ='Bond buy_1_V4_Sep25'!W25 -> Fixed | W17: FALSE
A18: ='Bond buy_1_V4_Sep25'!B26 -> BOTF267A | B18: ='Bond buy_1_V4_Sep25'!C26 -> TH0655036711 | C18: ='Bond buy_1_V4_Sep25'!D26 -> 2 | D18: ='Bond buy_1_V4_Sep25'!E26 -> 001 | E18: ='Bond buy_1_V4_Sep25'!F26 -> BOT Bond | F18: ='Bond buy_1_V4_Sep25'!G26 -> 45474 | G18: ='Bond buy_1_V4_Sep25'!H26 -> 46204 | H18: ='Bond buy_1_V4_Sep25'!I26 -> 1.68404 | ... V18: ='Bond buy_1_V4_Sep25'!W26 -> Floating | W18: FALSE
A19: =RRP_1_V4_Sep25!B19 -> LB29DA | B19: =RRP_1_V4_Sep25!C19 -> TH0623039C07 | C19: =RRP_1_V4_Sep25!D19 -> 1 | D19: =RRP_1_V4_Sep25!E19 -> 176015 | E19: =RRP_1_V4_Sep25!F19 -> Gov Bond | F19: =RRP_1_V4_Sep25!G19 -> 43784 | G19: =RRP_1_V4_Sep25!H19 -> 47469 | H19: =RRP_1_V4_Sep25!I19 -> 1.6 | ... V19: =RRP_1_V4_Sep25!W19 -> Fixed | W19: FALSE
A20: =RRP_2_V4_Sep25!B19 -> LB28DA | B20: =RRP_2_V4_Sep25!C19 -> TH0623038C09 | C20: =RRP_2_V4_Sep25!D19 -> 1 | D20: =RRP_2_V4_Sep25!E19 -> 176015 | E20: =RRP_2_V4_Sep25!F19 -> Gov Bond | F20: =RRP_2_V4_Sep25!G19 -> 43294 | G20: =RRP_2_V4_Sep25!H19 -> 47104 | H20: =RRP_2_V4_Sep25!I19 -> 2.875 | ... V20: =RRP_2_V4_Sep25!W19 -> Fixed | W20: FALSE
A21: ='Bond Buy-Sell_V4_Sep25 + Oct25'!A24 -> EXIM266A | B21: ='Bond Buy-Sell_V4_Sep25 + Oct25'!B24 -> TH0624036602 | C21: ='Bond Buy-Sell_V4_Sep25 + Oct25'!C24 -> 3 | D21: ='Bond Buy-Sell_V4_Sep25 + Oct25'!D24 -> 035 | E21: ='Bond Buy-Sell_V4_Sep25 + Oct25'!E24 -> SOE Bond | F21: ='Bond Buy-Sell_V4_Sep25 + Oct25'!F24 -> 45083 | G21: ='Bond Buy-Sell_V4_Sep25 + Oct25'!G24 -> 46179 | H21: ='Bond Buy-Sell_V4_Sep25 + Oct25'!H24 -> 2.71 | ... V21: ='Bond Buy-Sell_V4_Sep25 + Oct25'!V24 -> Fixed | W21: FALSE
A23: ='V4_Result_30 Sep 2025'!A22 -> portfolio_master
A24: {=TRANSPOSE('All Table_V4_Clean'!A74:A78)} -> portfolio_id | B24: portfolio_name | C24: portfolio_manager | D24: accounting_treatment | E24: created_timestamp
A25: ='Bond buy_1_V4_Sep25'!B34 -> 301 | B25: ='Bond buy_1_V4_Sep25'!C34 -> AMC - Govt | C25: ='Bond buy_1_V4_Sep25'!D34 -> Treasury Desk | D25: ='Bond buy_1_V4_Sep25'!E34 -> AMC | E25: ='Bond buy_1_V4_Sep25'!F34 -> 45839
A26: ='Bond buy_1_V4_Sep25'!B35 -> 302 | B26: ='Bond buy_1_V4_Sep25'!C35 -> AMC - T-Bill | C26: ='Bond buy_1_V4_Sep25'!D35 -> Treasury Desk | D26: ='Bond buy_1_V4_Sep25'!E35 -> AMC | E26: ='Bond buy_1_V4_Sep25'!F35 -> 45839
A27: ='Bond buy_1_V4_Sep25'!B36 -> 303 | B27: ='Bond buy_1_V4_Sep25'!C36 -> AMC - BOT bond | C27: ='Bond buy_1_V4_Sep25'!D36 -> Treasury Desk | D27: ='Bond buy_1_V4_Sep25'!E36 -> AMC | E27: ='Bond buy_1_V4_Sep25'!F36 -> 45839
A28: ='Bond buy_1_V4_Sep25'!B37 -> 401 | B28: ='Bond buy_1_V4_Sep25'!C37 -> FVOCI - T-Bill | C28: ='Bond buy_1_V4_Sep25'!D37 -> Treasury Desk | D28: ='Bond buy_1_V4_Sep25'!E37 -> FVOCI | E28: ='Bond buy_1_V4_Sep25'!F37 -> 45839
A29: ='Bond buy_1_V4_Sep25'!B38 -> 402 | B29: ='Bond buy_1_V4_Sep25'!C38 -> FVOCI - BOT bond | C29: ='Bond buy_1_V4_Sep25'!D38 -> Treasury Desk | D29: ='Bond buy_1_V4_Sep25'!E38 -> FVOCI | E29: ='Bond buy_1_V4_Sep25'!F38 -> 45839
A30: ='Bond buy_1_V4_Sep25'!B39 -> 403 | B30: ='Bond buy_1_V4_Sep25'!C39 -> FVOCI - SOE | C30: ='Bond buy_1_V4_Sep25'!D39 -> Treasury Desk | D30: ='Bond buy_1_V4_Sep25'!E39 -> FVOCI | E30: ='Bond buy_1_V4_Sep25'!F39 -> 45839
A33: ='V4_Result_30 Sep 2025'!A32 -> netting_agreement
A34: {=TRANSPOSE('All Table_V4_Clean'!A84:A98)} -> netting_agreement_id | B34: counterparty_id | C34: netting_set_id | D34: agreement_type | E34: netting_type | F34: collateral_contract_type | G34: trade_date | H34: value_date | I34: maturity_date | J34: is_replacement | K34: replaced_agreement_id | L34: settlement_currency | M34: created_at | N34: updated_at | O34: agreement_status
A35: =RRP_1_V4_Sep25!B31 -> GMRA_2023_BB | B35: =RRP_1_V4_Sep25!C31 -> 101 | C35: =RRP_1_V4_Sep25!D31 -> 20001 | D35: =RRP_1_V4_Sep25!E31 -> GMRA | E35: =RRP_1_V4_Sep25!F31 -> COLLATERAL | F35: =RRP_1_V4_Sep25!G31 -> REP | G35: =RRP_1_V4_Sep25!H31 -> 45823 | H35: =RRP_1_V4_Sep25!I31 -> 45839 | ... O35: =RRP_1_V4_Sep25!P31 -> Active
A36: =RRP_2_V4_Sep25!B31 -> GMRA_2023_KB | B36: =RRP_2_V4_Sep25!C31 -> 102 | C36: =RRP_2_V4_Sep25!D31 -> 20002 | D36: =RRP_2_V4_Sep25!E31 -> GMRA | E36: =RRP_2_V4_Sep25!F31 -> COLLATERAL | F36: =RRP_2_V4_Sep25!G31 -> REP | G36: =RRP_2_V4_Sep25!H31 -> 45823 | H36: =RRP_2_V4_Sep25!I31 -> 45839 | ... O36: =RRP_2_V4_Sep25!P31 -> Active
A37: =Repo_1_V4_Sep25!B25 -> GMRA_2023_KT | B37: =Repo_1_V4_Sep25!C25 -> 103 | C37: =Repo_1_V4_Sep25!D25 -> 20003 | D37: =Repo_1_V4_Sep25!E25 -> GMRA | E37: =Repo_1_V4_Sep25!F25 -> COLLATERAL | F37: =Repo_1_V4_Sep25!G25 -> REP | G37: =Repo_1_V4_Sep25!H25 -> 45823 | H37: =Repo_1_V4_Sep25!I25 -> 45839 | ... O37: =Repo_1_V4_Sep25!P25 -> Active
A38: =Repo_2_V4_Sep25!B25 -> GMRA_2024_KB | B38: =Repo_2_V4_Sep25!C25 -> 102 | C38: =Repo_2_V4_Sep25!D25 -> 20004 | D38: =Repo_2_V4_Sep25!E25 -> GMRA | E38: =Repo_2_V4_Sep25!F25 -> COLLATERAL | F38: =Repo_2_V4_Sep25!G25 -> REP | G38: =Repo_2_V4_Sep25!H25 -> 45823 | H38: =Repo_2_V4_Sep25!I25 -> 45839 | ... O38: =Repo_2_V4_Sep25!P25 -> Active
A41: ='V4_Result_30 Sep 2025'!A40 -> limit_utilization
A42: {=TRANSPOSE('All Table_V4_Clean'!A340:A350)} -> limit_id | B42: counterparty_id | C42: limit_type | D42: currency | E42: available_line | F42: total_credit_line | G42: utilization_amount | H42: credit_line_approve_date | I42: timestamp | J42: created_date | K42: entity_id
A43: =RRP_1_V4_Sep25!B25 -> 1001 | B43: =RRP_1_V4_Sep25!C25 -> 101 | C43: =RRP_1_V4_Sep25!D25 -> REPO_LIMIT | D43: =RRP_1_V4_Sep25!E25 -> THB | E43: =RRP_1_V4_Sep25!F25 -> 800000000 | F43: =RRP_1_V4_Sep25!G25 -> 1000000000 | G43: =RRP_1_V4_Sep25!H25 -> 200000000 | H43: =RRP_1_V4_Sep25!I25 -> 45782 | ... K43: =RRP_1_V4_Sep25!L25 -> BBL0107536000374
A44: =RRP_2_V4_Sep25!B25 -> 1002 | B44: =RRP_2_V4_Sep25!C25 -> 102 | C44: =RRP_2_V4_Sep25!D25 -> REPO_LIMIT | D44: =RRP_2_V4_Sep25!E25 -> THB | E44: =RRP_2_V4_Sep25!F25 -> 900000000 | F44: =RRP_2_V4_Sep25!G25 -> 1000000000 | G44: =RRP_2_V4_Sep25!H25 -> 300000000 | H44: =RRP_2_V4_Sep25!I25 -> 45782 | ... K44: =RRP_2_V4_Sep25!L25 -> KBANK0107536000315
A45: ='IB Lend_V4_Sep25'!A135 -> 2001 | B45: ='IB Lend_V4_Sep25'!B135 -> 101 | C45: ='IB Lend_V4_Sep25'!C135 -> PLACEMENT_LIMIT | D45: ='IB Lend_V4_Sep25'!D135 -> THB | E45: ='IB Lend_V4_Sep25'!E135 -> 500000000 | F45: ='IB Lend_V4_Sep25'!F135 -> 1000000000 | G45: ='IB Lend_V4_Sep25'!G135 -> 500000000 | H45: ='IB Lend_V4_Sep25'!H135 -> 45901 | ... K45: ='IB Lend_V4_Sep25'!K135 -> BBL0107536000374
A46: ='IB Lend_V4_Oct25'!A114 -> 2002 | B46: ='IB Lend_V4_Oct25'!B114 -> 104 | C46: ='IB Lend_V4_Oct25'!C114 -> PLACEMENT_LIMIT | D46: ='IB Lend_V4_Oct25'!D114 -> THB | E46: ='IB Lend_V4_Oct25'!E114 -> 400000000 | F46: ='IB Lend_V4_Oct25'!F114 -> 500000000 | G46: ='IB Lend_V4_Oct25'!G114 -> 100000000 | H46: ='IB Lend_V4_Oct25'!H114 -> 45828 | ... K46: ='IB Lend_V4_Oct25'!K114 -> CIMB0107537002338
A47: ='IB Lend_V4_Oct25'!A113 -> 2003 | B47: ='IB Lend_V4_Oct25'!B113 -> 113 | C47: ='IB Lend_V4_Oct25'!C113 -> PLACEMENT_LIMIT | D47: ='IB Lend_V4_Oct25'!D113 -> THB | E47: ='IB Lend_V4_Oct25'!E113 -> 1000000000 | F47: ='IB Lend_V4_Oct25'!F113 -> 500000000 | G47: ='IB Lend_V4_Oct25'!G113 -> 0 | H47: ='IB Lend_V4_Oct25'!H113 -> 45931 | ... K47: ='IB Lend_V4_Oct25'!K113 -> SCB0107536000102
A50: ='V4_Result_30 Sep 2025'!A48 -> repo_trades
A51: {=TRANSPOSE('All Table_V4_Clean'!A146:A171)} -> repo_trade_id | B51: trade_date | C51: trade_type | D51: counterparty_id | E51: netting_agreement_id | F51: netting_set_id | G51: nominal_amount | H51: purchase_date | I51: repurchase_date | J51: purchase_price | K51: repurchase_price | L51: currency | M51: reference_rate_id | N51: interest_rate_type | O51: interest_rate | P51: reference_rate | Q51: margin | R51: day_count_convention | S51: repo_rate | T51: term | U51: repo_out_flag | V51: repo_in_flag | W51: status | X51: limit_id | Y51: accrued_interest | Z51: entity_id
A52: =RRP_1_V4_Sep25!B123 -> 70001 | B52: =RRP_1_V4_Sep25!C123 -> 45905.583 | C52: =RRP_1_V4_Sep25!D123 -> Reverse REPO | D52: =RRP_1_V4_Sep25!E123 -> 101 | E52: =RRP_1_V4_Sep25!F123 -> GMRA_2023_BB | F52: =RRP_1_V4_Sep25!G123 -> 20001 | G52: =RRP_1_V4_Sep25!H123 -> 200000000 | H52: =RRP_1_V4_Sep25!I123 -> 45908 | ... Z52: =RRP_1_V4_Sep25!AA123 -> BBL0107536000374
A53: =RRP_2_V4_Oct25!B25 -> 70002 | B53: =RRP_2_V4_Oct25!C25 -> 45926.583 | C53: =RRP_2_V4_Oct25!D25 -> Reverse REPO | D53: =RRP_2_V4_Oct25!E25 -> 102 | E53: =RRP_2_V4_Oct25!F25 -> GMRA_2023_KB | F53: =RRP_2_V4_Oct25!G25 -> 20002 | G53: =RRP_2_V4_Oct25!H25 -> 300000000 | H53: =RRP_2_V4_Oct25!I25 -> 45929 | ... Y53: =RRP_2_V4_Oct25!Z25 -> 0 | Z53: =RRP_2_V4_Sep25!B13 -> KBANK0107536000315
A54: =Repo_1_V4_Sep25!B107 -> 70003 | B54: =Repo_1_V4_Sep25!C107 -> 45922.417 | C54: =Repo_1_V4_Sep25!D107 -> REPO | D54: =Repo_1_V4_Sep25!E107 -> 103 | E54: =Repo_1_V4_Sep25!F107 -> GMRA_2023_KT | F54: =Repo_1_V4_Sep25!G107 -> 20003 | G54: =Repo_1_V4_Sep25!H107 -> 50000000 | H54: =Repo_1_V4_Sep25!I107 -> 45924 | ... Z54: =Repo_1_V4_Sep25!AA107 -> KTB107537000882
A55: =Repo_2_V4_Oct25!B25 -> 70004 | B55: =Repo_2_V4_Oct25!C25 -> 45924.417 | C55: =Repo_2_V4_Oct25!D25 -> REPO | D55: =Repo_2_V4_Oct25!E25 -> 102 | E55: =Repo_2_V4_Oct25!F25 -> GMRA_2024_KB | F55: =Repo_2_V4_Oct25!G25 -> 20004 | G55: =Repo_2_V4_Oct25!H25 -> 30000000 | H55: =Repo_2_V4_Oct25!I25 -> 45926 | ... Y55: =Repo_2_V4_Oct25!Z25 -> 0 | Z55: =Z53 -> KBANK0107536000315
A58: ='V4_Result_30 Sep 2025'!A56 -> collateral_positions
A59: {=TRANSPOSE('All Table_V4_Clean'!A177:A187)} -> collateral_id | B59: repo_trade_id | C59: security_id | D59: nominal_amount | E59: allocation_date | F59: valuation_price | G59: market_value | H59: haircut_percentage | I59: collateral_value_after_haircut | J59: margin_call_id | K59: currency
A60: =RRP_1_V4_Sep25!B66 -> 70001_LB29DA_1 | B60: =RRP_1_V4_Sep25!C66 -> 70001 | C60: =RRP_1_V4_Sep25!D66 -> LB29DA | D60: =RRP_1_V4_Sep25!E66 -> 205000000 | E60: =RRP_1_V4_Sep25!F66 -> 45908 | F60: =RRP_1_V4_Sep25!G66 -> 99.85 | G60: =RRP_1_V4_Sep25!H66 -> 204692500 | H60: =RRP_1_V4_Sep25!I66 -> 2 | ... K60: =RRP_1_V4_Sep25!L66 -> THB
A61: =RRP_2_V4_Sep25!B66 -> 70002_LB28DA_1 | B61: =RRP_2_V4_Sep25!C66 -> 70002 | C61: =RRP_2_V4_Sep25!D66 -> LB28DA | D61: =RRP_2_V4_Sep25!E66 -> 305000000 | E61: =RRP_2_V4_Sep25!F66 -> 45929 | F61: =RRP_2_V4_Sep25!G66 -> 100.1 | G61: =RRP_2_V4_Sep25!H66 -> 305305000 | H61: =RRP_2_V4_Sep25!I66 -> 2 | ... K61: =RRP_2_V4_Sep25!L66 -> THB
A62: =Repo_1_V4_Sep25!B60 -> 70003_LB616A_1 | B62: =Repo_1_V4_Sep25!C60 -> 70003 | C62: =Repo_1_V4_Sep25!D60 -> LB616A | D62: =Repo_1_V4_Sep25!E60 -> 50000000 | E62: =Repo_1_V4_Sep25!F60 -> 45924 | F62: =Repo_1_V4_Sep25!G60 -> 170.81 | G62: =Repo_1_V4_Sep25!H60 -> 85405000 | H62: =Repo_1_V4_Sep25!I60 -> 2 | ... K62: =Repo_1_V4_Sep25!L60 -> THB
A63: =Repo_2_V4_Sep25!B60 -> 70004_BOT25NA_1 | B63: =Repo_2_V4_Sep25!C60 -> 70004 | C63: =Repo_2_V4_Sep25!D60 -> BOT25NA | D63: =Repo_2_V4_Sep25!E60 -> 30000000 | E63: =Repo_2_V4_Sep25!F60 -> 45926 | F63: =Repo_2_V4_Sep25!G60 -> 100.25761 | G63: =Repo_2_V4_Sep25!H60 -> 30078000 | H63: =Repo_2_V4_Sep25!I60 -> 2 | ... K63: =Repo_2_V4_Sep25!L60 -> THB
A66: ='V4_Result_30 Sep 2025'!A64 -> bond_trades
A67: {=TRANSPOSE('All Table_V4_Clean'!A193:A203)} -> bond_trade_id | B67: portfolio_id | C67: trade_date | D67: settlement_date | E67: security_id | F67: counterparty_id | G67: trade_type | H67: nominal_amount | I67: clean_price_trade | J67: yield_to_maturity | K67: settlement_status
A68: ='Bond Buy-Sell_V4_Sep25 + Oct25'!A96 -> 90001 | B68: ='Bond Buy-Sell_V4_Sep25 + Oct25'!B96 -> 403 | C68: ='Bond Buy-Sell_V4_Sep25 + Oct25'!C96 -> 45659 | D68: ='Bond Buy-Sell_V4_Sep25 + Oct25'!D96 -> 45663 | E68: ='Bond Buy-Sell_V4_Sep25 + Oct25'!E96 -> EXIM266A | F68: ='Bond Buy-Sell_V4_Sep25 + Oct25'!F96 -> 101 | G68: ='Bond Buy-Sell_V4_Sep25 + Oct25'!G96 -> Buy | H68: ='Bond Buy-Sell_V4_Sep25 + Oct25'!H96 -> 100000000 | ... K68: ='Bond Buy-Sell_V4_Sep25 + Oct25'!K96 -> Settled
A69: ='Bond Buy-Sell_V4_Sep25 + Oct25'!A97 -> 90002 | B69: ='Bond Buy-Sell_V4_Sep25 + Oct25'!B97 -> 403 | C69: ='Bond Buy-Sell_V4_Sep25 + Oct25'!C97 -> 45726 | D69: ='Bond Buy-Sell_V4_Sep25 + Oct25'!D97 -> 45728 | E69: ='Bond Buy-Sell_V4_Sep25 + Oct25'!E97 -> EXIM266A | F69: ='Bond Buy-Sell_V4_Sep25 + Oct25'!F97 -> 101 | G69: ='Bond Buy-Sell_V4_Sep25 + Oct25'!G97 -> Buy | H69: ='Bond Buy-Sell_V4_Sep25 + Oct25'!H97 -> 50000000 | ... K69: ='Bond Buy-Sell_V4_Sep25 + Oct25'!K97 -> Settled
A70: ='Bond Buy-Sell_V4_Sep25 + Oct25'!A98 -> 90003 | B70: ='Bond Buy-Sell_V4_Sep25 + Oct25'!B98 -> 403 | C70: ='Bond Buy-Sell_V4_Sep25 + Oct25'!C98 -> 45915 | D70: ='Bond Buy-Sell_V4_Sep25 + Oct25'!D98 -> 45917 | E70: ='Bond Buy-Sell_V4_Sep25 + Oct25'!E98 -> EXIM266A | F70: ='Bond Buy-Sell_V4_Sep25 + Oct25'!F98 -> 101 | G70: ='Bond Buy-Sell_V4_Sep25 + Oct25'!G98 -> Sell | H70: ='Bond Buy-Sell_V4_Sep25 + Oct25'!H98 -> 100000000 | ... K70: ='Bond Buy-Sell_V4_Sep25 + Oct25'!K98 -> Settled
A71: ='Bond buy_1_V4_Sep25'!B65 -> 90004 | B71: ='Bond buy_1_V4_Sep25'!C65 -> 403 | C71: ='Bond buy_1_V4_Sep25'!D65 -> 45854.458 | D71: ='Bond buy_1_V4_Sep25'!E65 -> 45856.458 | E71: ='Bond buy_1_V4_Sep25'!F65 -> GSB26OA | F71: ='Bond buy_1_V4_Sep25'!G65 -> 102 | G71: ='Bond buy_1_V4_Sep25'!H65 -> Buy | H71: ='Bond buy_1_V4_Sep25'!I65 -> 100000000 | ... K71: ='Bond buy_1_V4_Sep25'!L65 -> Settled
A72: ='Bond buy_1_V4_Sep25'!B66 -> 90005 | B72: ='Bond buy_1_V4_Sep25'!C66 -> 301 | C72: ='Bond buy_1_V4_Sep25'!D66 -> 45917.458 | D72: ='Bond buy_1_V4_Sep25'!E66 -> 45919.458 | E72: ='Bond buy_1_V4_Sep25'!F66 -> LB616A | F72: ='Bond buy_1_V4_Sep25'!G66 -> 101 | G72: ='Bond buy_1_V4_Sep25'!H66 -> Buy | H72: ='Bond buy_1_V4_Sep25'!I66 -> 100000000 | ... K72: ='Bond buy_1_V4_Sep25'!L66 -> Settled
A73: ='Bond buy_1_V4_Sep25'!B67 -> 90006 | B73: ='Bond buy_1_V4_Sep25'!C67 -> 302 | C73: ='Bond buy_1_V4_Sep25'!D67 -> 45917.458 | D73: ='Bond buy_1_V4_Sep25'!E67 -> 45919.458 | E73: ='Bond buy_1_V4_Sep25'!F67 -> TB26128A | F73: ='Bond buy_1_V4_Sep25'!G67 -> 101 | G73: ='Bond buy_1_V4_Sep25'!H67 -> Buy | H73: ='Bond buy_1_V4_Sep25'!I67 -> 100000000 | ... K73: ='Bond buy_1_V4_Sep25'!L67 -> Settled
A74: ='Bond buy_1_V4_Sep25'!B68 -> 90007 | B74: ='Bond buy_1_V4_Sep25'!C68 -> 303 | C74: ='Bond buy_1_V4_Sep25'!D68 -> 45917.458 | D74: ='Bond buy_1_V4_Sep25'!E68 -> 45919.458 | E74: ='Bond buy_1_V4_Sep25'!F68 -> BOT25NA | F74: ='Bond buy_1_V4_Sep25'!G68 -> 101 | G74: ='Bond buy_1_V4_Sep25'!H68 -> Buy | H74: ='Bond buy_1_V4_Sep25'!I68 -> 100000000 | ... K74: ='Bond buy_1_V4_Sep25'!L68 -> Settled
A75: ='Bond buy_1_V4_Sep25'!B69 -> 90008 | B75: ='Bond buy_1_V4_Sep25'!C69 -> 401 | C75: ='Bond buy_1_V4_Sep25'!D69 -> 45917.458 | D75: ='Bond buy_1_V4_Sep25'!E69 -> 45919.458 | E75: ='Bond buy_1_V4_Sep25'!F69 -> TB26211A | F75: ='Bond buy_1_V4_Sep25'!G69 -> 102 | G75: ='Bond buy_1_V4_Sep25'!H69 -> Buy | H75: ='Bond buy_1_V4_Sep25'!I69 -> 100000000 | ... K75: ='Bond buy_1_V4_Sep25'!L69 -> Settled
A76: ='Bond buy_1_V4_Sep25'!B70 -> 90009 | B76: ='Bond buy_1_V4_Sep25'!C70 -> 402 | C76: ='Bond buy_1_V4_Sep25'!D70 -> 45917.458 | D76: ='Bond buy_1_V4_Sep25'!E70 -> 45919.458 | E76: ='Bond buy_1_V4_Sep25'!F70 -> BOTF267A | F76: ='Bond buy_1_V4_Sep25'!G70 -> 102 | G76: ='Bond buy_1_V4_Sep25'!H70 -> Buy | H76: ='Bond buy_1_V4_Sep25'!I70 -> 100000000 | ... K76: ='Bond buy_1_V4_Sep25'!L70 -> Settled
A77: ='Bond Buy-Sell_V4_Sep25 + Oct25'!A151 -> 90010 | B77: ='Bond Buy-Sell_V4_Sep25 + Oct25'!B151 -> 403 | C77: ='Bond Buy-Sell_V4_Sep25 + Oct25'!C151 -> 45955 | D77: ='Bond Buy-Sell_V4_Sep25 + Oct25'!D151 -> 45959 | E77: ='Bond Buy-Sell_V4_Sep25 + Oct25'!E151 -> EXIM266A | F77: ='Bond Buy-Sell_V4_Sep25 + Oct25'!F151 -> 101 | G77: ='Bond Buy-Sell_V4_Sep25 + Oct25'!G151 -> Buy | H77: ='Bond Buy-Sell_V4_Sep25 + Oct25'!H151 -> 100000000 | ... K77: ='Bond Buy-Sell_V4_Sep25 + Oct25'!K151 -> Settled
A78: ='Bond sell_1_V4_Oct25'!B31 -> 90011 | B78: ='Bond sell_1_V4_Oct25'!C31 -> 403 | C78: ='Bond sell_1_V4_Oct25'!D31 -> 45950.458 | D78: ='Bond sell_1_V4_Oct25'!E31 -> 45952.458 | E78: ='Bond sell_1_V4_Oct25'!F31 -> GSB26OA | F78: ='Bond sell_1_V4_Oct25'!G31 -> 102 | G78: ='Bond sell_1_V4_Oct25'!H31 -> Sell | H78: ='Bond sell_1_V4_Oct25'!I31 -> 50000000 | ... K78: ='Bond sell_1_V4_Oct25'!L31 -> Settled
A80: ='V4_Result_30 Sep 2025'!A77 -> bond_transactions
A81: {=TRANSPOSE('All Table_V4_Clean'!A209:A238)} -> trade_id | B81: security_id | C81: portfolio_id | D81: counterparty_id | E81: trade_type | F81: trade_date | G81: settlement_date | H81: maturity_date | I81: currency | J81: nominal_amount | K81: clean_price | L81: clean_price_trade | M81: accrued_interest | N81: dirty_price | O81: classification | P81: book_value | Q81: market_clean_value | R81: market_value | S81: last_coupon_date | T81: coupon_rate_type | U81: coupon_reference_rate | V81: coupon_margin | W81: coupon_frequency | X81: coupon_rate | Y81: coupon_day_count_conv | Z81: rating_tris | AA81: rating_fitch | AB81: status | AC81: last_updated_timestamp | AD81: valuation_date
A82: ='Bond Buy-Sell_V4_Sep25 + Oct25'!A209 -> 90001 | B82: ='Bond Buy-Sell_V4_Sep25 + Oct25'!B209 -> EXIM266A | C82: ='Bond Buy-Sell_V4_Sep25 + Oct25'!C209 -> 403 | D82: ='Bond Buy-Sell_V4_Sep25 + Oct25'!D209 -> 101 | E82: ='Bond Buy-Sell_V4_Sep25 + Oct25'!E209 -> Buy | F82: ='Bond Buy-Sell_V4_Sep25 + Oct25'!F209 -> 45659 | G82: ='Bond Buy-Sell_V4_Sep25 + Oct25'!G209 -> 45663 | H82: ='Bond Buy-Sell_V4_Sep25 + Oct25'!H209 -> 46179 | ... AD82: ='Bond Buy-Sell_V4_Sep25 + Oct25'!AD209 -> 45961
A83: ='Bond Buy-Sell_V4_Sep25 + Oct25'!A210 -> 90002 | B83: ='Bond Buy-Sell_V4_Sep25 + Oct25'!B210 -> EXIM266A | C83: ='Bond Buy-Sell_V4_Sep25 + Oct25'!C210 -> 403 | D83: ='Bond Buy-Sell_V4_Sep25 + Oct25'!D210 -> 101 | E83: ='Bond Buy-Sell_V4_Sep25 + Oct25'!E210 -> Buy | F83: ='Bond Buy-Sell_V4_Sep25 + Oct25'!F210 -> 45726 | G83: ='Bond Buy-Sell_V4_Sep25 + Oct25'!G210 -> 45728 | H83: ='Bond Buy-Sell_V4_Sep25 + Oct25'!H210 -> 46179 | ... AD83: ='Bond Buy-Sell_V4_Sep25 + Oct25'!AD210 -> 45961
A84: ='Bond Buy-Sell_V4_Sep25 + Oct25'!A211 -> 90003 | B84: ='Bond Buy-Sell_V4_Sep25 + Oct25'!B211 -> EXIM266A | C84: ='Bond Buy-Sell_V4_Sep25 + Oct25'!C211 -> 403 | D84: ='Bond Buy-Sell_V4_Sep25 + Oct25'!D211 -> 101 | E84: ='Bond Buy-Sell_V4_Sep25 + Oct25'!E211 -> Sell | F84: ='Bond Buy-Sell_V4_Sep25 + Oct25'!F211 -> 45915 | G84: ='Bond Buy-Sell_V4_Sep25 + Oct25'!G211 -> 45917 | H84: ='Bond Buy-Sell_V4_Sep25 + Oct25'!H211 -> 46179 | ... AD84: ='Bond Buy-Sell_V4_Sep25 + Oct25'!AD211 -> 45961
A85: ='Bond buy_1_V4_Oct25'!B78 -> 90004 | B85: ='Bond buy_1_V4_Oct25'!C78 -> GSB26OA | C85: ='Bond buy_1_V4_Oct25'!D78 -> 403 | D85: ='Bond buy_1_V4_Oct25'!E78 -> 102 | E85: ='Bond buy_1_V4_Oct25'!F78 -> Buy | F85: ='Bond buy_1_V4_Oct25'!G78 -> 45854 | G85: ='Bond buy_1_V4_Oct25'!H78 -> 45856 | H85: ='Bond buy_1_V4_Oct25'!I78 -> 46311 | ... T85: ='Bond buy_1_V4_Oct25'!U78 -> Fixed | V85: ='Bond buy_1_V4_Oct25'!W78 -> 0 | W85: ='Bond buy_1_V4_Oct25'!X78 -> Semi-Annual | X85: ='Bond buy_1_V4_Oct25'!Y78 -> 1.69 | Y85: ='Bond buy_1_V4_Oct25'!Z78 -> Actual/365 | Z85: ='Bond buy_1_V4_Oct25'!AA78 -> AAA | AA85: ='Bond buy_1_V4_Oct25'!AB78 -> AAA(tha) | AB85: ='Bond buy_1_V4_Oct25'!AC78 -> Active | AC85: ='Bond buy_1_V4_Oct25'!AD78 -> 45946.458 | AD85: ='Bond buy_1_V4_Oct25'!AE78 -> 45946
A86: ='Bond buy_1_V4_Oct25'!B79 -> 90005 | B86: ='Bond buy_1_V4_Oct25'!C79 -> LB616A | C86: ='Bond buy_1_V4_Oct25'!D79 -> 301 | D86: ='Bond buy_1_V4_Oct25'!E79 -> 101 | E86: ='Bond buy_1_V4_Oct25'!F79 -> Buy | F86: ='Bond buy_1_V4_Oct25'!G79 -> 45917 | G86: ='Bond buy_1_V4_Oct25'!H79 -> 45919 | H86: ='Bond buy_1_V4_Oct25'!I79 -> 58974 | ... T86: ='Bond buy_1_V4_Oct25'!U79 -> Fixed | V86: ='Bond buy_1_V4_Oct25'!W79 -> 0 | W86: ='Bond buy_1_V4_Oct25'!X79 -> Semi-Annual | X86: ='Bond buy_1_V4_Oct25'!Y79 -> 4.85 | Y86: ='Bond buy_1_V4_Oct25'!Z79 -> Actual/365 | Z86: ='Bond buy_1_V4_Oct25'!AA79 -> AAA | AA86: ='Bond buy_1_V4_Oct25'!AB79 -> AAA(tha) | AB86: ='Bond buy_1_V4_Oct25'!AC79 -> Active | AC86: ='Bond buy_1_V4_Oct25'!AD79 -> 45961.458 | AD86: ='Bond buy_1_V4_Oct25'!AE79 -> 45961
A87: ='Bond buy_1_V4_Oct25'!B80 -> 90006 | B87: ='Bond buy_1_V4_Oct25'!C80 -> TB26128A | C87: ='Bond buy_1_V4_Oct25'!D80 -> 302 | D87: ='Bond buy_1_V4_Oct25'!E80 -> 101 | E87: ='Bond buy_1_V4_Oct25'!F80 -> Buy | F87: ='Bond buy_1_V4_Oct25'!G80 -> 45917 | G87: ='Bond buy_1_V4_Oct25'!H80 -> 45919 | H87: ='Bond buy_1_V4_Oct25'!I80 -> 46050 | ... T87: ='Bond buy_1_V4_Oct25'!U80 -> Fixed | V87: ='Bond buy_1_V4_Oct25'!W80 -> 0 | W87: ='Bond buy_1_V4_Oct25'!X80 -> At Maturity | X87: ='Bond buy_1_V4_Oct25'!Y80 -> 0 | Y87: ='Bond buy_1_V4_Oct25'!Z80 -> Actual/365 | Z87: ='Bond buy_1_V4_Oct25'!AA80 -> AAA | AA87: ='Bond buy_1_V4_Oct25'!AB80 -> AAA(tha) | AB87: ='Bond buy_1_V4_Oct25'!AC80 -> Active | AC87: ='Bond buy_1_V4_Oct25'!AD80 -> 45961.458 | AD87: ='Bond buy_1_V4_Oct25'!AE80 -> 45961
A88: ='Bond buy_1_V4_Oct25'!B81 -> 90007 | B88: ='Bond buy_1_V4_Oct25'!C81 -> BOT25NA | C88: ='Bond buy_1_V4_Oct25'!D81 -> 303 | D88: ='Bond buy_1_V4_Oct25'!E81 -> 101 | E88: ='Bond buy_1_V4_Oct25'!F81 -> Buy | F88: ='Bond buy_1_V4_Oct25'!G81 -> 45917 | G88: ='Bond buy_1_V4_Oct25'!H81 -> 45919 | H88: ='Bond buy_1_V4_Oct25'!I81 -> 45967 | ... T88: ='Bond buy_1_V4_Oct25'!U81 -> Fixed | V88: ='Bond buy_1_V4_Oct25'!W81 -> 0 | W88: ='Bond buy_1_V4_Oct25'!X81 -> Semi-Annual | X88: ='Bond buy_1_V4_Oct25'!Y81 -> 2.58 | Y88: ='Bond buy_1_V4_Oct25'!Z81 -> Actual/365 | Z88: ='Bond buy_1_V4_Oct25'!AA81 -> AAA | AA88: ='Bond buy_1_V4_Oct25'!AB81 -> AAA(tha) | AB88: ='Bond buy_1_V4_Oct25'!AC81 -> Active | AC88: ='Bond buy_1_V4_Oct25'!AD81 -> 45961.458 | AD88: ='Bond buy_1_V4_Oct25'!AE81 -> 45961
A89: ='Bond buy_1_V4_Oct25'!B82 -> 90008 | B89: ='Bond buy_1_V4_Oct25'!C82 -> TB26211A | C89: ='Bond buy_1_V4_Oct25'!D82 -> 401 | D89: ='Bond buy_1_V4_Oct25'!E82 -> 102 | E89: ='Bond buy_1_V4_Oct25'!F82 -> Buy | F89: ='Bond buy_1_V4_Oct25'!G82 -> 45917 | G89: ='Bond buy_1_V4_Oct25'!H82 -> 45919 | H89: ='Bond buy_1_V4_Oct25'!I82 -> 46064 | ... T89: ='Bond buy_1_V4_Oct25'!U82 -> Fixed | V89: ='Bond buy_1_V4_Oct25'!W82 -> 0 | W89: ='Bond buy_1_V4_Oct25'!X82 -> At Maturity | X89: ='Bond buy_1_V4_Oct25'!Y82 -> 0 | Y89: ='Bond buy_1_V4_Oct25'!Z82 -> Actual/365 | Z89: ='Bond buy_1_V4_Oct25'!AA82 -> AAA | AA89: ='Bond buy_1_V4_Oct25'!AB82 -> AAA(tha) | AB89: ='Bond buy_1_V4_Oct25'!AC82 -> Active | AC89: ='Bond buy_1_V4_Oct25'!AD82 -> 45961.458 | AD89: ='Bond buy_1_V4_Oct25'!AE82 -> 45961
A90: ='Bond buy_1_V4_Oct25'!B83 -> 90009 | B90: ='Bond buy_1_V4_Oct25'!C83 -> BOTF267A | C90: ='Bond buy_1_V4_Oct25'!D83 -> 402 | D90: ='Bond buy_1_V4_Oct25'!E83 -> 102 | E90: ='Bond buy_1_V4_Oct25'!F83 -> Buy | F90: ='Bond buy_1_V4_Oct25'!G83 -> 45917 | G90: ='Bond buy_1_V4_Oct25'!H83 -> 45919 | H90: ='Bond buy_1_V4_Oct25'!I83 -> 46204 | ... T90: ='Bond buy_1_V4_Oct25'!U83 -> Floating | V90: ='Bond buy_1_V4_Oct25'!W83 -> 0.05 | W90: ='Bond buy_1_V4_Oct25'!X83 -> Quarterly | X90: ='Bond buy_1_V4_Oct25'!Y83 -> 1.68404 | Y90: ='Bond buy_1_V4_Oct25'!Z83 -> Actual/365 | Z90: ='Bond buy_1_V4_Oct25'!AA83 -> AAA | AA90: ='Bond buy_1_V4_Oct25'!AB83 -> AAA(tha) | AB90: ='Bond buy_1_V4_Oct25'!AC83 -> Active | AC90: ='Bond buy_1_V4_Oct25'!AD83 -> 45961.458 | AD90: ='Bond buy_1_V4_Oct25'!AE83 -> 45961
A91: =RRP_1_V4_Sep25!B129 -> 70001 | B91: =RRP_1_V4_Sep25!C129 -> LB29DA | C91: =RRP_1_V4_Sep25!D129 -> 301 | D91: =RRP_1_V4_Sep25!E129 -> 101 | E91: =RRP_1_V4_Sep25!F129 -> ReverseRepo | F91: =RRP_1_V4_Sep25!G129 -> 45905 | G91: =RRP_1_V4_Sep25!H129 -> 45908 | H91: =RRP_1_V4_Sep25!I129 -> 45915 | ... AD91: =RRP_1_V4_Sep25!AE129 -> 45930
A92: =RRP_2_V4_Oct25!B31 -> 70002 | B92: =RRP_2_V4_Oct25!C31 -> LB28DA | C92: =RRP_2_V4_Oct25!D31 -> 302 | D92: =RRP_2_V4_Oct25!E31 -> 102 | E92: =RRP_2_V4_Oct25!F31 -> ReverseRepo | F92: =RRP_2_V4_Oct25!G31 -> 45926 | G92: =RRP_2_V4_Oct25!H31 -> 45929 | H92: =RRP_2_V4_Oct25!I31 -> 47104 | ... T92: =RRP_2_V4_Oct25!U31 -> Fixed | V92: =RRP_2_V4_Oct25!W31 -> 0 | W92: =RRP_2_V4_Oct25!X31 -> Semi-Annual | X92: =RRP_2_V4_Oct25!Y31 -> 2.875 | Y92: =RRP_2_V4_Oct25!Z31 -> Actual/365 | Z92: =RRP_2_V4_Oct25!AA31 -> AAA | AA92: =RRP_2_V4_Oct25!AB31 -> AAA(tha) | AB92: =RRP_2_V4_Oct25!AC31 -> Matured | AC92: =RRP_2_V4_Oct25!AD31 -> 45961 | AD92: =RRP_2_V4_Oct25!AE31 -> 45961
A93: =Repo_1_V4_Sep25!B113 -> 70003 | B93: =Repo_1_V4_Sep25!C113 -> LB616A | C93: =Repo_1_V4_Sep25!D113 -> 301 | D93: =Repo_1_V4_Sep25!E113 -> 103 | E93: =Repo_1_V4_Sep25!F113 -> Repo | F93: =Repo_1_V4_Sep25!G113 -> 45922 | G93: =Repo_1_V4_Sep25!H113 -> 45924 | H93: =Repo_1_V4_Sep25!I113 -> 58983 | ... AD93: =Repo_1_V4_Sep25!AE113 -> 45930
A94: =Repo_2_V4_Oct25!B31 -> 70004 | B94: =Repo_2_V4_Oct25!C31 -> BOT25NA | C94: =Repo_2_V4_Oct25!D31 -> 402 | D94: =Repo_2_V4_Oct25!E31 -> 102 | E94: =Repo_2_V4_Oct25!F31 -> Repo | F94: =Repo_2_V4_Oct25!G31 -> 45924 | G94: =Repo_2_V4_Oct25!H31 -> 45926 | H94: =Repo_2_V4_Oct25!I31 -> 45933 | ... T94: =Repo_2_V4_Oct25!U31 -> Fixed | V94: =Repo_2_V4_Oct25!W31 -> 0 | W94: =Repo_2_V4_Oct25!X31 -> Semi-Annual | X94: =Repo_2_V4_Oct25!Y31 -> 2.58 | Y94: =Repo_2_V4_Oct25!Z31 -> Actual/365 | Z94: =Repo_2_V4_Oct25!AA31 -> AAA | AA94: =Repo_2_V4_Oct25!AB31 -> AAA(tha) | AB94: =Repo_2_V4_Oct25!AC31 -> Matured | AC94: =Repo_2_V4_Oct25!AD31 -> 45961.708 | AD94: =Repo_2_V4_Oct25!AE31 -> 45961
A95: ='Bond Buy-Sell_V4_Sep25 + Oct25'!A212 -> 90010 | B95: ='Bond Buy-Sell_V4_Sep25 + Oct25'!B212 -> EXIM266A | C95: ='Bond Buy-Sell_V4_Sep25 + Oct25'!C212 -> 403 | D95: ='Bond Buy-Sell_V4_Sep25 + Oct25'!D212 -> 101 | E95: ='Bond Buy-Sell_V4_Sep25 + Oct25'!E212 -> Buy | F95: ='Bond Buy-Sell_V4_Sep25 + Oct25'!F212 -> 45955 | G95: ='Bond Buy-Sell_V4_Sep25 + Oct25'!G212 -> 45959 | H95: ='Bond Buy-Sell_V4_Sep25 + Oct25'!H212 -> 46179 | ... AD95: ='Bond Buy-Sell_V4_Sep25 + Oct25'!AD212 -> 45961
A96: ='Bond sell_1_V4_Oct25'!B49 -> 90011 | B96: ='Bond sell_1_V4_Oct25'!C49 -> GSB26OA | C96: ='Bond sell_1_V4_Oct25'!D49 -> 403 | D96: ='Bond sell_1_V4_Oct25'!E49 -> 102 | E96: ='Bond sell_1_V4_Oct25'!F49 -> Sell | F96: ='Bond sell_1_V4_Oct25'!G49 -> 45950 | G96: ='Bond sell_1_V4_Oct25'!H49 -> 45952 | H96: ='Bond sell_1_V4_Oct25'!I49 -> 46311 | ... T96: ='Bond sell_1_V4_Oct25'!U49 -> Fixed | V96: ='Bond sell_1_V4_Oct25'!W49 -> 0 | W96: ='Bond sell_1_V4_Oct25'!X49 -> Semi-Annual | X96: ='Bond sell_1_V4_Oct25'!Y49 -> 1.69 | Y96: ='Bond sell_1_V4_Oct25'!Z49 -> Actual/365 | Z96: ='Bond sell_1_V4_Oct25'!AA49 -> AAA | AA96: ='Bond sell_1_V4_Oct25'!AB49 -> AAA(tha) | AB96: ='Bond sell_1_V4_Oct25'!AC49 -> Active | AC96: ='Bond sell_1_V4_Oct25'!AD49 -> 45952.458 | AD96: ='Bond sell_1_V4_Oct25'!AE49 -> 45961
A98: ='V4_Result_30 Sep 2025'!A94 -> margin_calls
A99: {=TRANSPOSE('All Table_V4_Clean'!A302:A311)} -> margin_call_id | B99: counterparty_id | C99: repo_trade_id | D99: valuation_date | E99: call_currency | F99: call_type | G99: call_amount | H99: due_time | I99: status | J99: created_timestamp
A100: =RRP_1_V4_Sep25!B92 -> 1 | B100: =RRP_1_V4_Sep25!C92 -> 101 | C100: =RRP_1_V4_Sep25!D92 -> 70001 | D100: =RRP_1_V4_Sep25!E92 -> 45909 | E100: =RRP_1_V4_Sep25!F92 -> THB | F100: =RRP_1_V4_Sep25!G92 -> CALL | G100: =RRP_1_V4_Sep25!H92 -> 2100000 | H100: =RRP_1_V4_Sep25!I92 -> 45909.625 | ... J100: =RRP_1_V4_Sep25!K92 -> 45909.625
A101: =RRP_2_V4_Sep25!B92 -> 2 | B101: =RRP_2_V4_Sep25!C92 -> 102 | C101: =RRP_2_V4_Sep25!D92 -> 70002 | D101: =RRP_2_V4_Sep25!E92 -> 45930 | E101: =RRP_2_V4_Sep25!F92 -> THB | F101: =RRP_2_V4_Sep25!G92 -> CALL | G101: =RRP_2_V4_Sep25!H92 -> 5500000 | H101: =RRP_2_V4_Sep25!I92 -> 45930.625 | ... J101: =RRP_2_V4_Sep25!K92 -> 45930.625
A102: =Repo_2_V4_Sep25!B86 -> 3 | B102: =Repo_2_V4_Sep25!C86 -> 102 | C102: =Repo_2_V4_Sep25!D86 -> 70004 | D102: =Repo_2_V4_Sep25!E86 -> 45929 | E102: =Repo_2_V4_Sep25!F86 -> THB | F102: =Repo_2_V4_Sep25!G86 -> RETURN | G102: =Repo_2_V4_Sep25!H86 -> 600000 | H102: =Repo_2_V4_Sep25!I86 -> 45929.625 | ... J102: =Repo_2_V4_Sep25!K86 -> 45929.625
A105: ='V4_Result_30 Sep 2025'!A101 -> cash_margin_movements
A106: {=TRANSPOSE('All Table_V4_Clean'!A317:A334)} -> cash_margin_movement_id | B106: margin_call_id | C106: counterparty_id | D106: repo_trade_id | E106: call_currency | F106: movement_type | G106: amount | H106: outstanding_balance | I106: value_date | J106: created_timestamp | K106: bank_account_code | L106: daily_accrued_int_receivable | M106: accrued_int_receivable | N106: interest_on_margin_code | O106: interest_on_margin_rate | P106: day_count_basis | Q106: accrual_days | R106: interest_direction
A107: =RRP_1_V4_Sep25!B137 -> 1 | B107: =RRP_1_V4_Sep25!C137 -> 1 | C107: =RRP_1_V4_Sep25!D137 -> 101 | D107: =RRP_1_V4_Sep25!E137 -> 70001 | E107: =RRP_1_V4_Sep25!F137 -> THB | F107: =RRP_1_V4_Sep25!G137 -> RECEIVE | G107: =RRP_1_V4_Sep25!H137 -> 2100000 | H107: =RRP_1_V4_Sep25!I137 -> 2100000 | ... R107: =RRP_1_V4_Sep25!S137 -> NONE
A108: =RRP_1_V4_Sep25!B138 -> 2 | B108: =RRP_1_V4_Sep25!C138 -> 1 | C108: =RRP_1_V4_Sep25!D138 -> 101 | D108: =RRP_1_V4_Sep25!E138 -> 70001 | E108: =RRP_1_V4_Sep25!F138 -> THB | F108: =RRP_1_V4_Sep25!G138 -> PAY | G108: =RRP_1_V4_Sep25!H138 -> -2100000 | H108: =RRP_1_V4_Sep25!I138 -> 0 | ... R108: =RRP_1_V4_Sep25!S138 -> NONE
A109: =RRP_2_V4_Sep25!B143 -> 3 | B109: =RRP_2_V4_Sep25!C143 -> 2 | C109: =RRP_2_V4_Sep25!D143 -> 102 | D109: =RRP_2_V4_Sep25!E143 -> 70002 | E109: =RRP_2_V4_Sep25!F143 -> THB | F109: =RRP_2_V4_Sep25!G143 -> RECEIVE | G109: =RRP_2_V4_Sep25!H143 -> 5500000 | H109: =RRP_2_V4_Sep25!I143 -> 5500000 | ... R109: =RRP_2_V4_Sep25!S143 -> NONE
A110: =Repo_2_V4_Sep25!B126 -> 4 | B110: =Repo_2_V4_Sep25!C126 -> 3 | C110: =Repo_2_V4_Sep25!D126 -> 102 | D110: =Repo_2_V4_Sep25!E126 -> 70004 | E110: =Repo_2_V4_Sep25!F126 -> THB | F110: =Repo_2_V4_Sep25!G126 -> PAY | G110: =Repo_2_V4_Sep25!H126 -> -600000 | H110: =Repo_2_V4_Sep25!I126 -> -600000 | ... R110: =Repo_2_V4_Sep25!S126 -> NONE
A111: =Repo_2_V4_Sep25!B134 -> 5 | B111: =Repo_2_V4_Sep25!C134 -> 3 | C111: =Repo_2_V4_Sep25!D134 -> 102 | D111: =Repo_2_V4_Sep25!E134 -> 70004 | E111: =Repo_2_V4_Sep25!F134 -> THB | F111: =Repo_2_V4_Sep25!G134 -> RECEIVE | G111: =Repo_2_V4_Sep25!H134 -> 600000 | H111: =Repo_2_V4_Sep25!I134 -> 0 | ... R111: =Repo_2_V4_Sep25!S134 -> RECEIVABLE
A113: ='V4_Result_30 Sep 2025'!A109 -> position_costing
A114: {=TRANSPOSE('All Table_V4_Clean'!A272:A280)} -> costing_id | B114: position_id | C114: cost_method | D114: avg_book_price_pct | E114: sum_product_clean | F114: total_nominal_in | G114: cumulative_sold_nominal | H114: realized_gain_loss_to_date | I114: last_realization_date
A115: ='Bond Buy-Sell_V4_Sep25 + Oct25'!A176 -> 1 | B115: ='Bond Buy-Sell_V4_Sep25 + Oct25'!B176 -> 1 | C115: ='Bond Buy-Sell_V4_Sep25 + Oct25'!C176 -> WAC | D115: ='Bond Buy-Sell_V4_Sep25 + Oct25'!D176 -> 101.7295 | E115: ='Bond Buy-Sell_V4_Sep25 + Oct25'!E176 -> 1.5259425e+08 | F115: ='Bond Buy-Sell_V4_Sep25 + Oct25'!F176 -> 150000000 | G115: ='Bond Buy-Sell_V4_Sep25 + Oct25'!G176 -> 100000000 | H115: ='Bond Buy-Sell_V4_Sep25 + Oct25'!H176 -> -512562.33 | I115: ='Bond Buy-Sell_V4_Sep25 + Oct25'!I176 -> 45917
A116: ='Bond sell_1_V4_Oct25'!B60 -> 2 | B116: ='Bond sell_1_V4_Oct25'!C60 -> 2 | C116: ='Bond sell_1_V4_Oct25'!D60 -> WAC | D116: ='Bond sell_1_V4_Oct25'!E60 -> 100.26487 | E116: ='Bond sell_1_V4_Oct25'!F60 -> 10026487100 | F116: ='Bond sell_1_V4_Oct25'!G60 -> 100000000 | G116: ='Bond sell_1_V4_Oct25'!H60 -> 50000000 | H116: ='Bond sell_1_V4_Oct25'!I60 -> -32435.5 | I116: ='Bond sell_1_V4_Oct25'!J60 -> 45952
A118: ='V4_Result_30 Sep 2025'!A113 -> position_realization_events
A119: {=TRANSPOSE('All Table_V4_Clean'!A286:A296)} -> realization_id | B119: position_id | C119: trade_id | D119: event_date | E119: sold_nominal | F119: sell_clean_price_pct | G119: avg_book_price_pct | H119: realized_gainloss | I119: accrued_int_realized | J119: method_used | K119: created_at
...

Sheet V4_Result_30 Nov 2025
A1: Export as of | B1: =DATE(2025,11,30) -> 45991 | D1: Timestamp update as of | E1: 46037.666
A3: ='V4_Result_30 Sep 2025'!A3 -> counterparty_master
A4: {=TRANSPOSE('All Table_V4_Clean'!A25:A39)} -> entity_id | B4: counterparty_id | C4: legal_name | D4: short_code | E4: counterparty_type | F4: bank_code | G4: swift_bic | H4: primary_credit_rating | I4: primary_rating_agency | J4: primary_rating_date | K4: created_date | L4: last_updated_date | M4: involved_party_type | N4: customer_code | O4: reside_in_thailand_flag
A5: =RRP_1_V4_Sep25!B13 -> BBL0107536000374 | B5: =RRP_1_V4_Sep25!C13 -> 101 | C5: =RRP_1_V4_Sep25!D13 -> BANGKOK BANK PCL | D5: =RRP_1_V4_Sep25!E13 -> BBL | E5: =RRP_1_V4_Sep25!F13 -> Commercial Bank | F5: =RRP_1_V4_Sep25!G13 -> 002 | G5: =RRP_1_V4_Sep25!H13 -> BKKBTHBK | H5: =RRP_1_V4_Sep25!I13 -> AA- | ... M5: =RRP_1_V4_Sep25!N13 -> 176039 | N5: 2008 | O5: TRUE
A6: =RRP_2_V4_Sep25!B13 -> KBANK0107536000315 | B6: =RRP_2_V4_Sep25!C13 -> 102 | C6: =RRP_2_V4_Sep25!D13 -> KASIKORNBANK PCL | D6: =RRP_2_V4_Sep25!E13 -> KBANK | E6: =RRP_2_V4_Sep25!F13 -> Commercial Bank | F6: =RRP_2_V4_Sep25!G13 -> 004 | G6: =RRP_2_V4_Sep25!H13 -> KASITHBK | H6: =RRP_2_V4_Sep25!I13 -> AA | ... M6: =RRP_2_V4_Sep25!N13 -> 176039 | N6: 2008 | O6: TRUE
A7: =Repo_1_V4_Sep25!B13 -> KTB107537000882 | B7: =Repo_1_V4_Sep25!C13 -> 103 | C7: =Repo_1_V4_Sep25!D13 -> KRUNGTHAI BANK PCL | D7: =Repo_1_V4_Sep25!E13 -> KTB | E7: =Repo_1_V4_Sep25!F13 -> Commercial Bank | F7: =Repo_1_V4_Sep25!G13 -> 006 | G7: =Repo_1_V4_Sep25!H13 -> KRTHTHBK | H7: =Repo_1_V4_Sep25!I13 -> AA+ | ... M7: =Repo_1_V4_Sep25!N13 -> 176039 | N7: 2008 | O7: TRUE
A8: ='IB Lend_V4_Oct25'!A12 -> CIMB0107537002338 | B8: ='IB Lend_V4_Oct25'!B12 -> 104 | C8: ='IB Lend_V4_Oct25'!C12 -> CIMB THAI BANK PCL | D8: ='IB Lend_V4_Oct25'!D12 -> CIMB | E8: ='IB Lend_V4_Oct25'!E12 -> Commercial Bank | F8: ='IB Lend_V4_Oct25'!F12 -> 022 | G8: ='IB Lend_V4_Oct25'!G12 -> UBOBTHBK | H8: ='IB Lend_V4_Oct25'!H12 -> AA(THA) | ... M8: ='IB Lend_V4_Oct25'!M12 -> 176039 | N8: 2008 | O8: TRUE
A9: ='IB Lend_V4_Oct25'!A11 -> SCB0107536000102 | B9: ='IB Lend_V4_Oct25'!B11 -> 113 | C9: ='IB Lend_V4_Oct25'!C11 -> SIAM COMMERCIAL BANK PCL | D9: ='IB Lend_V4_Oct25'!D11 -> SCB | E9: ='IB Lend_V4_Oct25'!E11 -> Commercial Bank | F9: ='IB Lend_V4_Oct25'!F11 -> 084 | G9: ='IB Lend_V4_Oct25'!G11 -> SICOTHBK | H9: ='IB Lend_V4_Oct25'!H11 -> AA+(THA) | ... M9: ='IB Lend_V4_Oct25'!M11 -> 176039 | N9: 2008 | O9: TRUE
A11: ='V4_Result_30 Sep 2025'!A10 -> security_master
A12: {=TRANSPOSE('All Table_V4_Clean'!A46:A68)} -> security_id | B12: isin | C12: issuer_id | D12: unique_id | E12: instrument_type | F12: issue_date | G12: maturity_date | H12: coupon_rate | I12: coupon_margin | J12: coupon_reference_rate | K12: coupon_frequency | L12: coupon_day_count_conv | M12: currency | N12: country | O12: bond_structure | P12: rating_tris | Q12: rating_fitch | R12: is_eligible_bot_repo_collateral | S12: is_eligible_crm_collateral | T12: status | U12: status_timestamp | V12: coupon_rate_type | W12: cross_default
A13: ='Bond buy_1_V4_Sep25'!B21 -> GSB26OA | B13: ='Bond buy_1_V4_Sep25'!C21 -> TH1029036A07 | C13: ='Bond buy_1_V4_Sep25'!D21 -> 3 | D13: ='Bond buy_1_V4_Sep25'!E21 -> 176017 | E13: ='Bond buy_1_V4_Sep25'!F21 -> SOE Bond | F13: ='Bond buy_1_V4_Sep25'!G21 -> 43754 | G13: ='Bond buy_1_V4_Sep25'!H21 -> 46311 | H13: ='Bond buy_1_V4_Sep25'!I21 -> 1.69 | ... V13: ='Bond buy_1_V4_Sep25'!W21 -> Fixed | W13: FALSE
A14: ='Bond buy_1_V4_Sep25'!B22 -> LB616A | B14: ='Bond buy_1_V4_Sep25'!C22 -> TH0623B3B607 | C14: ='Bond buy_1_V4_Sep25'!D22 -> 1 | D14: ='Bond buy_1_V4_Sep25'!E22 -> 176015 | E14: ='Bond buy_1_V4_Sep25'!F22 -> Gov Bond | F14: ='Bond buy_1_V4_Sep25'!G22 -> 40606 | G14: ='Bond buy_1_V4_Sep25'!H22 -> 58974 | H14: ='Bond buy_1_V4_Sep25'!I22 -> 4.85 | ... V14: ='Bond buy_1_V4_Sep25'!W22 -> Fixed | W14: FALSE
A15: ='Bond buy_1_V4_Sep25'!B23 -> TB26128A | B15: ='Bond buy_1_V4_Sep25'!C23 -> TH0623A76183 | C15: ='Bond buy_1_V4_Sep25'!D23 -> 1 | D15: ='Bond buy_1_V4_Sep25'!E23 -> 176015 | E15: ='Bond buy_1_V4_Sep25'!F23 -> T-Bill | F15: ='Bond buy_1_V4_Sep25'!G23 -> 45868 | G15: ='Bond buy_1_V4_Sep25'!H23 -> 46050 | H15: ='Bond buy_1_V4_Sep25'!I23 -> 0 | ... V15: ='Bond buy_1_V4_Sep25'!W23 -> Fixed | W15: FALSE
A16: ='Bond buy_1_V4_Sep25'!B24 -> BOT25NA | B16: ='Bond buy_1_V4_Sep25'!C24 -> TH0655035B00 | C16: ='Bond buy_1_V4_Sep25'!D24 -> 2 | D16: ='Bond buy_1_V4_Sep25'!E24 -> 001 | E16: ='Bond buy_1_V4_Sep25'!F24 -> BOT Bond | F16: ='Bond buy_1_V4_Sep25'!G24 -> 45236 | G16: ='Bond buy_1_V4_Sep25'!H24 -> 45967 | H16: ='Bond buy_1_V4_Sep25'!I24 -> 2.58 | ... V16: ='Bond buy_1_V4_Sep25'!W24 -> Fixed | W16: FALSE
A17: ='Bond buy_1_V4_Sep25'!B25 -> TB26211A | B17: ='Bond buy_1_V4_Sep25'!C25 -> TH0623076286 | C17: ='Bond buy_1_V4_Sep25'!D25 -> 1 | D17: ='Bond buy_1_V4_Sep25'!E25 -> 176015 | E17: ='Bond buy_1_V4_Sep25'!F25 -> T-Bill | F17: ='Bond buy_1_V4_Sep25'!G25 -> 45882 | G17: ='Bond buy_1_V4_Sep25'!H25 -> 46064 | H17: ='Bond buy_1_V4_Sep25'!I25 -> 0 | ... V17: ='Bond buy_1_V4_Sep25'!W25 -> Fixed | W17: FALSE
A18: ='Bond buy_1_V4_Sep25'!B26 -> BOTF267A | B18: ='Bond buy_1_V4_Sep25'!C26 -> TH0655036711 | C18: ='Bond buy_1_V4_Sep25'!D26 -> 2 | D18: ='Bond buy_1_V4_Sep25'!E26 -> 001 | E18: ='Bond buy_1_V4_Sep25'!F26 -> BOT Bond | F18: ='Bond buy_1_V4_Sep25'!G26 -> 45474 | G18: ='Bond buy_1_V4_Sep25'!H26 -> 46204 | H18: ='Bond buy_1_V4_Sep25'!I26 -> 1.68404 | ... V18: ='Bond buy_1_V4_Sep25'!W26 -> Floating | W18: FALSE
A19: =RRP_1_V4_Sep25!B19 -> LB29DA | B19: =RRP_1_V4_Sep25!C19 -> TH0623039C07 | C19: =RRP_1_V4_Sep25!D19 -> 1 | D19: =RRP_1_V4_Sep25!E19 -> 176015 | E19: =RRP_1_V4_Sep25!F19 -> Gov Bond | F19: =RRP_1_V4_Sep25!G19 -> 43784 | G19: =RRP_1_V4_Sep25!H19 -> 47469 | H19: =RRP_1_V4_Sep25!I19 -> 1.6 | ... V19: =RRP_1_V4_Sep25!W19 -> Fixed | W19: FALSE
A20: =RRP_2_V4_Sep25!B19 -> LB28DA | B20: =RRP_2_V4_Sep25!C19 -> TH0623038C09 | C20: =RRP_2_V4_Sep25!D19 -> 1 | D20: =RRP_2_V4_Sep25!E19 -> 176015 | E20: =RRP_2_V4_Sep25!F19 -> Gov Bond | F20: =RRP_2_V4_Sep25!G19 -> 43294 | G20: =RRP_2_V4_Sep25!H19 -> 47104 | H20: =RRP_2_V4_Sep25!I19 -> 2.875 | ... V20: =RRP_2_V4_Sep25!W19 -> Fixed | W20: FALSE
A21: ='Bond Buy-Sell_V4_Sep25 + Oct25'!A24 -> EXIM266A | B21: ='Bond Buy-Sell_V4_Sep25 + Oct25'!B24 -> TH0624036602 | C21: ='Bond Buy-Sell_V4_Sep25 + Oct25'!C24 -> 3 | D21: ='Bond Buy-Sell_V4_Sep25 + Oct25'!D24 -> 035 | E21: ='Bond Buy-Sell_V4_Sep25 + Oct25'!E24 -> SOE Bond | F21: ='Bond Buy-Sell_V4_Sep25 + Oct25'!F24 -> 45083 | G21: ='Bond Buy-Sell_V4_Sep25 + Oct25'!G24 -> 46179 | H21: ='Bond Buy-Sell_V4_Sep25 + Oct25'!H24 -> 2.71 | ... V21: ='Bond Buy-Sell_V4_Sep25 + Oct25'!V24 -> Fixed | W21: FALSE
A22: =RRP_3_V4_Nov25!B19 -> LB27DA | B22: =RRP_3_V4_Nov25!C19 -> TH0623037C05 | C22: =RRP_3_V4_Nov25!D19 -> 1 | D22: =RRP_3_V4_Nov25!E19 -> 176015 | E22: =RRP_3_V4_Nov25!F19 -> Gov Bond | F22: =RRP_3_V4_Nov25!G19 -> 40970 | G22: =RRP_3_V4_Nov25!H19 -> 46738 | H22: =RRP_3_V4_Nov25!I19 -> 3.58 | ... V22: =RRP_3_V4_Nov25!W19 -> Fixed | W22: FALSE
T24: =RRP_3_V4_Nov25!U21
A25: ='V4_Result_30 Sep 2025'!A22 -> portfolio_master | T25: =RRP_3_V4_Nov25!U22
A26: {=TRANSPOSE('All Table_V4_Clean'!A74:A78)} -> portfolio_id | B26: portfolio_name | C26: portfolio_manager | D26: accounting_treatment | E26: created_timestamp
A27: ='Bond buy_1_V4_Sep25'!B34 -> 301 | B27: ='Bond buy_1_V4_Sep25'!C34 -> AMC - Govt | C27: ='Bond buy_1_V4_Sep25'!D34 -> Treasury Desk | D27: ='Bond buy_1_V4_Sep25'!E34 -> AMC | E27: ='Bond buy_1_V4_Sep25'!F34 -> 45839
A28: ='Bond buy_1_V4_Sep25'!B35 -> 302 | B28: ='Bond buy_1_V4_Sep25'!C35 -> AMC - T-Bill | C28: ='Bond buy_1_V4_Sep25'!D35 -> Treasury Desk | D28: ='Bond buy_1_V4_Sep25'!E35 -> AMC | E28: ='Bond buy_1_V4_Sep25'!F35 -> 45839
A29: ='Bond buy_1_V4_Sep25'!B36 -> 303 | B29: ='Bond buy_1_V4_Sep25'!C36 -> AMC - BOT bond | C29: ='Bond buy_1_V4_Sep25'!D36 -> Treasury Desk | D29: ='Bond buy_1_V4_Sep25'!E36 -> AMC | E29: ='Bond buy_1_V4_Sep25'!F36 -> 45839
A30: ='Bond buy_1_V4_Sep25'!B37 -> 401 | B30: ='Bond buy_1_V4_Sep25'!C37 -> FVOCI - T-Bill | C30: ='Bond buy_1_V4_Sep25'!D37 -> Treasury Desk | D30: ='Bond buy_1_V4_Sep25'!E37 -> FVOCI | E30: ='Bond buy_1_V4_Sep25'!F37 -> 45839
A31: ='Bond buy_1_V4_Sep25'!B38 -> 402 | B31: ='Bond buy_1_V4_Sep25'!C38 -> FVOCI - BOT bond | C31: ='Bond buy_1_V4_Sep25'!D38 -> Treasury Desk | D31: ='Bond buy_1_V4_Sep25'!E38 -> FVOCI | E31: ='Bond buy_1_V4_Sep25'!F38 -> 45839
A32: ='Bond buy_1_V4_Sep25'!B39 -> 403 | B32: ='Bond buy_1_V4_Sep25'!C39 -> FVOCI - SOE | C32: ='Bond buy_1_V4_Sep25'!D39 -> Treasury Desk | D32: ='Bond buy_1_V4_Sep25'!E39 -> FVOCI | E32: ='Bond buy_1_V4_Sep25'!F39 -> 45839
A35: ='V4_Result_30 Sep 2025'!A32 -> netting_agreement
A36: {=TRANSPOSE('All Table_V4_Clean'!A84:A98)} -> netting_agreement_id | B36: counterparty_id | C36: netting_set_id | D36: agreement_type | E36: netting_type | F36: collateral_contract_type | G36: trade_date | H36: value_date | I36: maturity_date | J36: is_replacement | K36: replaced_agreement_id | L36: settlement_currency | M36: created_at | N36: updated_at | O36: agreement_status
A37: =RRP_1_V4_Sep25!B31 -> GMRA_2023_BB | B37: =RRP_1_V4_Sep25!C31 -> 101 | C37: =RRP_1_V4_Sep25!D31 -> 20001 | D37: =RRP_1_V4_Sep25!E31 -> GMRA | E37: =RRP_1_V4_Sep25!F31 -> COLLATERAL | F37: =RRP_1_V4_Sep25!G31 -> REP | G37: =RRP_1_V4_Sep25!H31 -> 45823 | H37: =RRP_1_V4_Sep25!I31 -> 45839 | ... O37: =RRP_1_V4_Sep25!P31 -> Active
A38: =RRP_2_V4_Sep25!B31 -> GMRA_2023_KB | B38: =RRP_2_V4_Sep25!C31 -> 102 | C38: =RRP_2_V4_Sep25!D31 -> 20002 | D38: =RRP_2_V4_Sep25!E31 -> GMRA | E38: =RRP_2_V4_Sep25!F31 -> COLLATERAL | F38: =RRP_2_V4_Sep25!G31 -> REP | G38: =RRP_2_V4_Sep25!H31 -> 45823 | H38: =RRP_2_V4_Sep25!I31 -> 45839 | ... O38: =RRP_2_V4_Sep25!P31 -> Active
A39: =Repo_1_V4_Sep25!B25 -> GMRA_2023_KT | B39: =Repo_1_V4_Sep25!C25 -> 103 | C39: =Repo_1_V4_Sep25!D25 -> 20003 | D39: =Repo_1_V4_Sep25!E25 -> GMRA | E39: =Repo_1_V4_Sep25!F25 -> COLLATERAL | F39: =Repo_1_V4_Sep25!G25 -> REP | G39: =Repo_1_V4_Sep25!H25 -> 45823 | H39: =Repo_1_V4_Sep25!I25 -> 45839 | ... O39: =Repo_1_V4_Sep25!P25 -> Active
A40: =Repo_2_V4_Sep25!B25 -> GMRA_2024_KB | B40: =Repo_2_V4_Sep25!C25 -> 102 | C40: =Repo_2_V4_Sep25!D25 -> 20004 | D40: =Repo_2_V4_Sep25!E25 -> GMRA | E40: =Repo_2_V4_Sep25!F25 -> COLLATERAL | F40: =Repo_2_V4_Sep25!G25 -> REP | G40: =Repo_2_V4_Sep25!H25 -> 45823 | H40: =Repo_2_V4_Sep25!I25 -> 45839 | ... O40: =Repo_2_V4_Sep25!P25 -> Active
A43: ='V4_Result_30 Sep 2025'!A40 -> limit_utilization
A44: {=TRANSPOSE('All Table_V4_Clean'!A340:A350)} -> limit_id | B44: counterparty_id | C44: limit_type | D44: currency | E44: available_line | F44: total_credit_line | G44: utilization_amount | H44: credit_line_approve_date | I44: timestamp | J44: created_date | K44: entity_id
A45: =RRP_1_V4_Sep25!B25 -> 1001 | B45: =RRP_1_V4_Sep25!C25 -> 101 | C45: =RRP_1_V4_Sep25!D25 -> REPO_LIMIT | D45: =RRP_1_V4_Sep25!E25 -> THB | E45: =RRP_1_V4_Sep25!F25 -> 800000000 | F45: =RRP_1_V4_Sep25!G25 -> 1000000000 | G45: =RRP_1_V4_Sep25!H25 -> 200000000 | H45: =RRP_1_V4_Sep25!I25 -> 45782 | ... K45: =RRP_1_V4_Sep25!L25 -> BBL0107536000374
A46: =RRP_3_V4_Nov25!B25 -> 1002 | B46: =RRP_3_V4_Nov25!C25 -> 102 | C46: =RRP_3_V4_Nov25!D25 -> REPO_LIMIT | D46: =RRP_3_V4_Nov25!E25 -> THB | E46: =RRP_3_V4_Nov25!F25 -> 1000000000 | F46: =RRP_3_V4_Nov25!G25 -> 1000000000 | G46: =RRP_3_V4_Nov25!H25 -> 300000000 | H46: =RRP_3_V4_Nov25!I25 -> 45782 | ... K46: =RRP_3_V4_Nov25!L25 -> KBANK0107536000315
A47: ='IB Lend_V4_Sep25'!A135 -> 2001 | B47: ='IB Lend_V4_Sep25'!B135 -> 101 | C47: ='IB Lend_V4_Sep25'!C135 -> PLACEMENT_LIMIT | D47: ='IB Lend_V4_Sep25'!D135 -> THB | E47: ='IB Lend_V4_Sep25'!E135 -> 500000000 | F47: ='IB Lend_V4_Sep25'!F135 -> 1000000000 | G47: ='IB Lend_V4_Sep25'!G135 -> 500000000 | H47: ='IB Lend_V4_Sep25'!H135 -> 45901 | ... K47: ='IB Lend_V4_Sep25'!K135 -> BBL0107536000374
A48: ='IB Lend_V4_Sep25'!A226 -> 2002 | B48: ='IB Lend_V4_Sep25'!B226 -> 104 | C48: ='IB Lend_V4_Sep25'!C226 -> PLACEMENT_LIMIT | D48: ='IB Lend_V4_Sep25'!D226 -> THB | E48: ='IB Lend_V4_Sep25'!E226 -> 400000000 | F48: ='IB Lend_V4_Sep25'!F226 -> 500000000 | G48: ='IB Lend_V4_Sep25'!G226 -> 100000000 | H48: ='IB Lend_V4_Sep25'!H226 -> 45828 | ... K48: ='IB Lend_V4_Sep25'!K226 -> CIMB0107537002338
A49: ='IB Lend_V4_Nov 25'!A113 -> 2003 | B49: ='IB Lend_V4_Nov 25'!B113 -> 113 | C49: ='IB Lend_V4_Nov 25'!C113 -> PLACEMENT_LIMIT | D49: ='IB Lend_V4_Nov 25'!D113 -> THB | E49: ='IB Lend_V4_Nov 25'!E113 -> 500000000 | F49: ='IB Lend_V4_Nov 25'!F113 -> 1000000000 | G49: ='IB Lend_V4_Nov 25'!G113 -> 500000000 | H49: ='IB Lend_V4_Nov 25'!H113 -> 45931 | ... K49: ='IB Lend_V4_Nov 25'!K113 -> SCB0107536000102
A52: ='V4_Result_30 Sep 2025'!A48 -> repo_trades
A53: {=TRANSPOSE('All Table_V4_Clean'!A146:A171)} -> repo_trade_id | B53: trade_date | C53: trade_type | D53: counterparty_id | E53: netting_agreement_id | F53: netting_set_id | G53: nominal_amount | H53: purchase_date | I53: repurchase_date | J53: purchase_price | K53: repurchase_price | L53: currency | M53: reference_rate_id | N53: interest_rate_type | O53: interest_rate | P53: reference_rate | Q53: margin | R53: day_count_convention | S53: repo_rate | T53: term | U53: repo_out_flag | V53: repo_in_flag | W53: status | X53: limit_id | Y53: accrued_interest | Z53: entity_id
A54: =RRP_1_V4_Sep25!B123 -> 70001 | B54: =RRP_1_V4_Sep25!C123 -> 45905.583 | C54: =RRP_1_V4_Sep25!D123 -> Reverse REPO | D54: =RRP_1_V4_Sep25!E123 -> 101 | E54: =RRP_1_V4_Sep25!F123 -> GMRA_2023_BB | F54: =RRP_1_V4_Sep25!G123 -> 20001 | G54: =RRP_1_V4_Sep25!H123 -> 200000000 | H54: =RRP_1_V4_Sep25!I123 -> 45908 | ... Z54: =RRP_1_V4_Sep25!AA123 -> BBL0107536000374
A55: =RRP_2_V4_Oct25!B25 -> 70002 | B55: =RRP_2_V4_Oct25!C25 -> 45926.583 | C55: =RRP_2_V4_Oct25!D25 -> Reverse REPO | D55: =RRP_2_V4_Oct25!E25 -> 102 | E55: =RRP_2_V4_Oct25!F25 -> GMRA_2023_KB | F55: =RRP_2_V4_Oct25!G25 -> 20002 | G55: =RRP_2_V4_Oct25!H25 -> 300000000 | H55: =RRP_2_V4_Oct25!I25 -> 45929 | ... Y55: =RRP_2_V4_Oct25!Z25 -> 0 | Z55: =RRP_2_V4_Sep25!B13 -> KBANK0107536000315
A56: =Repo_1_V4_Sep25!B107 -> 70003 | B56: =Repo_1_V4_Sep25!C107 -> 45922.417 | C56: =Repo_1_V4_Sep25!D107 -> REPO | D56: =Repo_1_V4_Sep25!E107 -> 103 | E56: =Repo_1_V4_Sep25!F107 -> GMRA_2023_KT | F56: =Repo_1_V4_Sep25!G107 -> 20003 | G56: =Repo_1_V4_Sep25!H107 -> 50000000 | H56: =Repo_1_V4_Sep25!I107 -> 45924 | ... Z56: =Repo_1_V4_Sep25!AA107 -> KTB107537000882
A57: =Repo_2_V4_Oct25!B25 -> 70004 | B57: =Repo_2_V4_Oct25!C25 -> 45924.417 | C57: =Repo_2_V4_Oct25!D25 -> REPO | D57: =Repo_2_V4_Oct25!E25 -> 102 | E57: =Repo_2_V4_Oct25!F25 -> GMRA_2024_KB | F57: =Repo_2_V4_Oct25!G25 -> 20004 | G57: =Repo_2_V4_Oct25!H25 -> 30000000 | H57: =Repo_2_V4_Oct25!I25 -> 45926 | ... Y57: =Repo_2_V4_Oct25!Z25 -> 0 | Z57: =Z55 -> KBANK0107536000315
A58: =RRP_3_V4_Nov25!B118 -> 70005 | B58: =RRP_3_V4_Nov25!C118 -> 45985.583 | C58: =RRP_3_V4_Nov25!D118 -> Reverse REPO | D58: =RRP_3_V4_Nov25!E118 -> 102 | E58: =RRP_3_V4_Nov25!F118 -> GMRA_2023_KB | F58: =RRP_3_V4_Nov25!G118 -> 20002 | G58: =RRP_3_V4_Nov25!H118 -> 300000000 | H58: =RRP_3_V4_Nov25!I118 -> 45987 | ... Z58: =RRP_3_V4_Nov25!AA118 -> KBANK0107536000315
A59: =Repo_3_V4_Nov25!B113 -> 70006 | B59: =Repo_3_V4_Nov25!C113 -> 45985.417 | C59: =Repo_3_V4_Nov25!D113 -> REPO | D59: =Repo_3_V4_Nov25!E113 -> 102 | E59: =Repo_3_V4_Nov25!F113 -> GMRA_2024_KB | F59: =Repo_3_V4_Nov25!G113 -> 20004 | G59: =Repo_3_V4_Nov25!H113 -> 20000000 | H59: =Repo_3_V4_Nov25!I113 -> 45987 | ... Z59: =Repo_3_V4_Nov25!AA113 -> KBANK0107536000315
A62: ='V4_Result_30 Sep 2025'!A56 -> collateral_positions
A63: {=TRANSPOSE('All Table_V4_Clean'!A177:A187)} -> collateral_id | B63: repo_trade_id | C63: security_id | D63: nominal_amount | E63: allocation_date | F63: valuation_price | G63: market_value | H63: haircut_percentage | I63: collateral_value_after_haircut | J63: margin_call_id | K63: currency
A64: =RRP_1_V4_Sep25!B66 -> 70001_LB29DA_1 | B64: =RRP_1_V4_Sep25!C66 -> 70001 | C64: =RRP_1_V4_Sep25!D66 -> LB29DA | D64: =RRP_1_V4_Sep25!E66 -> 205000000 | E64: =RRP_1_V4_Sep25!F66 -> 45908 | F64: =RRP_1_V4_Sep25!G66 -> 99.85 | G64: =RRP_1_V4_Sep25!H66 -> 204692500 | H64: =RRP_1_V4_Sep25!I66 -> 2 | ... K64: =RRP_1_V4_Sep25!L66 -> THB
A65: =RRP_2_V4_Sep25!B66 -> 70002_LB28DA_1 | B65: =RRP_2_V4_Sep25!C66 -> 70002 | C65: =RRP_2_V4_Sep25!D66 -> LB28DA | D65: =RRP_2_V4_Sep25!E66 -> 305000000 | E65: =RRP_2_V4_Sep25!F66 -> 45929 | F65: =RRP_2_V4_Sep25!G66 -> 100.1 | G65: =RRP_2_V4_Sep25!H66 -> 305305000 | H65: =RRP_2_V4_Sep25!I66 -> 2 | ... K65: =RRP_2_V4_Sep25!L66 -> THB
A66: =Repo_1_V4_Sep25!B60 -> 70003_LB616A_1 | B66: =Repo_1_V4_Sep25!C60 -> 70003 | C66: =Repo_1_V4_Sep25!D60 -> LB616A | D66: =Repo_1_V4_Sep25!E60 -> 50000000 | E66: =Repo_1_V4_Sep25!F60 -> 45924 | F66: =Repo_1_V4_Sep25!G60 -> 170.81 | G66: =Repo_1_V4_Sep25!H60 -> 85405000 | H66: =Repo_1_V4_Sep25!I60 -> 2 | ... K66: =Repo_1_V4_Sep25!L60 -> THB
A67: =Repo_2_V4_Sep25!B60 -> 70004_BOT25NA_1 | B67: =Repo_2_V4_Sep25!C60 -> 70004 | C67: =Repo_2_V4_Sep25!D60 -> BOT25NA | D67: =Repo_2_V4_Sep25!E60 -> 30000000 | E67: =Repo_2_V4_Sep25!F60 -> 45926 | F67: =Repo_2_V4_Sep25!G60 -> 100.25761 | G67: =Repo_2_V4_Sep25!H60 -> 30078000 | H67: =Repo_2_V4_Sep25!I60 -> 2 | ... K67: =Repo_2_V4_Sep25!L60 -> THB
A68: =RRP_3_V4_Nov25!B66 -> 70005_LB27DA_1 | B68: =RRP_3_V4_Nov25!C66 -> 70005 | C68: =RRP_3_V4_Nov25!D66 -> LB27DA | D68: =RRP_3_V4_Nov25!E66 -> 305000000 | E68: =RRP_3_V4_Nov25!F66 -> 45987 | F68: =RRP_3_V4_Nov25!G66 -> 116.5 | G68: =RRP_3_V4_Nov25!H66 -> 355325000 | H68: =RRP_3_V4_Nov25!I66 -> 2 | ... K68: =RRP_3_V4_Nov25!L66 -> THB
A69: =Repo_3_V4_Nov25!B60 -> 70006_LB616A_1 | B69: =Repo_3_V4_Nov25!C60 -> 70006 | C69: =Repo_3_V4_Nov25!D60 -> LB616A | D69: =Repo_3_V4_Nov25!E60 -> 20000000 | E69: =Repo_3_V4_Nov25!F60 -> 45987 | F69: =Repo_3_V4_Nov25!G60 -> 156.78 | G69: =Repo_3_V4_Nov25!H60 -> 31356000 | H69: =Repo_3_V4_Nov25!I60 -> 2 | ... K69: =Repo_3_V4_Nov25!L60 -> THB
A72: ='V4_Result_30 Sep 2025'!A64 -> bond_trades
A73: {=TRANSPOSE('All Table_V4_Clean'!A193:A203)} -> bond_trade_id | B73: portfolio_id | C73: trade_date | D73: settlement_date | E73: security_id | F73: counterparty_id | G73: trade_type | H73: nominal_amount | I73: clean_price_trade | J73: yield_to_maturity | K73: settlement_status
A74: ='Bond Buy-Sell_V4_Sep25 + Oct25'!A96 -> 90001 | B74: ='Bond Buy-Sell_V4_Sep25 + Oct25'!B96 -> 403 | C74: ='Bond Buy-Sell_V4_Sep25 + Oct25'!C96 -> 45659 | D74: ='Bond Buy-Sell_V4_Sep25 + Oct25'!D96 -> 45663 | E74: ='Bond Buy-Sell_V4_Sep25 + Oct25'!E96 -> EXIM266A | F74: ='Bond Buy-Sell_V4_Sep25 + Oct25'!F96 -> 101 | G74: ='Bond Buy-Sell_V4_Sep25 + Oct25'!G96 -> Buy | H74: ='Bond Buy-Sell_V4_Sep25 + Oct25'!H96 -> 100000000 | ... K74: ='Bond Buy-Sell_V4_Sep25 + Oct25'!K96 -> Settled
A75: ='Bond Buy-Sell_V4_Sep25 + Oct25'!A97 -> 90002 | B75: ='Bond Buy-Sell_V4_Sep25 + Oct25'!B97 -> 403 | C75: ='Bond Buy-Sell_V4_Sep25 + Oct25'!C97 -> 45726 | D75: ='Bond Buy-Sell_V4_Sep25 + Oct25'!D97 -> 45728 | E75: ='Bond Buy-Sell_V4_Sep25 + Oct25'!E97 -> EXIM266A | F75: ='Bond Buy-Sell_V4_Sep25 + Oct25'!F97 -> 101 | G75: ='Bond Buy-Sell_V4_Sep25 + Oct25'!G97 -> Buy | H75: ='Bond Buy-Sell_V4_Sep25 + Oct25'!H97 -> 50000000 | ... K75: ='Bond Buy-Sell_V4_Sep25 + Oct25'!K97 -> Settled
A76: ='Bond Buy-Sell_V4_Sep25 + Oct25'!A98 -> 90003 | B76: ='Bond Buy-Sell_V4_Sep25 + Oct25'!B98 -> 403 | C76: ='Bond Buy-Sell_V4_Sep25 + Oct25'!C98 -> 45915 | D76: ='Bond Buy-Sell_V4_Sep25 + Oct25'!D98 -> 45917 | E76: ='Bond Buy-Sell_V4_Sep25 + Oct25'!E98 -> EXIM266A | F76: ='Bond Buy-Sell_V4_Sep25 + Oct25'!F98 -> 101 | G76: ='Bond Buy-Sell_V4_Sep25 + Oct25'!G98 -> Sell | H76: ='Bond Buy-Sell_V4_Sep25 + Oct25'!H98 -> 100000000 | ... K76: ='Bond Buy-Sell_V4_Sep25 + Oct25'!K98 -> Settled
A77: ='Bond buy_1_V4_Sep25'!B65 -> 90004 | B77: ='Bond buy_1_V4_Sep25'!C65 -> 403 | C77: ='Bond buy_1_V4_Sep25'!D65 -> 45854.458 | D77: ='Bond buy_1_V4_Sep25'!E65 -> 45856.458 | E77: ='Bond buy_1_V4_Sep25'!F65 -> GSB26OA | F77: ='Bond buy_1_V4_Sep25'!G65 -> 102 | G77: ='Bond buy_1_V4_Sep25'!H65 -> Buy | H77: ='Bond buy_1_V4_Sep25'!I65 -> 100000000 | ... K77: ='Bond buy_1_V4_Sep25'!L65 -> Settled
A78: ='Bond buy_1_V4_Sep25'!B66 -> 90005 | B78: ='Bond buy_1_V4_Sep25'!C66 -> 301 | C78: ='Bond buy_1_V4_Sep25'!D66 -> 45917.458 | D78: ='Bond buy_1_V4_Sep25'!E66 -> 45919.458 | E78: ='Bond buy_1_V4_Sep25'!F66 -> LB616A | F78: ='Bond buy_1_V4_Sep25'!G66 -> 101 | G78: ='Bond buy_1_V4_Sep25'!H66 -> Buy | H78: ='Bond buy_1_V4_Sep25'!I66 -> 100000000 | ... K78: ='Bond buy_1_V4_Sep25'!L66 -> Settled
A79: ='Bond buy_1_V4_Sep25'!B67 -> 90006 | B79: ='Bond buy_1_V4_Sep25'!C67 -> 302 | C79: ='Bond buy_1_V4_Sep25'!D67 -> 45917.458 | D79: ='Bond buy_1_V4_Sep25'!E67 -> 45919.458 | E79: ='Bond buy_1_V4_Sep25'!F67 -> TB26128A | F79: ='Bond buy_1_V4_Sep25'!G67 -> 101 | G79: ='Bond buy_1_V4_Sep25'!H67 -> Buy | H79: ='Bond buy_1_V4_Sep25'!I67 -> 100000000 | ... K79: ='Bond buy_1_V4_Sep25'!L67 -> Settled
A80: ='Bond buy_1_V4_Sep25'!B68 -> 90007 | B80: ='Bond buy_1_V4_Sep25'!C68 -> 303 | C80: ='Bond buy_1_V4_Sep25'!D68 -> 45917.458 | D80: ='Bond buy_1_V4_Sep25'!E68 -> 45919.458 | E80: ='Bond buy_1_V4_Sep25'!F68 -> BOT25NA | F80: ='Bond buy_1_V4_Sep25'!G68 -> 101 | G80: ='Bond buy_1_V4_Sep25'!H68 -> Buy | H80: ='Bond buy_1_V4_Sep25'!I68 -> 100000000 | ... K80: ='Bond buy_1_V4_Sep25'!L68 -> Settled
A81: ='Bond buy_1_V4_Sep25'!B69 -> 90008 | B81: ='Bond buy_1_V4_Sep25'!C69 -> 401 | C81: ='Bond buy_1_V4_Sep25'!D69 -> 45917.458 | D81: ='Bond buy_1_V4_Sep25'!E69 -> 45919.458 | E81: ='Bond buy_1_V4_Sep25'!F69 -> TB26211A | F81: ='Bond buy_1_V4_Sep25'!G69 -> 102 | G81: ='Bond buy_1_V4_Sep25'!H69 -> Buy | H81: ='Bond buy_1_V4_Sep25'!I69 -> 100000000 | ... K81: ='Bond buy_1_V4_Sep25'!L69 -> Settled
A82: ='Bond buy_1_V4_Sep25'!B70 -> 90009 | B82: ='Bond buy_1_V4_Sep25'!C70 -> 402 | C82: ='Bond buy_1_V4_Sep25'!D70 -> 45917.458 | D82: ='Bond buy_1_V4_Sep25'!E70 -> 45919.458 | E82: ='Bond buy_1_V4_Sep25'!F70 -> BOTF267A | F82: ='Bond buy_1_V4_Sep25'!G70 -> 102 | G82: ='Bond buy_1_V4_Sep25'!H70 -> Buy | H82: ='Bond buy_1_V4_Sep25'!I70 -> 100000000 | ... K82: ='Bond buy_1_V4_Sep25'!L70 -> Settled
A83: ='Bond Buy-Sell_V4_Sep25 + Oct25'!A151 -> 90010 | B83: ='Bond Buy-Sell_V4_Sep25 + Oct25'!B151 -> 403 | C83: ='Bond Buy-Sell_V4_Sep25 + Oct25'!C151 -> 45955 | D83: ='Bond Buy-Sell_V4_Sep25 + Oct25'!D151 -> 45959 | E83: ='Bond Buy-Sell_V4_Sep25 + Oct25'!E151 -> EXIM266A | F83: ='Bond Buy-Sell_V4_Sep25 + Oct25'!F151 -> 101 | G83: ='Bond Buy-Sell_V4_Sep25 + Oct25'!G151 -> Buy | H83: ='Bond Buy-Sell_V4_Sep25 + Oct25'!H151 -> 100000000 | ... K83: ='Bond Buy-Sell_V4_Sep25 + Oct25'!K151 -> Settled
A84: ='Bond sell_1_V4_Oct25'!B31 -> 90011 | B84: ='Bond sell_1_V4_Oct25'!C31 -> 403 | C84: ='Bond sell_1_V4_Oct25'!D31 -> 45950.458 | D84: ='Bond sell_1_V4_Oct25'!E31 -> 45952.458 | E84: ='Bond sell_1_V4_Oct25'!F31 -> GSB26OA | F84: ='Bond sell_1_V4_Oct25'!G31 -> 102 | G84: ='Bond sell_1_V4_Oct25'!H31 -> Sell | H84: ='Bond sell_1_V4_Oct25'!I31 -> 50000000 | ... K84: ='Bond sell_1_V4_Oct25'!L31 -> Settled
A88: ='V4_Result_30 Sep 2025'!A77 -> bond_transactions
A89: {=TRANSPOSE('All Table_V4_Clean'!A209:A238)} -> trade_id | B89: security_id | C89: portfolio_id | D89: counterparty_id | E89: trade_type | F89: trade_date | G89: settlement_date | H89: maturity_date | I89: currency | J89: nominal_amount | K89: clean_price | L89: clean_price_trade | M89: accrued_interest | N89: dirty_price | O89: classification | P89: book_value | Q89: market_clean_value | R89: market_value | S89: last_coupon_date | T89: coupon_rate_type | U89: coupon_reference_rate | V89: coupon_margin | W89: coupon_frequency | X89: coupon_rate | Y89: coupon_day_count_conv | Z89: rating_tris | AA89: rating_fitch | AB89: status | AC89: last_updated_timestamp | AD89: valuation_date
A90: ='Bond Buy-Sell_V4_Sep25 + Oct25'!A209 -> 90001 | B90: ='Bond Buy-Sell_V4_Sep25 + Oct25'!B209 -> EXIM266A | C90: ='Bond Buy-Sell_V4_Sep25 + Oct25'!C209 -> 403 | D90: ='Bond Buy-Sell_V4_Sep25 + Oct25'!D209 -> 101 | E90: ='Bond Buy-Sell_V4_Sep25 + Oct25'!E209 -> Buy | F90: ='Bond Buy-Sell_V4_Sep25 + Oct25'!F209 -> 45659 | G90: ='Bond Buy-Sell_V4_Sep25 + Oct25'!G209 -> 45663 | H90: ='Bond Buy-Sell_V4_Sep25 + Oct25'!H209 -> 46179 | ... AD90: ='Bond Buy-Sell_V4_Sep25 + Oct25'!AD209 -> 45961
A91: ='Bond Buy-Sell_V4_Sep25 + Oct25'!A210 -> 90002 | B91: ='Bond Buy-Sell_V4_Sep25 + Oct25'!B210 -> EXIM266A | C91: ='Bond Buy-Sell_V4_Sep25 + Oct25'!C210 -> 403 | D91: ='Bond Buy-Sell_V4_Sep25 + Oct25'!D210 -> 101 | E91: ='Bond Buy-Sell_V4_Sep25 + Oct25'!E210 -> Buy | F91: ='Bond Buy-Sell_V4_Sep25 + Oct25'!F210 -> 45726 | G91: ='Bond Buy-Sell_V4_Sep25 + Oct25'!G210 -> 45728 | H91: ='Bond Buy-Sell_V4_Sep25 + Oct25'!H210 -> 46179 | ... AD91: ='Bond Buy-Sell_V4_Sep25 + Oct25'!AD210 -> 45961
A92: ='Bond Buy-Sell_V4_Sep25 + Oct25'!A211 -> 90003 | B92: ='Bond Buy-Sell_V4_Sep25 + Oct25'!B211 -> EXIM266A | C92: ='Bond Buy-Sell_V4_Sep25 + Oct25'!C211 -> 403 | D92: ='Bond Buy-Sell_V4_Sep25 + Oct25'!D211 -> 101 | E92: ='Bond Buy-Sell_V4_Sep25 + Oct25'!E211 -> Sell | F92: ='Bond Buy-Sell_V4_Sep25 + Oct25'!F211 -> 45915 | G92: ='Bond Buy-Sell_V4_Sep25 + Oct25'!G211 -> 45917 | H92: ='Bond Buy-Sell_V4_Sep25 + Oct25'!H211 -> 46179 | ... AD92: ='Bond Buy-Sell_V4_Sep25 + Oct25'!AD211 -> 45961
A93: ='Bond buy_1_V4_Oct25'!B78 -> 90004 | B93: ='Bond buy_1_V4_Oct25'!C78 -> GSB26OA | C93: ='Bond buy_1_V4_Oct25'!D78 -> 403 | D93: ='Bond buy_1_V4_Oct25'!E78 -> 102 | E93: ='Bond buy_1_V4_Oct25'!F78 -> Buy | F93: ='Bond buy_1_V4_Oct25'!G78 -> 45854 | G93: ='Bond buy_1_V4_Oct25'!H78 -> 45856 | H93: ='Bond buy_1_V4_Oct25'!I78 -> 46311 | ... T93: ='Bond buy_1_V4_Oct25'!U78 -> Fixed | V93: ='Bond buy_1_V4_Oct25'!W78 -> 0 | W93: ='Bond buy_1_V4_Oct25'!X78 -> Semi-Annual | X93: ='Bond buy_1_V4_Oct25'!Y78 -> 1.69 | Y93: ='Bond buy_1_V4_Oct25'!Z78 -> Actual/365 | Z93: ='Bond buy_1_V4_Oct25'!AA78 -> AAA | AA93: ='Bond buy_1_V4_Oct25'!AB78 -> AAA(tha) | AB93: ='Bond buy_1_V4_Oct25'!AC78 -> Active | AC93: ='Bond buy_1_V4_Oct25'!AD78 -> 45946.458 | AD93: ='Bond buy_1_V4_Oct25'!AE78 -> 45946
A94: ='Bond buy_1_V4_Oct25'!B79 -> 90005 | B94: ='Bond buy_1_V4_Oct25'!C79 -> LB616A | C94: ='Bond buy_1_V4_Oct25'!D79 -> 301 | D94: ='Bond buy_1_V4_Oct25'!E79 -> 101 | E94: ='Bond buy_1_V4_Oct25'!F79 -> Buy | F94: ='Bond buy_1_V4_Oct25'!G79 -> 45917 | G94: ='Bond buy_1_V4_Oct25'!H79 -> 45919 | H94: ='Bond buy_1_V4_Oct25'!I79 -> 58974 | ... T94: ='Bond buy_1_V4_Oct25'!U79 -> Fixed | V94: ='Bond buy_1_V4_Oct25'!W79 -> 0 | W94: ='Bond buy_1_V4_Oct25'!X79 -> Semi-Annual | X94: ='Bond buy_1_V4_Oct25'!Y79 -> 4.85 | Y94: ='Bond buy_1_V4_Oct25'!Z79 -> Actual/365 | Z94: ='Bond buy_1_V4_Oct25'!AA79 -> AAA | AA94: ='Bond buy_1_V4_Oct25'!AB79 -> AAA(tha) | AB94: ='Bond buy_1_V4_Oct25'!AC79 -> Active | AC94: ='Bond buy_1_V4_Oct25'!AD79 -> 45961.458 | AD94: ='Bond buy_1_V4_Oct25'!AE79 -> 45961
A95: ='Bond buy_1_V4_Oct25'!B80 -> 90006 | B95: ='Bond buy_1_V4_Oct25'!C80 -> TB26128A | C95: ='Bond buy_1_V4_Oct25'!D80 -> 302 | D95: ='Bond buy_1_V4_Oct25'!E80 -> 101 | E95: ='Bond buy_1_V4_Oct25'!F80 -> Buy | F95: ='Bond buy_1_V4_Oct25'!G80 -> 45917 | G95: ='Bond buy_1_V4_Oct25'!H80 -> 45919 | H95: ='Bond buy_1_V4_Oct25'!I80 -> 46050 | ... T95: ='Bond buy_1_V4_Oct25'!U80 -> Fixed | V95: ='Bond buy_1_V4_Oct25'!W80 -> 0 | W95: ='Bond buy_1_V4_Oct25'!X80 -> At Maturity | X95: ='Bond buy_1_V4_Oct25'!Y80 -> 0 | Y95: ='Bond buy_1_V4_Oct25'!Z80 -> Actual/365 | Z95: ='Bond buy_1_V4_Oct25'!AA80 -> AAA | AA95: ='Bond buy_1_V4_Oct25'!AB80 -> AAA(tha) | AB95: ='Bond buy_1_V4_Oct25'!AC80 -> Active | AC95: ='Bond buy_1_V4_Oct25'!AD80 -> 45961.458 | AD95: ='Bond buy_1_V4_Oct25'!AE80 -> 45961
A96: ='Bond buy_1_V4_Oct25'!B81 -> 90007 | B96: ='Bond buy_1_V4_Oct25'!C81 -> BOT25NA | C96: ='Bond buy_1_V4_Oct25'!D81 -> 303 | D96: ='Bond buy_1_V4_Oct25'!E81 -> 101 | E96: ='Bond buy_1_V4_Oct25'!F81 -> Buy | F96: ='Bond buy_1_V4_Oct25'!G81 -> 45917 | G96: ='Bond buy_1_V4_Oct25'!H81 -> 45919 | H96: ='Bond buy_1_V4_Oct25'!I81 -> 45967 | ... T96: ='Bond buy_1_V4_Oct25'!U81 -> Fixed | V96: ='Bond buy_1_V4_Oct25'!W81 -> 0 | W96: ='Bond buy_1_V4_Oct25'!X81 -> Semi-Annual | X96: ='Bond buy_1_V4_Oct25'!Y81 -> 2.58 | Y96: ='Bond buy_1_V4_Oct25'!Z81 -> Actual/365 | Z96: ='Bond buy_1_V4_Oct25'!AA81 -> AAA | AA96: ='Bond buy_1_V4_Oct25'!AB81 -> AAA(tha) | AB96: ='Bond buy_1_V4_Oct25'!AC81 -> Active | AC96: ='Bond buy_1_V4_Oct25'!AD81 -> 45961.458 | AD96: ='Bond buy_1_V4_Oct25'!AE81 -> 45961
A97: ='Bond buy_1_V4_Oct25'!B82 -> 90008 | B97: ='Bond buy_1_V4_Oct25'!C82 -> TB26211A | C97: ='Bond buy_1_V4_Oct25'!D82 -> 401 | D97: ='Bond buy_1_V4_Oct25'!E82 -> 102 | E97: ='Bond buy_1_V4_Oct25'!F82 -> Buy | F97: ='Bond buy_1_V4_Oct25'!G82 -> 45917 | G97: ='Bond buy_1_V4_Oct25'!H82 -> 45919 | H97: ='Bond buy_1_V4_Oct25'!I82 -> 46064 | ... T97: ='Bond buy_1_V4_Oct25'!U82 -> Fixed | V97: ='Bond buy_1_V4_Oct25'!W82 -> 0 | W97: ='Bond buy_1_V4_Oct25'!X82 -> At Maturity | X97: ='Bond buy_1_V4_Oct25'!Y82 -> 0 | Y97: ='Bond buy_1_V4_Oct25'!Z82 -> Actual/365 | Z97: ='Bond buy_1_V4_Oct25'!AA82 -> AAA | AA97: ='Bond buy_1_V4_Oct25'!AB82 -> AAA(tha) | AB97: ='Bond buy_1_V4_Oct25'!AC82 -> Active | AC97: ='Bond buy_1_V4_Oct25'!AD82 -> 45961.458 | AD97: ='Bond buy_1_V4_Oct25'!AE82 -> 45961
A98: ='Bond buy_1_V4_Oct25'!B83 -> 90009 | B98: ='Bond buy_1_V4_Oct25'!C83 -> BOTF267A | C98: ='Bond buy_1_V4_Oct25'!D83 -> 402 | D98: ='Bond buy_1_V4_Oct25'!E83 -> 102 | E98: ='Bond buy_1_V4_Oct25'!F83 -> Buy | F98: ='Bond buy_1_V4_Oct25'!G83 -> 45917 | G98: ='Bond buy_1_V4_Oct25'!H83 -> 45919 | H98: ='Bond buy_1_V4_Oct25'!I83 -> 46204 | ... T98: ='Bond buy_1_V4_Oct25'!U83 -> Floating | V98: ='Bond buy_1_V4_Oct25'!W83 -> 0.05 | W98: ='Bond buy_1_V4_Oct25'!X83 -> Quarterly | X98: ='Bond buy_1_V4_Oct25'!Y83 -> 1.68404 | Y98: ='Bond buy_1_V4_Oct25'!Z83 -> Actual/365 | Z98: ='Bond buy_1_V4_Oct25'!AA83 -> AAA | AA98: ='Bond buy_1_V4_Oct25'!AB83 -> AAA(tha) | AB98: ='Bond buy_1_V4_Oct25'!AC83 -> Active | AC98: ='Bond buy_1_V4_Oct25'!AD83 -> 45961.458 | AD98: ='Bond buy_1_V4_Oct25'!AE83 -> 45961
A99: =RRP_1_V4_Sep25!B129 -> 70001 | B99: =RRP_1_V4_Sep25!C129 -> LB29DA | C99: =RRP_1_V4_Sep25!D129 -> 301 | D99: =RRP_1_V4_Sep25!E129 -> 101 | E99: =RRP_1_V4_Sep25!F129 -> ReverseRepo | F99: =RRP_1_V4_Sep25!G129 -> 45905 | G99: =RRP_1_V4_Sep25!H129 -> 45908 | H99: =RRP_1_V4_Sep25!I129 -> 45915 | ... AD99: =RRP_1_V4_Sep25!AE129 -> 45930
A100: =RRP_2_V4_Oct25!B31 -> 70002 | B100: =RRP_2_V4_Oct25!C31 -> LB28DA | C100: =RRP_2_V4_Oct25!D31 -> 302 | D100: =RRP_2_V4_Oct25!E31 -> 102 | E100: =RRP_2_V4_Oct25!F31 -> ReverseRepo | F100: =RRP_2_V4_Oct25!G31 -> 45926 | G100: =RRP_2_V4_Oct25!H31 -> 45929 | H100: =RRP_2_V4_Oct25!I31 -> 47104 | ... T100: =RRP_2_V4_Oct25!U31 -> Fixed | V100: =RRP_2_V4_Oct25!W31 -> 0 | W100: =RRP_2_V4_Oct25!X31 -> Semi-Annual | X100: =RRP_2_V4_Oct25!Y31 -> 2.875 | Y100: =RRP_2_V4_Oct25!Z31 -> Actual/365 | Z100: =RRP_2_V4_Oct25!AA31 -> AAA | AA100: =RRP_2_V4_Oct25!AB31 -> AAA(tha) | AB100: =RRP_2_V4_Oct25!AC31 -> Matured | AC100: =RRP_2_V4_Oct25!AD31 -> 45961 | AD100: =RRP_2_V4_Oct25!AE31 -> 45961
A101: =Repo_1_V4_Sep25!B113 -> 70003 | B101: =Repo_1_V4_Sep25!C113 -> LB616A | C101: =Repo_1_V4_Sep25!D113 -> 301 | D101: =Repo_1_V4_Sep25!E113 -> 103 | E101: =Repo_1_V4_Sep25!F113 -> Repo | F101: =Repo_1_V4_Sep25!G113 -> 45922 | G101: =Repo_1_V4_Sep25!H113 -> 45924 | H101: =Repo_1_V4_Sep25!I113 -> 58983 | ... AD101: =Repo_1_V4_Sep25!AE113 -> 45930
A102: =Repo_2_V4_Oct25!B31 -> 70004 | B102: =Repo_2_V4_Oct25!C31 -> BOT25NA | C102: =Repo_2_V4_Oct25!D31 -> 402 | D102: =Repo_2_V4_Oct25!E31 -> 102 | E102: =Repo_2_V4_Oct25!F31 -> Repo | F102: =Repo_2_V4_Oct25!G31 -> 45924 | G102: =Repo_2_V4_Oct25!H31 -> 45926 | H102: =Repo_2_V4_Oct25!I31 -> 45933 | ... T102: =Repo_2_V4_Oct25!U31 -> Fixed | V102: =Repo_2_V4_Oct25!W31 -> 0 | W102: =Repo_2_V4_Oct25!X31 -> Semi-Annual | X102: =Repo_2_V4_Oct25!Y31 -> 2.58 | Y102: =Repo_2_V4_Oct25!Z31 -> Actual/365 | Z102: =Repo_2_V4_Oct25!AA31 -> AAA | AA102: =Repo_2_V4_Oct25!AB31 -> AAA(tha) | AB102: =Repo_2_V4_Oct25!AC31 -> Matured | AC102: =Repo_2_V4_Oct25!AD31 -> 45961.708 | AD102: =Repo_2_V4_Oct25!AE31 -> 45961
A103: ='Bond Buy-Sell_V4_Sep25 + Oct25'!A212 -> 90010 | B103: ='Bond Buy-Sell_V4_Sep25 + Oct25'!B212 -> EXIM266A | C103: ='Bond Buy-Sell_V4_Sep25 + Oct25'!C212 -> 403 | D103: ='Bond Buy-Sell_V4_Sep25 + Oct25'!D212 -> 101 | E103: ='Bond Buy-Sell_V4_Sep25 + Oct25'!E212 -> Buy | F103: ='Bond Buy-Sell_V4_Sep25 + Oct25'!F212 -> 45955 | G103: ='Bond Buy-Sell_V4_Sep25 + Oct25'!G212 -> 45959 | H103: ='Bond Buy-Sell_V4_Sep25 + Oct25'!H212 -> 46179 | ... AD103: ='Bond Buy-Sell_V4_Sep25 + Oct25'!AD212 -> 45961
A104: ='Bond sell_1_V4_Oct25'!B49 -> 90011 | B104: ='Bond sell_1_V4_Oct25'!C49 -> GSB26OA | C104: ='Bond sell_1_V4_Oct25'!D49 -> 403 | D104: ='Bond sell_1_V4_Oct25'!E49 -> 102 | E104: ='Bond sell_1_V4_Oct25'!F49 -> Sell | F104: ='Bond sell_1_V4_Oct25'!G49 -> 45950 | G104: ='Bond sell_1_V4_Oct25'!H49 -> 45952 | H104: ='Bond sell_1_V4_Oct25'!I49 -> 46311 | ... T104: ='Bond sell_1_V4_Oct25'!U49 -> Fixed | V104: ='Bond sell_1_V4_Oct25'!W49 -> 0 | W104: ='Bond sell_1_V4_Oct25'!X49 -> Semi-Annual | X104: ='Bond sell_1_V4_Oct25'!Y49 -> 1.69 | Y104: ='Bond sell_1_V4_Oct25'!Z49 -> Actual/365 | Z104: ='Bond sell_1_V4_Oct25'!AA49 -> AAA | AA104: ='Bond sell_1_V4_Oct25'!AB49 -> AAA(tha) | AB104: ='Bond sell_1_V4_Oct25'!AC49 -> Active | AC104: ='Bond sell_1_V4_Oct25'!AD49 -> 45952.458 | AD104: ='Bond sell_1_V4_Oct25'!AE49 -> 45961
A105: =RRP_3_V4_Nov25!B124 -> 70005 | B105: =RRP_3_V4_Nov25!C124 -> LB27DA | C105: =RRP_3_V4_Nov25!D124 -> 301 | D105: =RRP_3_V4_Nov25!E124 -> 102 | E105: =RRP_3_V4_Nov25!F124 -> ReverseRepo | F105: =RRP_3_V4_Nov25!G124 -> 45985.583 | G105: =RRP_3_V4_Nov25!H124 -> 45987 | H105: =RRP_3_V4_Nov25!I124 -> 45994 | ... AD105: =RRP_3_V4_Nov25!AE124 -> 45991
A106: =Repo_3_V4_Nov25!B119 -> 70006 | B106: =Repo_3_V4_Nov25!C119 -> LB616A | C106: =Repo_3_V4_Nov25!D119 -> 301 | D106: =Repo_3_V4_Nov25!E119 -> 102 | E106: =Repo_3_V4_Nov25!F119 -> Repo | F106: =Repo_3_V4_Nov25!G119 -> 45985.417 | G106: =Repo_3_V4_Nov25!H119 -> 45987 | H106: =Repo_3_V4_Nov25!I119 -> 45994 | ... AD106: =Repo_3_V4_Nov25!AE119 -> 45991
A109: ='V4_Result_30 Sep 2025'!A94 -> margin_calls
A110: {=TRANSPOSE('All Table_V4_Clean'!A302:A311)} -> margin_call_id | B110: counterparty_id | C110: repo_trade_id | D110: valuation_date | E110: call_currency | F110: call_type | G110: call_amount | H110: due_time | I110: status | J110: created_timestamp
A111: =RRP_1_V4_Sep25!B92 -> 1 | B111: =RRP_1_V4_Sep25!C92 -> 101 | C111: =RRP_1_V4_Sep25!D92 -> 70001 | D111: =RRP_1_V4_Sep25!E92 -> 45909 | E111: =RRP_1_V4_Sep25!F92 -> THB | F111: =RRP_1_V4_Sep25!G92 -> CALL | G111: =RRP_1_V4_Sep25!H92 -> 2100000 | H111: =RRP_1_V4_Sep25!I92 -> 45909.625 | ... J111: =RRP_1_V4_Sep25!K92 -> 45909.625
A112: =RRP_2_V4_Sep25!B92 -> 2 | B112: =RRP_2_V4_Sep25!C92 -> 102 | C112: =RRP_2_V4_Sep25!D92 -> 70002 | D112: =RRP_2_V4_Sep25!E92 -> 45930 | E112: =RRP_2_V4_Sep25!F92 -> THB | F112: =RRP_2_V4_Sep25!G92 -> CALL | G112: =RRP_2_V4_Sep25!H92 -> 5500000 | H112: =RRP_2_V4_Sep25!I92 -> 45930.625 | ... J112: =RRP_2_V4_Sep25!K92 -> 45930.625
A113: =Repo_2_V4_Sep25!B86 -> 3 | B113: =Repo_2_V4_Sep25!C86 -> 102 | C113: =Repo_2_V4_Sep25!D86 -> 70004 | D113: =Repo_2_V4_Sep25!E86 -> 45929 | E113: =Repo_2_V4_Sep25!F86 -> THB | F113: =Repo_2_V4_Sep25!G86 -> RETURN | G113: =Repo_2_V4_Sep25!H86 -> 600000 | H113: =Repo_2_V4_Sep25!I86 -> 45929.625 | ... J113: =Repo_2_V4_Sep25!K86 -> 45929.625
A116: ='V4_Result_30 Sep 2025'!A101 -> cash_margin_movements
A117: {=TRANSPOSE('All Table_V4_Clean'!A317:A334)} -> cash_margin_movement_id | B117: margin_call_id | C117: counterparty_id | D117: repo_trade_id | E117: call_currency | F117: movement_type | G117: amount | H117: outstanding_balance | I117: value_date | J117: created_timestamp | K117: bank_account_code | L117: daily_accrued_int_receivable | M117: accrued_int_receivable | N117: interest_on_margin_code | O117: interest_on_margin_rate | P117: day_count_basis | Q117: accrual_days | R117: interest_direction
A118: =RRP_1_V4_Sep25!B137 -> 1 | B118: =RRP_1_V4_Sep25!C137 -> 1 | C118: =RRP_1_V4_Sep25!D137 -> 101 | D118: =RRP_1_V4_Sep25!E137 -> 70001 | E118: =RRP_1_V4_Sep25!F137 -> THB | F118: =RRP_1_V4_Sep25!G137 -> RECEIVE | G118: =RRP_1_V4_Sep25!H137 -> 2100000 | H118: =RRP_1_V4_Sep25!I137 -> 2100000 | ... R118: =RRP_1_V4_Sep25!S137 -> NONE
A119: =RRP_1_V4_Sep25!B138 -> 2 | B119: =RRP_1_V4_Sep25!C138 -> 1 | C119: =RRP_1_V4_Sep25!D138 -> 101 | D119: =RRP_1_V4_Sep25!E138 -> 70001 | E119: =RRP_1_V4_Sep25!F138 -> THB | F119: =RRP_1_V4_Sep25!G138 -> PAY | G119: =RRP_1_V4_Sep25!H138 -> -2100000 | H119: =RRP_1_V4_Sep25!I138 -> 0 | ... R119: =RRP_1_V4_Sep25!S138 -> NONE
A120: =RRP_2_V4_Sep25!B143 -> 3 | B120: =RRP_2_V4_Sep25!C143 -> 2 | C120: =RRP_2_V4_Sep25!D143 -> 102 | D120: =RRP_2_V4_Sep25!E143 -> 70002 | E120: =RRP_2_V4_Sep25!F143 -> THB | F120: =RRP_2_V4_Sep25!G143 -> RECEIVE | G120: =RRP_2_V4_Sep25!H143 -> 5500000 | H120: =RRP_2_V4_Sep25!I143 -> 5500000 | ... R120: =RRP_2_V4_Sep25!S143 -> NONE
...

Sheet V4_Result_31 Dec 2025
A1: Export as of | B1: =DATE(2025,12,31) -> 46022 | D1: Timestamp update as of | E1: 46037.666
A3: ='V4_Result_30 Sep 2025'!A3 -> counterparty_master
A4: {=TRANSPOSE('All Table_V4_Clean'!A25:A39)} -> entity_id | B4: counterparty_id | C4: legal_name | D4: short_code | E4: counterparty_type | F4: bank_code | G4: swift_bic | H4: primary_credit_rating | I4: primary_rating_agency | J4: primary_rating_date | K4: created_date | L4: last_updated_date | M4: involved_party_type | N4: customer_code | O4: reside_in_thailand_flag
A5: =RRP_1_V4_Sep25!B13 -> BBL0107536000374 | B5: =RRP_1_V4_Sep25!C13 -> 101 | C5: =RRP_1_V4_Sep25!D13 -> BANGKOK BANK PCL | D5: =RRP_1_V4_Sep25!E13 -> BBL | E5: =RRP_1_V4_Sep25!F13 -> Commercial Bank | F5: =RRP_1_V4_Sep25!G13 -> 002 | G5: =RRP_1_V4_Sep25!H13 -> BKKBTHBK | H5: =RRP_1_V4_Sep25!I13 -> AA- | ... M5: =RRP_1_V4_Sep25!N13 -> 176039 | N5: 2008 | O5: TRUE
A6: =RRP_2_V4_Sep25!B13 -> KBANK0107536000315 | B6: =RRP_2_V4_Sep25!C13 -> 102 | C6: =RRP_2_V4_Sep25!D13 -> KASIKORNBANK PCL | D6: =RRP_2_V4_Sep25!E13 -> KBANK | E6: =RRP_2_V4_Sep25!F13 -> Commercial Bank | F6: =RRP_2_V4_Sep25!G13 -> 004 | G6: =RRP_2_V4_Sep25!H13 -> KASITHBK | H6: =RRP_2_V4_Sep25!I13 -> AA | ... M6: =RRP_2_V4_Sep25!N13 -> 176039 | N6: 2008 | O6: TRUE
A7: =Repo_1_V4_Sep25!B13 -> KTB107537000882 | B7: =Repo_1_V4_Sep25!C13 -> 103 | C7: =Repo_1_V4_Sep25!D13 -> KRUNGTHAI BANK PCL | D7: =Repo_1_V4_Sep25!E13 -> KTB | E7: =Repo_1_V4_Sep25!F13 -> Commercial Bank | F7: =Repo_1_V4_Sep25!G13 -> 006 | G7: =Repo_1_V4_Sep25!H13 -> KRTHTHBK | H7: =Repo_1_V4_Sep25!I13 -> AA+ | ... M7: =Repo_1_V4_Sep25!N13 -> 176039 | N7: 2008 | O7: TRUE
A8: ='IB Lend_V4_Oct25'!A12 -> CIMB0107537002338 | B8: ='IB Lend_V4_Oct25'!B12 -> 104 | C8: ='IB Lend_V4_Oct25'!C12 -> CIMB THAI BANK PCL | D8: ='IB Lend_V4_Oct25'!D12 -> CIMB | E8: ='IB Lend_V4_Oct25'!E12 -> Commercial Bank | F8: ='IB Lend_V4_Oct25'!F12 -> 022 | G8: ='IB Lend_V4_Oct25'!G12 -> UBOBTHBK | H8: ='IB Lend_V4_Oct25'!H12 -> AA(THA) | ... M8: ='IB Lend_V4_Oct25'!M12 -> 176039 | N8: 2008 | O8: TRUE
A9: ='IB Lend_V4_Oct25'!A11 -> SCB0107536000102 | B9: ='IB Lend_V4_Oct25'!B11 -> 113 | C9: ='IB Lend_V4_Oct25'!C11 -> SIAM COMMERCIAL BANK PCL | D9: ='IB Lend_V4_Oct25'!D11 -> SCB | E9: ='IB Lend_V4_Oct25'!E11 -> Commercial Bank | F9: ='IB Lend_V4_Oct25'!F11 -> 084 | G9: ='IB Lend_V4_Oct25'!G11 -> SICOTHBK | H9: ='IB Lend_V4_Oct25'!H11 -> AA+(THA) | ... M9: ='IB Lend_V4_Oct25'!M11 -> 176039 | N9: 2008 | O9: TRUE
A11: ='V4_Result_30 Sep 2025'!A10 -> security_master
A12: {=TRANSPOSE('All Table_V4_Clean'!A46:A68)} -> security_id | B12: isin | C12: issuer_id | D12: unique_id | E12: instrument_type | F12: issue_date | G12: maturity_date | H12: coupon_rate | I12: coupon_margin | J12: coupon_reference_rate | K12: coupon_frequency | L12: coupon_day_count_conv | M12: currency | N12: country | O12: bond_structure | P12: rating_tris | Q12: rating_fitch | R12: is_eligible_bot_repo_collateral | S12: is_eligible_crm_collateral | T12: status | U12: status_timestamp | V12: coupon_rate_type | W12: cross_default
A13: ='Bond buy_1_V4_Sep25'!B21 -> GSB26OA | B13: ='Bond buy_1_V4_Sep25'!C21 -> TH1029036A07 | C13: ='Bond buy_1_V4_Sep25'!D21 -> 3 | D13: ='Bond buy_1_V4_Sep25'!E21 -> 176017 | E13: ='Bond buy_1_V4_Sep25'!F21 -> SOE Bond | F13: ='Bond buy_1_V4_Sep25'!G21 -> 43754 | G13: ='Bond buy_1_V4_Sep25'!H21 -> 46311 | H13: ='Bond buy_1_V4_Sep25'!I21 -> 1.69 | ... V13: ='Bond buy_1_V4_Sep25'!W21 -> Fixed | W13: FALSE
A14: ='Bond buy_1_V4_Sep25'!B22 -> LB616A | B14: ='Bond buy_1_V4_Sep25'!C22 -> TH0623B3B607 | C14: ='Bond buy_1_V4_Sep25'!D22 -> 1 | D14: ='Bond buy_1_V4_Sep25'!E22 -> 176015 | E14: ='Bond buy_1_V4_Sep25'!F22 -> Gov Bond | F14: ='Bond buy_1_V4_Sep25'!G22 -> 40606 | G14: ='Bond buy_1_V4_Sep25'!H22 -> 58974 | H14: ='Bond buy_1_V4_Sep25'!I22 -> 4.85 | ... V14: ='Bond buy_1_V4_Sep25'!W22 -> Fixed | W14: FALSE
A15: ='Bond buy_1_V4_Sep25'!B23 -> TB26128A | B15: ='Bond buy_1_V4_Sep25'!C23 -> TH0623A76183 | C15: ='Bond buy_1_V4_Sep25'!D23 -> 1 | D15: ='Bond buy_1_V4_Sep25'!E23 -> 176015 | E15: ='Bond buy_1_V4_Sep25'!F23 -> T-Bill | F15: ='Bond buy_1_V4_Sep25'!G23 -> 45868 | G15: ='Bond buy_1_V4_Sep25'!H23 -> 46050 | H15: ='Bond buy_1_V4_Sep25'!I23 -> 0 | ... V15: ='Bond buy_1_V4_Sep25'!W23 -> Fixed | W15: FALSE
A16: ='Bond buy_1_V4_Sep25'!B24 -> BOT25NA | B16: ='Bond buy_1_V4_Sep25'!C24 -> TH0655035B00 | C16: ='Bond buy_1_V4_Sep25'!D24 -> 2 | D16: ='Bond buy_1_V4_Sep25'!E24 -> 001 | E16: ='Bond buy_1_V4_Sep25'!F24 -> BOT Bond | F16: ='Bond buy_1_V4_Sep25'!G24 -> 45236 | G16: ='Bond buy_1_V4_Sep25'!H24 -> 45967 | H16: ='Bond buy_1_V4_Sep25'!I24 -> 2.58 | ... V16: ='Bond buy_1_V4_Sep25'!W24 -> Fixed | W16: FALSE
A17: ='Bond buy_1_V4_Sep25'!B25 -> TB26211A | B17: ='Bond buy_1_V4_Sep25'!C25 -> TH0623076286 | C17: ='Bond buy_1_V4_Sep25'!D25 -> 1 | D17: ='Bond buy_1_V4_Sep25'!E25 -> 176015 | E17: ='Bond buy_1_V4_Sep25'!F25 -> T-Bill | F17: ='Bond buy_1_V4_Sep25'!G25 -> 45882 | G17: ='Bond buy_1_V4_Sep25'!H25 -> 46064 | H17: ='Bond buy_1_V4_Sep25'!I25 -> 0 | ... V17: ='Bond buy_1_V4_Sep25'!W25 -> Fixed | W17: FALSE
A18: ='Bond buy_1_V4_Sep25'!B26 -> BOTF267A | B18: ='Bond buy_1_V4_Sep25'!C26 -> TH0655036711 | C18: ='Bond buy_1_V4_Sep25'!D26 -> 2 | D18: ='Bond buy_1_V4_Sep25'!E26 -> 001 | E18: ='Bond buy_1_V4_Sep25'!F26 -> BOT Bond | F18: ='Bond buy_1_V4_Sep25'!G26 -> 45474 | G18: ='Bond buy_1_V4_Sep25'!H26 -> 46204 | H18: ='Bond buy_1_V4_Sep25'!I26 -> 1.68404 | ... V18: ='Bond buy_1_V4_Sep25'!W26 -> Floating | W18: FALSE
A19: =RRP_1_V4_Sep25!B19 -> LB29DA | B19: =RRP_1_V4_Sep25!C19 -> TH0623039C07 | C19: =RRP_1_V4_Sep25!D19 -> 1 | D19: =RRP_1_V4_Sep25!E19 -> 176015 | E19: =RRP_1_V4_Sep25!F19 -> Gov Bond | F19: =RRP_1_V4_Sep25!G19 -> 43784 | G19: =RRP_1_V4_Sep25!H19 -> 47469 | H19: =RRP_1_V4_Sep25!I19 -> 1.6 | ... V19: =RRP_1_V4_Sep25!W19 -> Fixed | W19: FALSE
A20: =RRP_2_V4_Sep25!B19 -> LB28DA | B20: =RRP_2_V4_Sep25!C19 -> TH0623038C09 | C20: =RRP_2_V4_Sep25!D19 -> 1 | D20: =RRP_2_V4_Sep25!E19 -> 176015 | E20: =RRP_2_V4_Sep25!F19 -> Gov Bond | F20: =RRP_2_V4_Sep25!G19 -> 43294 | G20: =RRP_2_V4_Sep25!H19 -> 47104 | H20: =RRP_2_V4_Sep25!I19 -> 2.875 | ... V20: =RRP_2_V4_Sep25!W19 -> Fixed | W20: FALSE
A21: ='Bond Buy-Sell_V4_Sep25 + Oct25'!A24 -> EXIM266A | B21: ='Bond Buy-Sell_V4_Sep25 + Oct25'!B24 -> TH0624036602 | C21: ='Bond Buy-Sell_V4_Sep25 + Oct25'!C24 -> 3 | D21: ='Bond Buy-Sell_V4_Sep25 + Oct25'!D24 -> 035 | E21: ='Bond Buy-Sell_V4_Sep25 + Oct25'!E24 -> SOE Bond | F21: ='Bond Buy-Sell_V4_Sep25 + Oct25'!F24 -> 45083 | G21: ='Bond Buy-Sell_V4_Sep25 + Oct25'!G24 -> 46179 | H21: ='Bond Buy-Sell_V4_Sep25 + Oct25'!H24 -> 2.71 | ... V21: ='Bond Buy-Sell_V4_Sep25 + Oct25'!V24 -> Fixed | W21: FALSE
A22: =RRP_3_V4_Nov25!B19 -> LB27DA | B22: =RRP_3_V4_Nov25!C19 -> TH0623037C05 | C22: =RRP_3_V4_Nov25!D19 -> 1 | D22: =RRP_3_V4_Nov25!E19 -> 176015 | E22: =RRP_3_V4_Nov25!F19 -> Gov Bond | F22: =RRP_3_V4_Nov25!G19 -> 40970 | G22: =RRP_3_V4_Nov25!H19 -> 46738 | H22: =RRP_3_V4_Nov25!I19 -> 3.58 | ... V22: =RRP_3_V4_Nov25!W19 -> Fixed | W22: FALSE
A23: =RRP_4_V4_Dec25!B19 -> LB284A | B23: =RRP_4_V4_Dec25!C19 -> TH0623038609 | C23: =RRP_4_V4_Dec25!D19 -> 1 | D23: =RRP_4_V4_Dec25!E19 -> 176015 | E23: =RRP_4_V4_Dec25!F19 -> Gov Bond | F23: =RRP_4_V4_Dec25!G19 -> 45674 | G23: =RRP_4_V4_Dec25!H19 -> 46860 | H23: =RRP_4_V4_Dec25!I19 -> 2.05 | ... V23: =RRP_4_V4_Dec25!W19 -> Fixed | W23: FALSE
A25: ='V4_Result_30 Sep 2025'!A22 -> portfolio_master | T25: =RRP_3_V4_Nov25!U22
A26: {=TRANSPOSE('All Table_V4_Clean'!A74:A78)} -> portfolio_id | B26: portfolio_name | C26: portfolio_manager | D26: accounting_treatment | E26: created_timestamp
A27: ='Bond buy_1_V4_Sep25'!B34 -> 301 | B27: ='Bond buy_1_V4_Sep25'!C34 -> AMC - Govt | C27: ='Bond buy_1_V4_Sep25'!D34 -> Treasury Desk | D27: ='Bond buy_1_V4_Sep25'!E34 -> AMC | E27: ='Bond buy_1_V4_Sep25'!F34 -> 45839
A28: ='Bond buy_1_V4_Sep25'!B35 -> 302 | B28: ='Bond buy_1_V4_Sep25'!C35 -> AMC - T-Bill | C28: ='Bond buy_1_V4_Sep25'!D35 -> Treasury Desk | D28: ='Bond buy_1_V4_Sep25'!E35 -> AMC | E28: ='Bond buy_1_V4_Sep25'!F35 -> 45839
A29: ='Bond buy_1_V4_Sep25'!B36 -> 303 | B29: ='Bond buy_1_V4_Sep25'!C36 -> AMC - BOT bond | C29: ='Bond buy_1_V4_Sep25'!D36 -> Treasury Desk | D29: ='Bond buy_1_V4_Sep25'!E36 -> AMC | E29: ='Bond buy_1_V4_Sep25'!F36 -> 45839
A30: ='Bond buy_1_V4_Sep25'!B37 -> 401 | B30: ='Bond buy_1_V4_Sep25'!C37 -> FVOCI - T-Bill | C30: ='Bond buy_1_V4_Sep25'!D37 -> Treasury Desk | D30: ='Bond buy_1_V4_Sep25'!E37 -> FVOCI | E30: ='Bond buy_1_V4_Sep25'!F37 -> 45839
A31: ='Bond buy_1_V4_Sep25'!B38 -> 402 | B31: ='Bond buy_1_V4_Sep25'!C38 -> FVOCI - BOT bond | C31: ='Bond buy_1_V4_Sep25'!D38 -> Treasury Desk | D31: ='Bond buy_1_V4_Sep25'!E38 -> FVOCI | E31: ='Bond buy_1_V4_Sep25'!F38 -> 45839
A32: ='Bond buy_1_V4_Sep25'!B39 -> 403 | B32: ='Bond buy_1_V4_Sep25'!C39 -> FVOCI - SOE | C32: ='Bond buy_1_V4_Sep25'!D39 -> Treasury Desk | D32: ='Bond buy_1_V4_Sep25'!E39 -> FVOCI | E32: ='Bond buy_1_V4_Sep25'!F39 -> 45839
A35: ='V4_Result_30 Sep 2025'!A32 -> netting_agreement
A36: {=TRANSPOSE('All Table_V4_Clean'!A84:A98)} -> netting_agreement_id | B36: counterparty_id | C36: netting_set_id | D36: agreement_type | E36: netting_type | F36: collateral_contract_type | G36: trade_date | H36: value_date | I36: maturity_date | J36: is_replacement | K36: replaced_agreement_id | L36: settlement_currency | M36: created_at | N36: updated_at | O36: agreement_status
A37: =RRP_1_V4_Sep25!B31 -> GMRA_2023_BB | B37: =RRP_1_V4_Sep25!C31 -> 101 | C37: =RRP_1_V4_Sep25!D31 -> 20001 | D37: =RRP_1_V4_Sep25!E31 -> GMRA | E37: =RRP_1_V4_Sep25!F31 -> COLLATERAL | F37: =RRP_1_V4_Sep25!G31 -> REP | G37: =RRP_1_V4_Sep25!H31 -> 45823 | H37: =RRP_1_V4_Sep25!I31 -> 45839 | ... O37: =RRP_1_V4_Sep25!P31 -> Active
A38: =RRP_2_V4_Sep25!B31 -> GMRA_2023_KB | B38: =RRP_2_V4_Sep25!C31 -> 102 | C38: =RRP_2_V4_Sep25!D31 -> 20002 | D38: =RRP_2_V4_Sep25!E31 -> GMRA | E38: =RRP_2_V4_Sep25!F31 -> COLLATERAL | F38: =RRP_2_V4_Sep25!G31 -> REP | G38: =RRP_2_V4_Sep25!H31 -> 45823 | H38: =RRP_2_V4_Sep25!I31 -> 45839 | ... O38: =RRP_2_V4_Sep25!P31 -> Active
A39: =Repo_1_V4_Sep25!B25 -> GMRA_2023_KT | B39: =Repo_1_V4_Sep25!C25 -> 103 | C39: =Repo_1_V4_Sep25!D25 -> 20003 | D39: =Repo_1_V4_Sep25!E25 -> GMRA | E39: =Repo_1_V4_Sep25!F25 -> COLLATERAL | F39: =Repo_1_V4_Sep25!G25 -> REP | G39: =Repo_1_V4_Sep25!H25 -> 45823 | H39: =Repo_1_V4_Sep25!I25 -> 45839 | ... O39: =Repo_1_V4_Sep25!P25 -> Active
A40: =Repo_2_V4_Sep25!B25 -> GMRA_2024_KB | B40: =Repo_2_V4_Sep25!C25 -> 102 | C40: =Repo_2_V4_Sep25!D25 -> 20004 | D40: =Repo_2_V4_Sep25!E25 -> GMRA | E40: =Repo_2_V4_Sep25!F25 -> COLLATERAL | F40: =Repo_2_V4_Sep25!G25 -> REP | G40: =Repo_2_V4_Sep25!H25 -> 45823 | H40: =Repo_2_V4_Sep25!I25 -> 45839 | ... O40: =Repo_2_V4_Sep25!P25 -> Active
A43: ='V4_Result_30 Sep 2025'!A40 -> limit_utilization
A44: {=TRANSPOSE('All Table_V4_Clean'!A340:A350)} -> limit_id | B44: counterparty_id | C44: limit_type | D44: currency | E44: available_line | F44: total_credit_line | G44: utilization_amount | H44: credit_line_approve_date | I44: timestamp | J44: created_date | K44: entity_id
A45: =RRP_4_V4_Dec25!B25 -> 1001 | B45: =RRP_4_V4_Dec25!C25 -> 101 | C45: =RRP_4_V4_Dec25!D25 -> REPO_LIMIT | D45: =RRP_4_V4_Dec25!E25 -> THB | E45: =RRP_4_V4_Dec25!F25 -> 900000000 | F45: =RRP_4_V4_Dec25!G25 -> 1000000000 | G45: =RRP_4_V4_Dec25!H25 -> 100000000 | H45: =RRP_4_V4_Dec25!I25 -> 45782 | ... K45: =RRP_4_V4_Dec25!L25 -> BBL0107536000374
A46: =RRP_3_V4_Nov25!B25 -> 1002 | B46: =RRP_3_V4_Nov25!C25 -> 102 | C46: =RRP_3_V4_Nov25!D25 -> REPO_LIMIT | D46: =RRP_3_V4_Nov25!E25 -> THB | E46: =RRP_3_V4_Nov25!F25 -> 1000000000 | F46: =RRP_3_V4_Nov25!G25 -> 1000000000 | G46: =RRP_3_V4_Nov25!H25 -> 300000000 | H46: =RRP_3_V4_Nov25!I25 -> 45782 | ... K46: =RRP_3_V4_Nov25!L25 -> KBANK0107536000315
A47: ='IB Lend_V4_Sep25'!A135 -> 2001 | B47: ='IB Lend_V4_Sep25'!B135 -> 101 | C47: ='IB Lend_V4_Sep25'!C135 -> PLACEMENT_LIMIT | D47: ='IB Lend_V4_Sep25'!D135 -> THB | E47: ='IB Lend_V4_Sep25'!E135 -> 500000000 | F47: ='IB Lend_V4_Sep25'!F135 -> 1000000000 | G47: ='IB Lend_V4_Sep25'!G135 -> 500000000 | H47: ='IB Lend_V4_Sep25'!H135 -> 45901 | ... K47: ='IB Lend_V4_Sep25'!K135 -> BBL0107536000374
A48: ='IB Lend_V4_Sep25'!A285 -> 2002 | B48: ='IB Lend_V4_Sep25'!B285 -> 104 | C48: ='IB Lend_V4_Sep25'!C285 -> PLACEMENT_LIMIT | D48: ='IB Lend_V4_Sep25'!D285 -> THB | E48: ='IB Lend_V4_Sep25'!E285 -> 500000000 | F48: ='IB Lend_V4_Sep25'!F285 -> 500000000 | G48: ='IB Lend_V4_Sep25'!G285 -> 0 | H48: ='IB Lend_V4_Sep25'!H285 -> 45828 | ... K48: ='IB Lend_V4_Sep25'!K285 -> CIMB0107537002338
A49: ='IB Lend_V4_Nov 25'!A136 -> 2003 | B49: ='IB Lend_V4_Nov 25'!B136 -> 113 | C49: ='IB Lend_V4_Nov 25'!C136 -> PLACEMENT_LIMIT | D49: ='IB Lend_V4_Nov 25'!D136 -> THB | E49: ='IB Lend_V4_Nov 25'!E136 -> 1000000000 | F49: ='IB Lend_V4_Nov 25'!F136 -> 1000000000 | G49: ='IB Lend_V4_Nov 25'!G136 -> 0 | H49: ='IB Lend_V4_Nov 25'!H136 -> 45931 | ... K49: ='IB Lend_V4_Nov 25'!K136 -> SCB0107536000102
A52: ='V4_Result_30 Sep 2025'!A48 -> repo_trades
A53: {=TRANSPOSE('All Table_V4_Clean'!A146:A171)} -> repo_trade_id | B53: trade_date | C53: trade_type | D53: counterparty_id | E53: netting_agreement_id | F53: netting_set_id | G53: nominal_amount | H53: purchase_date | I53: repurchase_date | J53: purchase_price | K53: repurchase_price | L53: currency | M53: reference_rate_id | N53: interest_rate_type | O53: interest_rate | P53: reference_rate | Q53: margin | R53: day_count_convention | S53: repo_rate | T53: term | U53: repo_out_flag | V53: repo_in_flag | W53: status | X53: limit_id | Y53: accrued_interest | Z53: entity_id
A54: =RRP_1_V4_Sep25!B123 -> 70001 | B54: =RRP_1_V4_Sep25!C123 -> 45905.583 | C54: =RRP_1_V4_Sep25!D123 -> Reverse REPO | D54: =RRP_1_V4_Sep25!E123 -> 101 | E54: =RRP_1_V4_Sep25!F123 -> GMRA_2023_BB | F54: =RRP_1_V4_Sep25!G123 -> 20001 | G54: =RRP_1_V4_Sep25!H123 -> 200000000 | H54: =RRP_1_V4_Sep25!I123 -> 45908 | ... Z54: =RRP_1_V4_Sep25!AA123 -> BBL0107536000374
A55: =RRP_2_V4_Oct25!B25 -> 70002 | B55: =RRP_2_V4_Oct25!C25 -> 45926.583 | C55: =RRP_2_V4_Oct25!D25 -> Reverse REPO | D55: =RRP_2_V4_Oct25!E25 -> 102 | E55: =RRP_2_V4_Oct25!F25 -> GMRA_2023_KB | F55: =RRP_2_V4_Oct25!G25 -> 20002 | G55: =RRP_2_V4_Oct25!H25 -> 300000000 | H55: =RRP_2_V4_Oct25!I25 -> 45929 | ... Y55: =RRP_2_V4_Oct25!Z25 -> 0 | Z55: =RRP_2_V4_Sep25!B13 -> KBANK0107536000315
A56: =Repo_1_V4_Sep25!B107 -> 70003 | B56: =Repo_1_V4_Sep25!C107 -> 45922.417 | C56: =Repo_1_V4_Sep25!D107 -> REPO | D56: =Repo_1_V4_Sep25!E107 -> 103 | E56: =Repo_1_V4_Sep25!F107 -> GMRA_2023_KT | F56: =Repo_1_V4_Sep25!G107 -> 20003 | G56: =Repo_1_V4_Sep25!H107 -> 50000000 | H56: =Repo_1_V4_Sep25!I107 -> 45924 | ... Z56: =Repo_1_V4_Sep25!AA107 -> KTB107537000882
A57: =Repo_2_V4_Oct25!B25 -> 70004 | B57: =Repo_2_V4_Oct25!C25 -> 45924.417 | C57: =Repo_2_V4_Oct25!D25 -> REPO | D57: =Repo_2_V4_Oct25!E25 -> 102 | E57: =Repo_2_V4_Oct25!F25 -> GMRA_2024_KB | F57: =Repo_2_V4_Oct25!G25 -> 20004 | G57: =Repo_2_V4_Oct25!H25 -> 30000000 | H57: =Repo_2_V4_Oct25!I25 -> 45926 | ... Y57: =Repo_2_V4_Oct25!Z25 -> 0 | Z57: =Z55 -> KBANK0107536000315
A58: =RRP_3_V4_Nov25!B118 -> 70005 | B58: =RRP_3_V4_Nov25!C118 -> 45985.583 | C58: =RRP_3_V4_Nov25!D118 -> Reverse REPO | D58: =RRP_3_V4_Nov25!E118 -> 102 | E58: =RRP_3_V4_Nov25!F118 -> GMRA_2023_KB | F58: =RRP_3_V4_Nov25!G118 -> 20002 | G58: =RRP_3_V4_Nov25!H118 -> 300000000 | H58: =RRP_3_V4_Nov25!I118 -> 45987 | ... V58: =RRP_3_V4_Nov25!W118 -> TRUE | W58: Matured | X58: =RRP_3_V4_Nov25!Y118 -> 1002 | Y58: 0 | Z58: =RRP_3_V4_Nov25!AA118 -> KBANK0107536000315
A59: =Repo_3_V4_Nov25!B113 -> 70006 | B59: =Repo_3_V4_Nov25!C113 -> 45985.417 | C59: =Repo_3_V4_Nov25!D113 -> REPO | D59: =Repo_3_V4_Nov25!E113 -> 102 | E59: =Repo_3_V4_Nov25!F113 -> GMRA_2024_KB | F59: =Repo_3_V4_Nov25!G113 -> 20004 | G59: =Repo_3_V4_Nov25!H113 -> 20000000 | H59: =Repo_3_V4_Nov25!I113 -> 45987 | ... V59: =Repo_3_V4_Nov25!W113 -> FALSE | W59: Matured | X59: =Repo_3_V4_Nov25!Y113 | Y59: 0 | Z59: =Repo_3_V4_Nov25!AA113 -> KBANK0107536000315
A60: =RRP_4_V4_Dec25!B119 -> 70007 | B60: =RRP_4_V4_Dec25!C119 -> 46015.583 | C60: =RRP_4_V4_Dec25!D119 -> Reverse REPO | D60: =RRP_4_V4_Dec25!E119 -> 101 | E60: =RRP_4_V4_Dec25!F119 -> GMRA_2023_BB | F60: =RRP_4_V4_Dec25!G119 -> 20001 | G60: =RRP_4_V4_Dec25!H119 -> 100000000 | H60: =RRP_4_V4_Dec25!I119 -> 46017 | ... Z60: =RRP_4_V4_Dec25!AA119 -> BBL0107536000374
A61: =Repo_4_V4_Dec25!B113 -> 70008 | B61: =Repo_4_V4_Dec25!C113 -> 46015.417 | C61: =Repo_4_V4_Dec25!D113 -> REPO | D61: =Repo_4_V4_Dec25!E113 -> 101 | E61: =Repo_4_V4_Dec25!F113 -> GMRA_2023_BB | F61: =Repo_4_V4_Dec25!G113 -> 20001 | G61: =Repo_4_V4_Dec25!H113 -> 50000000 | H61: =Repo_4_V4_Dec25!I113 -> 46017 | ... Z61: =Repo_4_V4_Dec25!AA113 -> BBL0107536000374
A63: ='V4_Result_30 Sep 2025'!A56 -> collateral_positions
A64: {=TRANSPOSE('All Table_V4_Clean'!A177:A187)} -> collateral_id | B64: repo_trade_id | C64: security_id | D64: nominal_amount | E64: allocation_date | F64: valuation_price | G64: market_value | H64: haircut_percentage | I64: collateral_value_after_haircut | J64: margin_call_id | K64: currency
A65: =RRP_1_V4_Sep25!B66 -> 70001_LB29DA_1 | B65: =RRP_1_V4_Sep25!C66 -> 70001 | C65: =RRP_1_V4_Sep25!D66 -> LB29DA | D65: =RRP_1_V4_Sep25!E66 -> 205000000 | E65: =RRP_1_V4_Sep25!F66 -> 45908 | F65: =RRP_1_V4_Sep25!G66 -> 99.85 | G65: =RRP_1_V4_Sep25!H66 -> 204692500 | H65: =RRP_1_V4_Sep25!I66 -> 2 | ... K65: =RRP_1_V4_Sep25!L66 -> THB
A66: =RRP_2_V4_Sep25!B66 -> 70002_LB28DA_1 | B66: =RRP_2_V4_Sep25!C66 -> 70002 | C66: =RRP_2_V4_Sep25!D66 -> LB28DA | D66: =RRP_2_V4_Sep25!E66 -> 305000000 | E66: =RRP_2_V4_Sep25!F66 -> 45929 | F66: =RRP_2_V4_Sep25!G66 -> 100.1 | G66: =RRP_2_V4_Sep25!H66 -> 305305000 | H66: =RRP_2_V4_Sep25!I66 -> 2 | ... K66: =RRP_2_V4_Sep25!L66 -> THB
A67: =Repo_1_V4_Sep25!B60 -> 70003_LB616A_1 | B67: =Repo_1_V4_Sep25!C60 -> 70003 | C67: =Repo_1_V4_Sep25!D60 -> LB616A | D67: =Repo_1_V4_Sep25!E60 -> 50000000 | E67: =Repo_1_V4_Sep25!F60 -> 45924 | F67: =Repo_1_V4_Sep25!G60 -> 170.81 | G67: =Repo_1_V4_Sep25!H60 -> 85405000 | H67: =Repo_1_V4_Sep25!I60 -> 2 | ... K67: =Repo_1_V4_Sep25!L60 -> THB
A68: =Repo_2_V4_Sep25!B60 -> 70004_BOT25NA_1 | B68: =Repo_2_V4_Sep25!C60 -> 70004 | C68: =Repo_2_V4_Sep25!D60 -> BOT25NA | D68: =Repo_2_V4_Sep25!E60 -> 30000000 | E68: =Repo_2_V4_Sep25!F60 -> 45926 | F68: =Repo_2_V4_Sep25!G60 -> 100.25761 | G68: =Repo_2_V4_Sep25!H60 -> 30078000 | H68: =Repo_2_V4_Sep25!I60 -> 2 | ... K68: =Repo_2_V4_Sep25!L60 -> THB
A69: =RRP_3_V4_Nov25!B66 -> 70005_LB27DA_1 | B69: =RRP_3_V4_Nov25!C66 -> 70005 | C69: =RRP_3_V4_Nov25!D66 -> LB27DA | D69: =RRP_3_V4_Nov25!E66 -> 305000000 | E69: =RRP_3_V4_Nov25!F66 -> 45987 | F69: =RRP_3_V4_Nov25!G66 -> 116.5 | G69: =RRP_3_V4_Nov25!H66 -> 355325000 | H69: =RRP_3_V4_Nov25!I66 -> 2 | ... K69: =RRP_3_V4_Nov25!L66 -> THB
A70: =Repo_3_V4_Nov25!B60 -> 70006_LB616A_1 | B70: =Repo_3_V4_Nov25!C60 -> 70006 | C70: =Repo_3_V4_Nov25!D60 -> LB616A | D70: =Repo_3_V4_Nov25!E60 -> 20000000 | E70: =Repo_3_V4_Nov25!F60 -> 45987 | F70: =Repo_3_V4_Nov25!G60 -> 156.78 | G70: =Repo_3_V4_Nov25!H60 -> 31356000 | H70: =Repo_3_V4_Nov25!I60 -> 2 | ... K70: =Repo_3_V4_Nov25!L60 -> THB
A71: =RRP_4_V4_Dec25!B66 -> 70007_LB284A_1 | B71: =RRP_4_V4_Dec25!C66 -> 70007 | C71: =RRP_4_V4_Dec25!D66 -> LB284A | D71: =RRP_4_V4_Dec25!E66 -> 105000000 | E71: =RRP_4_V4_Dec25!F66 -> 46017 | F71: =RRP_4_V4_Dec25!G66 -> 119.5336 | G71: =RRP_4_V4_Dec25!H66 -> 125510280 | H71: =RRP_4_V4_Dec25!I66 -> 2 | ... K71: =RRP_4_V4_Dec25!L66 -> THB
A72: =Repo_4_V4_Dec25!B60 -> 70008_LB616A_1 | B72: =Repo_4_V4_Dec25!C60 -> 70008 | C72: =Repo_4_V4_Dec25!D60 -> LB616A | D72: =Repo_4_V4_Dec25!E60 -> 50000000 | E72: =Repo_4_V4_Dec25!F60 -> 46017 | F72: =Repo_4_V4_Dec25!G60 -> 157.33 | G72: =Repo_4_V4_Dec25!H60 -> 78665000 | H72: =Repo_4_V4_Dec25!I60 -> 2 | ... K72: =Repo_4_V4_Dec25!L60 -> THB
A75: ='V4_Result_30 Sep 2025'!A64 -> bond_trades
A76: {=TRANSPOSE('All Table_V4_Clean'!A193:A203)} -> bond_trade_id | B76: portfolio_id | C76: trade_date | D76: settlement_date | E76: security_id | F76: counterparty_id | G76: trade_type | H76: nominal_amount | I76: clean_price_trade | J76: yield_to_maturity | K76: settlement_status
A77: ='Bond Buy-Sell_V4_Sep25 + Oct25'!A96 -> 90001 | B77: ='Bond Buy-Sell_V4_Sep25 + Oct25'!B96 -> 403 | C77: ='Bond Buy-Sell_V4_Sep25 + Oct25'!C96 -> 45659 | D77: ='Bond Buy-Sell_V4_Sep25 + Oct25'!D96 -> 45663 | E77: ='Bond Buy-Sell_V4_Sep25 + Oct25'!E96 -> EXIM266A | F77: ='Bond Buy-Sell_V4_Sep25 + Oct25'!F96 -> 101 | G77: ='Bond Buy-Sell_V4_Sep25 + Oct25'!G96 -> Buy | H77: ='Bond Buy-Sell_V4_Sep25 + Oct25'!H96 -> 100000000 | ... K77: ='Bond Buy-Sell_V4_Sep25 + Oct25'!K96 -> Settled
A78: ='Bond Buy-Sell_V4_Sep25 + Oct25'!A97 -> 90002 | B78: ='Bond Buy-Sell_V4_Sep25 + Oct25'!B97 -> 403 | C78: ='Bond Buy-Sell_V4_Sep25 + Oct25'!C97 -> 45726 | D78: ='Bond Buy-Sell_V4_Sep25 + Oct25'!D97 -> 45728 | E78: ='Bond Buy-Sell_V4_Sep25 + Oct25'!E97 -> EXIM266A | F78: ='Bond Buy-Sell_V4_Sep25 + Oct25'!F97 -> 101 | G78: ='Bond Buy-Sell_V4_Sep25 + Oct25'!G97 -> Buy | H78: ='Bond Buy-Sell_V4_Sep25 + Oct25'!H97 -> 50000000 | ... K78: ='Bond Buy-Sell_V4_Sep25 + Oct25'!K97 -> Settled
A79: ='Bond Buy-Sell_V4_Sep25 + Oct25'!A98 -> 90003 | B79: ='Bond Buy-Sell_V4_Sep25 + Oct25'!B98 -> 403 | C79: ='Bond Buy-Sell_V4_Sep25 + Oct25'!C98 -> 45915 | D79: ='Bond Buy-Sell_V4_Sep25 + Oct25'!D98 -> 45917 | E79: ='Bond Buy-Sell_V4_Sep25 + Oct25'!E98 -> EXIM266A | F79: ='Bond Buy-Sell_V4_Sep25 + Oct25'!F98 -> 101 | G79: ='Bond Buy-Sell_V4_Sep25 + Oct25'!G98 -> Sell | H79: ='Bond Buy-Sell_V4_Sep25 + Oct25'!H98 -> 100000000 | ... K79: ='Bond Buy-Sell_V4_Sep25 + Oct25'!K98 -> Settled
A80: ='Bond buy_1_V4_Sep25'!B65 -> 90004 | B80: ='Bond buy_1_V4_Sep25'!C65 -> 403 | C80: ='Bond buy_1_V4_Sep25'!D65 -> 45854.458 | D80: ='Bond buy_1_V4_Sep25'!E65 -> 45856.458 | E80: ='Bond buy_1_V4_Sep25'!F65 -> GSB26OA | F80: ='Bond buy_1_V4_Sep25'!G65 -> 102 | G80: ='Bond buy_1_V4_Sep25'!H65 -> Buy | H80: ='Bond buy_1_V4_Sep25'!I65 -> 100000000 | ... K80: ='Bond buy_1_V4_Sep25'!L65 -> Settled
A81: ='Bond buy_1_V4_Sep25'!B66 -> 90005 | B81: ='Bond buy_1_V4_Sep25'!C66 -> 301 | C81: ='Bond buy_1_V4_Sep25'!D66 -> 45917.458 | D81: ='Bond buy_1_V4_Sep25'!E66 -> 45919.458 | E81: ='Bond buy_1_V4_Sep25'!F66 -> LB616A | F81: ='Bond buy_1_V4_Sep25'!G66 -> 101 | G81: ='Bond buy_1_V4_Sep25'!H66 -> Buy | H81: ='Bond buy_1_V4_Sep25'!I66 -> 100000000 | ... K81: ='Bond buy_1_V4_Sep25'!L66 -> Settled
A82: ='Bond buy_1_V4_Sep25'!B67 -> 90006 | B82: ='Bond buy_1_V4_Sep25'!C67 -> 302 | C82: ='Bond buy_1_V4_Sep25'!D67 -> 45917.458 | D82: ='Bond buy_1_V4_Sep25'!E67 -> 45919.458 | E82: ='Bond buy_1_V4_Sep25'!F67 -> TB26128A | F82: ='Bond buy_1_V4_Sep25'!G67 -> 101 | G82: ='Bond buy_1_V4_Sep25'!H67 -> Buy | H82: ='Bond buy_1_V4_Sep25'!I67 -> 100000000 | ... K82: ='Bond buy_1_V4_Sep25'!L67 -> Settled
A83: ='Bond buy_1_V4_Sep25'!B68 -> 90007 | B83: ='Bond buy_1_V4_Sep25'!C68 -> 303 | C83: ='Bond buy_1_V4_Sep25'!D68 -> 45917.458 | D83: ='Bond buy_1_V4_Sep25'!E68 -> 45919.458 | E83: ='Bond buy_1_V4_Sep25'!F68 -> BOT25NA | F83: ='Bond buy_1_V4_Sep25'!G68 -> 101 | G83: ='Bond buy_1_V4_Sep25'!H68 -> Buy | H83: ='Bond buy_1_V4_Sep25'!I68 -> 100000000 | ... K83: ='Bond buy_1_V4_Sep25'!L68 -> Settled
A84: ='Bond buy_1_V4_Sep25'!B69 -> 90008 | B84: ='Bond buy_1_V4_Sep25'!C69 -> 401 | C84: ='Bond buy_1_V4_Sep25'!D69 -> 45917.458 | D84: ='Bond buy_1_V4_Sep25'!E69 -> 45919.458 | E84: ='Bond buy_1_V4_Sep25'!F69 -> TB26211A | F84: ='Bond buy_1_V4_Sep25'!G69 -> 102 | G84: ='Bond buy_1_V4_Sep25'!H69 -> Buy | H84: ='Bond buy_1_V4_Sep25'!I69 -> 100000000 | ... K84: ='Bond buy_1_V4_Sep25'!L69 -> Settled
A85: ='Bond buy_1_V4_Sep25'!B70 -> 90009 | B85: ='Bond buy_1_V4_Sep25'!C70 -> 402 | C85: ='Bond buy_1_V4_Sep25'!D70 -> 45917.458 | D85: ='Bond buy_1_V4_Sep25'!E70 -> 45919.458 | E85: ='Bond buy_1_V4_Sep25'!F70 -> BOTF267A | F85: ='Bond buy_1_V4_Sep25'!G70 -> 102 | G85: ='Bond buy_1_V4_Sep25'!H70 -> Buy | H85: ='Bond buy_1_V4_Sep25'!I70 -> 100000000 | ... K85: ='Bond buy_1_V4_Sep25'!L70 -> Settled
A86: ='Bond Buy-Sell_V4_Sep25 + Oct25'!A151 -> 90010 | B86: ='Bond Buy-Sell_V4_Sep25 + Oct25'!B151 -> 403 | C86: ='Bond Buy-Sell_V4_Sep25 + Oct25'!C151 -> 45955 | D86: ='Bond Buy-Sell_V4_Sep25 + Oct25'!D151 -> 45959 | E86: ='Bond Buy-Sell_V4_Sep25 + Oct25'!E151 -> EXIM266A | F86: ='Bond Buy-Sell_V4_Sep25 + Oct25'!F151 -> 101 | G86: ='Bond Buy-Sell_V4_Sep25 + Oct25'!G151 -> Buy | H86: ='Bond Buy-Sell_V4_Sep25 + Oct25'!H151 -> 100000000 | ... K86: ='Bond Buy-Sell_V4_Sep25 + Oct25'!K151 -> Settled
A87: ='Bond sell_1_V4_Oct25'!B31 -> 90011 | B87: ='Bond sell_1_V4_Oct25'!C31 -> 403 | C87: ='Bond sell_1_V4_Oct25'!D31 -> 45950.458 | D87: ='Bond sell_1_V4_Oct25'!E31 -> 45952.458 | E87: ='Bond sell_1_V4_Oct25'!F31 -> GSB26OA | F87: ='Bond sell_1_V4_Oct25'!G31 -> 102 | G87: ='Bond sell_1_V4_Oct25'!H31 -> Sell | H87: ='Bond sell_1_V4_Oct25'!I31 -> 50000000 | ... K87: ='Bond sell_1_V4_Oct25'!L31 -> Settled
A91: ='V4_Result_30 Sep 2025'!A77 -> bond_transactions
A92: {=TRANSPOSE('All Table_V4_Clean'!A209:A238)} -> trade_id | B92: security_id | C92: portfolio_id | D92: counterparty_id | E92: trade_type | F92: trade_date | G92: settlement_date | H92: maturity_date | I92: currency | J92: nominal_amount | K92: clean_price | L92: clean_price_trade | M92: accrued_interest | N92: dirty_price | O92: classification | P92: book_value | Q92: market_clean_value | R92: market_value | S92: last_coupon_date | T92: coupon_rate_type | U92: coupon_reference_rate | V92: coupon_margin | W92: coupon_frequency | X92: coupon_rate | Y92: coupon_day_count_conv | Z92: rating_tris | AA92: rating_fitch | AB92: status | AC92: last_updated_timestamp | AD92: valuation_date
A93: ='Bond Buy-Sell_V4_Sep25 + Oct25'!A209 -> 90001 | B93: ='Bond Buy-Sell_V4_Sep25 + Oct25'!B209 -> EXIM266A | C93: ='Bond Buy-Sell_V4_Sep25 + Oct25'!C209 -> 403 | D93: ='Bond Buy-Sell_V4_Sep25 + Oct25'!D209 -> 101 | E93: ='Bond Buy-Sell_V4_Sep25 + Oct25'!E209 -> Buy | F93: ='Bond Buy-Sell_V4_Sep25 + Oct25'!F209 -> 45659 | G93: ='Bond Buy-Sell_V4_Sep25 + Oct25'!G209 -> 45663 | H93: ='Bond Buy-Sell_V4_Sep25 + Oct25'!H209 -> 46179 | ... AD93: ='Bond Buy-Sell_V4_Sep25 + Oct25'!AD209 -> 45961
A94: ='Bond Buy-Sell_V4_Sep25 + Oct25'!A210 -> 90002 | B94: ='Bond Buy-Sell_V4_Sep25 + Oct25'!B210 -> EXIM266A | C94: ='Bond Buy-Sell_V4_Sep25 + Oct25'!C210 -> 403 | D94: ='Bond Buy-Sell_V4_Sep25 + Oct25'!D210 -> 101 | E94: ='Bond Buy-Sell_V4_Sep25 + Oct25'!E210 -> Buy | F94: ='Bond Buy-Sell_V4_Sep25 + Oct25'!F210 -> 45726 | G94: ='Bond Buy-Sell_V4_Sep25 + Oct25'!G210 -> 45728 | H94: ='Bond Buy-Sell_V4_Sep25 + Oct25'!H210 -> 46179 | ... AD94: ='Bond Buy-Sell_V4_Sep25 + Oct25'!AD210 -> 45961
A95: ='Bond Buy-Sell_V4_Sep25 + Oct25'!A211 -> 90003 | B95: ='Bond Buy-Sell_V4_Sep25 + Oct25'!B211 -> EXIM266A | C95: ='Bond Buy-Sell_V4_Sep25 + Oct25'!C211 -> 403 | D95: ='Bond Buy-Sell_V4_Sep25 + Oct25'!D211 -> 101 | E95: ='Bond Buy-Sell_V4_Sep25 + Oct25'!E211 -> Sell | F95: ='Bond Buy-Sell_V4_Sep25 + Oct25'!F211 -> 45915 | G95: ='Bond Buy-Sell_V4_Sep25 + Oct25'!G211 -> 45917 | H95: ='Bond Buy-Sell_V4_Sep25 + Oct25'!H211 -> 46179 | ... AD95: ='Bond Buy-Sell_V4_Sep25 + Oct25'!AD211 -> 45961
A96: ='Bond buy_1_V4_Oct25'!B78 -> 90004 | B96: ='Bond buy_1_V4_Oct25'!C78 -> GSB26OA | C96: ='Bond buy_1_V4_Oct25'!D78 -> 403 | D96: ='Bond buy_1_V4_Oct25'!E78 -> 102 | E96: ='Bond buy_1_V4_Oct25'!F78 -> Buy | F96: ='Bond buy_1_V4_Oct25'!G78 -> 45854 | G96: ='Bond buy_1_V4_Oct25'!H78 -> 45856 | H96: ='Bond buy_1_V4_Oct25'!I78 -> 46311 | ... T96: ='Bond buy_1_V4_Oct25'!U78 -> Fixed | V96: ='Bond buy_1_V4_Oct25'!W78 -> 0 | W96: ='Bond buy_1_V4_Oct25'!X78 -> Semi-Annual | X96: ='Bond buy_1_V4_Oct25'!Y78 -> 1.69 | Y96: ='Bond buy_1_V4_Oct25'!Z78 -> Actual/365 | Z96: ='Bond buy_1_V4_Oct25'!AA78 -> AAA | AA96: ='Bond buy_1_V4_Oct25'!AB78 -> AAA(tha) | AB96: ='Bond buy_1_V4_Oct25'!AC78 -> Active | AC96: ='Bond buy_1_V4_Oct25'!AD78 -> 45946.458 | AD96: ='Bond buy_1_V4_Oct25'!AE78 -> 45946
A97: ='Bond buy_1_V4_Oct25'!B79 -> 90005 | B97: ='Bond buy_1_V4_Oct25'!C79 -> LB616A | C97: ='Bond buy_1_V4_Oct25'!D79 -> 301 | D97: ='Bond buy_1_V4_Oct25'!E79 -> 101 | E97: ='Bond buy_1_V4_Oct25'!F79 -> Buy | F97: ='Bond buy_1_V4_Oct25'!G79 -> 45917 | G97: ='Bond buy_1_V4_Oct25'!H79 -> 45919 | H97: ='Bond buy_1_V4_Oct25'!I79 -> 58974 | ... T97: ='Bond buy_1_V4_Oct25'!U79 -> Fixed | V97: ='Bond buy_1_V4_Oct25'!W79 -> 0 | W97: ='Bond buy_1_V4_Oct25'!X79 -> Semi-Annual | X97: ='Bond buy_1_V4_Oct25'!Y79 -> 4.85 | Y97: ='Bond buy_1_V4_Oct25'!Z79 -> Actual/365 | Z97: ='Bond buy_1_V4_Oct25'!AA79 -> AAA | AA97: ='Bond buy_1_V4_Oct25'!AB79 -> AAA(tha) | AB97: ='Bond buy_1_V4_Oct25'!AC79 -> Active | AC97: ='Bond buy_1_V4_Oct25'!AD79 -> 45961.458 | AD97: ='Bond buy_1_V4_Oct25'!AE79 -> 45961
A98: ='Bond buy_1_V4_Oct25'!B80 -> 90006 | B98: ='Bond buy_1_V4_Oct25'!C80 -> TB26128A | C98: ='Bond buy_1_V4_Oct25'!D80 -> 302 | D98: ='Bond buy_1_V4_Oct25'!E80 -> 101 | E98: ='Bond buy_1_V4_Oct25'!F80 -> Buy | F98: ='Bond buy_1_V4_Oct25'!G80 -> 45917 | G98: ='Bond buy_1_V4_Oct25'!H80 -> 45919 | H98: ='Bond buy_1_V4_Oct25'!I80 -> 46050 | ... T98: ='Bond buy_1_V4_Oct25'!U80 -> Fixed | V98: ='Bond buy_1_V4_Oct25'!W80 -> 0 | W98: ='Bond buy_1_V4_Oct25'!X80 -> At Maturity | X98: ='Bond buy_1_V4_Oct25'!Y80 -> 0 | Y98: ='Bond buy_1_V4_Oct25'!Z80 -> Actual/365 | Z98: ='Bond buy_1_V4_Oct25'!AA80 -> AAA | AA98: ='Bond buy_1_V4_Oct25'!AB80 -> AAA(tha) | AB98: ='Bond buy_1_V4_Oct25'!AC80 -> Active | AC98: ='Bond buy_1_V4_Oct25'!AD80 -> 45961.458 | AD98: ='Bond buy_1_V4_Oct25'!AE80 -> 45961
A99: ='Bond buy_1_V4_Oct25'!B81 -> 90007 | B99: ='Bond buy_1_V4_Oct25'!C81 -> BOT25NA | C99: ='Bond buy_1_V4_Oct25'!D81 -> 303 | D99: ='Bond buy_1_V4_Oct25'!E81 -> 101 | E99: ='Bond buy_1_V4_Oct25'!F81 -> Buy | F99: ='Bond buy_1_V4_Oct25'!G81 -> 45917 | G99: ='Bond buy_1_V4_Oct25'!H81 -> 45919 | H99: ='Bond buy_1_V4_Oct25'!I81 -> 45967 | ... T99: ='Bond buy_1_V4_Oct25'!U81 -> Fixed | V99: ='Bond buy_1_V4_Oct25'!W81 -> 0 | W99: ='Bond buy_1_V4_Oct25'!X81 -> Semi-Annual | X99: ='Bond buy_1_V4_Oct25'!Y81 -> 2.58 | Y99: ='Bond buy_1_V4_Oct25'!Z81 -> Actual/365 | Z99: ='Bond buy_1_V4_Oct25'!AA81 -> AAA | AA99: ='Bond buy_1_V4_Oct25'!AB81 -> AAA(tha) | AB99: ='Bond buy_1_V4_Oct25'!AC81 -> Active | AC99: ='Bond buy_1_V4_Oct25'!AD81 -> 45961.458 | AD99: ='Bond buy_1_V4_Oct25'!AE81 -> 45961
A100: ='Bond buy_1_V4_Oct25'!B82 -> 90008 | B100: ='Bond buy_1_V4_Oct25'!C82 -> TB26211A | C100: ='Bond buy_1_V4_Oct25'!D82 -> 401 | D100: ='Bond buy_1_V4_Oct25'!E82 -> 102 | E100: ='Bond buy_1_V4_Oct25'!F82 -> Buy | F100: ='Bond buy_1_V4_Oct25'!G82 -> 45917 | G100: ='Bond buy_1_V4_Oct25'!H82 -> 45919 | H100: ='Bond buy_1_V4_Oct25'!I82 -> 46064 | ... T100: ='Bond buy_1_V4_Oct25'!U82 -> Fixed | V100: ='Bond buy_1_V4_Oct25'!W82 -> 0 | W100: ='Bond buy_1_V4_Oct25'!X82 -> At Maturity | X100: ='Bond buy_1_V4_Oct25'!Y82 -> 0 | Y100: ='Bond buy_1_V4_Oct25'!Z82 -> Actual/365 | Z100: ='Bond buy_1_V4_Oct25'!AA82 -> AAA | AA100: ='Bond buy_1_V4_Oct25'!AB82 -> AAA(tha) | AB100: ='Bond buy_1_V4_Oct25'!AC82 -> Active | AC100: ='Bond buy_1_V4_Oct25'!AD82 -> 45961.458 | AD100: ='Bond buy_1_V4_Oct25'!AE82 -> 45961
A101: ='Bond buy_1_V4_Oct25'!B83 -> 90009 | B101: ='Bond buy_1_V4_Oct25'!C83 -> BOTF267A | C101: ='Bond buy_1_V4_Oct25'!D83 -> 402 | D101: ='Bond buy_1_V4_Oct25'!E83 -> 102 | E101: ='Bond buy_1_V4_Oct25'!F83 -> Buy | F101: ='Bond buy_1_V4_Oct25'!G83 -> 45917 | G101: ='Bond buy_1_V4_Oct25'!H83 -> 45919 | H101: ='Bond buy_1_V4_Oct25'!I83 -> 46204 | ... T101: ='Bond buy_1_V4_Oct25'!U83 -> Floating | V101: ='Bond buy_1_V4_Oct25'!W83 -> 0.05 | W101: ='Bond buy_1_V4_Oct25'!X83 -> Quarterly | X101: ='Bond buy_1_V4_Oct25'!Y83 -> 1.68404 | Y101: ='Bond buy_1_V4_Oct25'!Z83 -> Actual/365 | Z101: ='Bond buy_1_V4_Oct25'!AA83 -> AAA | AA101: ='Bond buy_1_V4_Oct25'!AB83 -> AAA(tha) | AB101: ='Bond buy_1_V4_Oct25'!AC83 -> Active | AC101: ='Bond buy_1_V4_Oct25'!AD83 -> 45961.458 | AD101: ='Bond buy_1_V4_Oct25'!AE83 -> 45961
A102: =RRP_1_V4_Sep25!B129 -> 70001 | B102: =RRP_1_V4_Sep25!C129 -> LB29DA | C102: =RRP_1_V4_Sep25!D129 -> 301 | D102: =RRP_1_V4_Sep25!E129 -> 101 | E102: =RRP_1_V4_Sep25!F129 -> ReverseRepo | F102: =RRP_1_V4_Sep25!G129 -> 45905 | G102: =RRP_1_V4_Sep25!H129 -> 45908 | H102: =RRP_1_V4_Sep25!I129 -> 45915 | ... AD102: =RRP_1_V4_Sep25!AE129 -> 45930
A103: =RRP_2_V4_Oct25!B31 -> 70002 | B103: =RRP_2_V4_Oct25!C31 -> LB28DA | C103: =RRP_2_V4_Oct25!D31 -> 302 | D103: =RRP_2_V4_Oct25!E31 -> 102 | E103: =RRP_2_V4_Oct25!F31 -> ReverseRepo | F103: =RRP_2_V4_Oct25!G31 -> 45926 | G103: =RRP_2_V4_Oct25!H31 -> 45929 | H103: =RRP_2_V4_Oct25!I31 -> 47104 | ... T103: =RRP_2_V4_Oct25!U31 -> Fixed | V103: =RRP_2_V4_Oct25!W31 -> 0 | W103: =RRP_2_V4_Oct25!X31 -> Semi-Annual | X103: =RRP_2_V4_Oct25!Y31 -> 2.875 | Y103: =RRP_2_V4_Oct25!Z31 -> Actual/365 | Z103: =RRP_2_V4_Oct25!AA31 -> AAA | AA103: =RRP_2_V4_Oct25!AB31 -> AAA(tha) | AB103: =RRP_2_V4_Oct25!AC31 -> Matured | AC103: =RRP_2_V4_Oct25!AD31 -> 45961 | AD103: =RRP_2_V4_Oct25!AE31 -> 45961
A104: =Repo_1_V4_Sep25!B113 -> 70003 | B104: =Repo_1_V4_Sep25!C113 -> LB616A | C104: =Repo_1_V4_Sep25!D113 -> 301 | D104: =Repo_1_V4_Sep25!E113 -> 103 | E104: =Repo_1_V4_Sep25!F113 -> Repo | F104: =Repo_1_V4_Sep25!G113 -> 45922 | G104: =Repo_1_V4_Sep25!H113 -> 45924 | H104: =Repo_1_V4_Sep25!I113 -> 58983 | ... AD104: =Repo_1_V4_Sep25!AE113 -> 45930
A105: =Repo_2_V4_Oct25!B31 -> 70004 | B105: =Repo_2_V4_Oct25!C31 -> BOT25NA | C105: =Repo_2_V4_Oct25!D31 -> 402 | D105: =Repo_2_V4_Oct25!E31 -> 102 | E105: =Repo_2_V4_Oct25!F31 -> Repo | F105: =Repo_2_V4_Oct25!G31 -> 45924 | G105: =Repo_2_V4_Oct25!H31 -> 45926 | H105: =Repo_2_V4_Oct25!I31 -> 45933 | ... T105: =Repo_2_V4_Oct25!U31 -> Fixed | V105: =Repo_2_V4_Oct25!W31 -> 0 | W105: =Repo_2_V4_Oct25!X31 -> Semi-Annual | X105: =Repo_2_V4_Oct25!Y31 -> 2.58 | Y105: =Repo_2_V4_Oct25!Z31 -> Actual/365 | Z105: =Repo_2_V4_Oct25!AA31 -> AAA | AA105: =Repo_2_V4_Oct25!AB31 -> AAA(tha) | AB105: =Repo_2_V4_Oct25!AC31 -> Matured | AC105: =Repo_2_V4_Oct25!AD31 -> 45961.708 | AD105: =Repo_2_V4_Oct25!AE31 -> 45961
A106: ='Bond Buy-Sell_V4_Sep25 + Oct25'!A212 -> 90010 | B106: ='Bond Buy-Sell_V4_Sep25 + Oct25'!B212 -> EXIM266A | C106: ='Bond Buy-Sell_V4_Sep25 + Oct25'!C212 -> 403 | D106: ='Bond Buy-Sell_V4_Sep25 + Oct25'!D212 -> 101 | E106: ='Bond Buy-Sell_V4_Sep25 + Oct25'!E212 -> Buy | F106: ='Bond Buy-Sell_V4_Sep25 + Oct25'!F212 -> 45955 | G106: ='Bond Buy-Sell_V4_Sep25 + Oct25'!G212 -> 45959 | H106: ='Bond Buy-Sell_V4_Sep25 + Oct25'!H212 -> 46179 | ... AD106: ='Bond Buy-Sell_V4_Sep25 + Oct25'!AD212 -> 45961
A107: ='Bond sell_1_V4_Oct25'!B49 -> 90011 | B107: ='Bond sell_1_V4_Oct25'!C49 -> GSB26OA | C107: ='Bond sell_1_V4_Oct25'!D49 -> 403 | D107: ='Bond sell_1_V4_Oct25'!E49 -> 102 | E107: ='Bond sell_1_V4_Oct25'!F49 -> Sell | F107: ='Bond sell_1_V4_Oct25'!G49 -> 45950 | G107: ='Bond sell_1_V4_Oct25'!H49 -> 45952 | H107: ='Bond sell_1_V4_Oct25'!I49 -> 46311 | ... T107: ='Bond sell_1_V4_Oct25'!U49 -> Fixed | V107: ='Bond sell_1_V4_Oct25'!W49 -> 0 | W107: ='Bond sell_1_V4_Oct25'!X49 -> Semi-Annual | X107: ='Bond sell_1_V4_Oct25'!Y49 -> 1.69 | Y107: ='Bond sell_1_V4_Oct25'!Z49 -> Actual/365 | Z107: ='Bond sell_1_V4_Oct25'!AA49 -> AAA | AA107: ='Bond sell_1_V4_Oct25'!AB49 -> AAA(tha) | AB107: ='Bond sell_1_V4_Oct25'!AC49 -> Active | AC107: ='Bond sell_1_V4_Oct25'!AD49 -> 45952.458 | AD107: ='Bond sell_1_V4_Oct25'!AE49 -> 45961
A108: =RRP_3_V4_Nov25!B124 -> 70005 | B108: =RRP_3_V4_Nov25!C124 -> LB27DA | C108: =RRP_3_V4_Nov25!D124 -> 301 | D108: =RRP_3_V4_Nov25!E124 -> 102 | E108: =RRP_3_V4_Nov25!F124 -> ReverseRepo | F108: =RRP_3_V4_Nov25!G124 -> 45985.583 | G108: =RRP_3_V4_Nov25!H124 -> 45987 | H108: =RRP_3_V4_Nov25!I124 -> 45994 | ... AD108: =RRP_3_V4_Nov25!AE124 -> 45991
A109: =Repo_3_V4_Nov25!B119 -> 70006 | B109: =Repo_3_V4_Nov25!C119 -> LB616A | C109: =Repo_3_V4_Nov25!D119 -> 301 | D109: =Repo_3_V4_Nov25!E119 -> 102 | E109: =Repo_3_V4_Nov25!F119 -> Repo | F109: =Repo_3_V4_Nov25!G119 -> 45985.417 | G109: =Repo_3_V4_Nov25!H119 -> 45987 | H109: =Repo_3_V4_Nov25!I119 -> 45994 | ... AD109: =Repo_3_V4_Nov25!AE119 -> 45991
A110: =RRP_4_V4_Dec25!B125 -> 70007 | B110: =RRP_4_V4_Dec25!C125 -> LB284A | C110: =RRP_4_V4_Dec25!D125 -> 301 | D110: =RRP_4_V4_Dec25!E125 -> 101 | E110: =RRP_4_V4_Dec25!F125 -> ReverseRepo | F110: =RRP_4_V4_Dec25!G125 -> 46015.583 | G110: =RRP_4_V4_Dec25!H125 -> 46017 | H110: =RRP_4_V4_Dec25!I125 -> 46031 | ... AD110: =RRP_4_V4_Dec25!AE125 -> 46022
A111: =Repo_4_V4_Dec25!B119 -> 70008 | B111: =Repo_4_V4_Dec25!C119 -> LB616A | C111: =Repo_4_V4_Dec25!D119 -> 301 | D111: =Repo_4_V4_Dec25!E119 -> 102 | E111: =Repo_4_V4_Dec25!F119 -> Repo | F111: =Repo_4_V4_Dec25!G119 -> 46015.417 | G111: =Repo_4_V4_Dec25!H119 -> 46017 | H111: =Repo_4_V4_Dec25!I119 -> 46031 | ... AD111: =Repo_4_V4_Dec25!AE119 -> 46022
A112: ='Bond position_1_V4_Dec 25'!B60 -> 80001 | B112: ='Bond position_1_V4_Dec 25'!C60 -> EXIM266A | C112: ='Bond position_1_V4_Dec 25'!D60 -> 403 | D112: ='Bond position_1_V4_Dec 25'!E60 -> 101 | E112: ='Bond position_1_V4_Dec 25'!F60 -> Coupon | F112: ='Bond position_1_V4_Dec 25'!G60 -> 45999 | G112: ='Bond position_1_V4_Dec 25'!H60 -> 45999 | H112: ='Bond position_1_V4_Dec 25'!I60 -> 45999 | ... AD112: ='Bond position_1_V4_Dec 25'!AE60 -> 45999
A113: ='Bond position_1_V4_Dec 25'!B61 -> 80002 | B113: ='Bond position_1_V4_Dec 25'!C61 -> LB616A | C113: ='Bond position_1_V4_Dec 25'!D61 -> 301 | D113: ='Bond position_1_V4_Dec 25'!E61 -> 101 | E113: ='Bond position_1_V4_Dec 25'!F61 -> Coupon | F113: ='Bond position_1_V4_Dec 25'!G61 -> 46008 | G113: ='Bond position_1_V4_Dec 25'!H61 -> 46008 | H113: ='Bond position_1_V4_Dec 25'!I61 -> 46008 | ... AD113: ='Bond position_1_V4_Dec 25'!AE61 -> 46008
A118: ='V4_Result_30 Sep 2025'!A94 -> margin_calls
A119: {=TRANSPOSE('All Table_V4_Clean'!A302:A311)} -> margin_call_id | B119: counterparty_id | C119: repo_trade_id | D119: valuation_date | E119: call_currency | F119: call_type | G119: call_amount | H119: due_time | I119: status | J119: created_timestamp
...

Sheet Detail mock cases >>

Sheet Bond_coupon_rec_event_31 Oct 20
A1: Export as of | B1: =DATE(2025,10,31) -> 45961
A3: bond_trades
A4: bond_trade_id | B4: portfolio_id | C4: trade_date | D4: settlement_date | E4: security_id | F4: counterparty_id | G4: trade_type | H4: nominal_amount | I4: clean_price_trade | J4: yield_to_maturity | K4: settlement_status
A5: VARCHAR(40) | B5: VARCHAR(40) | C5: DATE | D5: DATE | E5: VARCHAR(10) | F5: VARCHAR(40) | G5: VARCHAR(10) | H5: DECIMAL(20,2) | I5: DECIMAL(18,6) | J5: DECIMAL(10,6) | K5: VARCHAR(20)
A6: 90004 | B6: 403 | C6: 45854 | D6: 45856 | E6: GSB26OA | F6: 102 | G6: Buy | H6: 100000000 | I6: 100.26487 | J6: 1.46 | K6: Settled
A7: 90009 | B7: 402 | C7: 45917 | D7: 45919 | E7: BOTF267A | F7: 102 | G7: Buy | H7: 100000000 | I7: 100.02849 | J7: 1.52 | K7: Settled
A9: bond_transactions
A10: trade_id | B10: security_id | C10: portfolio_id | D10: counterparty_id | E10: trade_type | F10: trade_date | G10: settlement_date | H10: maturity_date | I10: currency | J10: nominal_amount | K10: clean_price | L10: clean_price_trade | M10: accrued_interest | N10: dirty_price | O10: classification | P10: book_value | Q10: market_clean_value | R10: market_value | S10: last_coupon_date | T10: coupon_rate_type | U10: coupon_reference_rate | V10: coupon_margin | W10: coupon_frequency | X10: coupon_rate | Y10: coupon_day_count_conv | Z10: rating_tris | AA10: rating_fitch | AB10: status | AC10: last_updated_timestamp | AD10: valuation_date
A11: VARCHAR(40) | B11: VARCHAR(10) | C11: VARCHAR(40) | D11: VARCHAR(40) | E11: VARCHAR(10) | F11: DATE | G11: DATE | H11: DATE | I11: VARCHAR(3) | J11: DECIMAL(20,2) | K11: DECIMAL(18,6) | L11: DECIMAL(18,6) | M11: DECIMAL(20,2) | N11: DECIMAL(20,2) | O11: VARCHAR(10) | P11: DECIMAL(20,2) | Q11: DECIMAL(20,2) | R11: DECIMAL(20,2) | S11: DATE | T11: VARCHAR(10) | U11: VARCHAR(20) | V11: DECIMAL(10,6) | W11: VARCHAR(20) | X11: DECIMAL(10,6) | Y11: VARCHAR(20) | Z11: VARCHAR(8) | AA11: VARCHAR(8) | AB11: VARCHAR(20) | AC11: DATETIME | AD11: DATE
A12: 90004 | B12: GSB26OA | C12: 403 | D12: 102 | E12: Buy | F12: 45854 | G12: 45856 | H12: 46311 | I12: THB | J12: 100000000 | K12: 100.03 | L12: 100.26487 | M12: 773232.88 | N12: 100.80323 | O12: FVOCI | P12: 100264871 | Q12: 100030000 | R12: 1.0080323e+08 | S12: 45763 | T12: Fixed | V12: 0 | W12: Semi-Annual | X12: 1.69 | Y12: Actual/365 | Z12: AAA | AA12: AAA(tha) | AB12: Active | AC12: 45930.458 | AD12: 45930
A13: 60001 | B13: GSB26OA | C13: 403 | D13: 102 | E13: Coupon | F13: 45946 | G13: 45946 | H13: 45946 | I13: THB | J13: 100000000 | M13: =0.847313%*J13 -> 847313 | O13: FVOCI | P13: 0 | Q13: 0 | R13: 0 | S13: 45946 | T13: Fixed | V13: 0 | W13: Semi-Annual | X13: 1.69 | Y13: Actual/365 | Z13: AAA | AA13: AAA(tha) | AB13: Active | AC13: 45946.458 | AD13: 45946
A14: 60002 | B14: BOTF267A | C14: 402 | D14: 102 | E14: Coupon | F14: 45931 | G14: 45931 | H14: 45931 | I14: THB | J14: 100000000 | M14: =0.390393%*J14 -> 390393 | O14: FVOCI | P14: 0 | Q14: 0 | R14: 0 | S14: 45931 | T14: Floating | U14: Compounded THOR | V14: 0.05 | W14: Quarterly | X14: 1.68404 | Y14: Actual/365 | Z14: AAA | AA14: AAA(tha) | AB14: Active | AC14: 45931.458 | AD14: 45931
